Workbook

Sheet label_inventory
A1: (Child) ASIN | B1: Brand | C1: Product | D1: Size | E1: label_inventory
A2: B0BRTJGR33 | B2: TPS Plant Foods | C2: Fiddle Leaf Fig Plant Food for All Fig and Other Ficus Trees, Liquid Houseplant Fertilizer 8 oz (250mL) | D2: 8oz | E2: {=XLOOKUP(A2, production_planning!L:L, production_planning!AI:AI, "")} -> 3134
A3: B0BRTKV4TC | B3: TPS Plant Foods | C3: Liquid Plant Food for use in AeroGarden, IDOO and Hydroponic Growing Systems, Liquid Fertilizer 8 oz (250mL) | D3: 8oz | E3: {=XLOOKUP(A3, production_planning!L:L, production_planning!AI:AI, "")} -> 9627
A4: B0BRTK1P8Z | B4: TPS Plant Foods | C4: Monstera Plant Food for Monsteras and Philodendrons, Tropical Houseplant Liquid Fertilizer 8 oz (250mL) | D4: 8oz | E4: {=XLOOKUP(A4, production_planning!L:L, production_planning!AI:AI, "")} -> 5550
A5: B0C73SNJCH | B5: TPS Plant Foods | C5: Lemon Tree Fertilizer, Complete Lemon Tree Plant Food, 8 oz (250mL) | D5: 8oz | E5: {=XLOOKUP(A5, production_planning!L:L, production_planning!AI:AI, "")} -> 9073
A6: B0BRTJB518 | B6: TPS Plant Foods | C6: Indoor Plant Food, Liquid Fertilizer for Healthy Growth & Vibrant Foliage in Houseplants, by TPS Plant Foods, 8 oz (250 mL) | D6: 8oz | E6: {=XLOOKUP(A6, production_planning!L:L, production_planning!AI:AI, "")} -> 8191
A7: B0BRTJBFP7 | B7: TPS Plant Foods | C7: Orchid Plant Food for All Orchids and Acid Loving Houseplants, Promotes Growth and Blooms, Liquid Fertilizer 8 oz (250mL) | D7: 8oz | E7: {=XLOOKUP(A7, production_planning!L:L, production_planning!AI:AI, "")} -> 5979
A8: B07CX36LW8 | B8: TPS Nutrients | C8: TPS NUTRIENTS Silica Gold Plant Strength Nutrient and Supplement with Bioavailable Silicon 1 Quart (32 oz) | D8: Quart | E8: {=XLOOKUP(A8, production_planning!L:L, production_planning!AI:AI, "")} -> 4459
A9: B0C73TCVFW | B9: TPS Plant Foods | C9: Lemon Tree Fertilizer for Lemon Trees and Citrus, Liquid Plant Food, 32 oz (1 Quart) | D9: Quart | E9: {=XLOOKUP(A9, production_planning!L:L, production_planning!AI:AI, "")} -> 2970
A10: B0BRTJ4PLB | B10: TPS Plant Foods | C10: Succulent Plant Food for Succulents, Cactus, Jade and Aloe, Liquid Houseplant Fertilizer 8 oz (250mL) | D10: 8oz | E10: {=XLOOKUP(A10, production_planning!L:L, production_planning!AI:AI, "")} -> 1567
A11: B0C73S6Q23 | B11: TPS Plant Foods | C11: Citrus Fertilizer for All Citrus and Fruiting Trees, Liquid Plant Food 8 oz (250mL) | D11: 8oz | E11: {=XLOOKUP(A11, production_planning!L:L, production_planning!AI:AI, "")} -> 7337
A12: B09P2JPHZ6 | B12: TPS Nutrients | C12: TPS NUTRIENTS Billions Concentrated Microbial Root Enhancer, 100% Water-Soluble with Mycorrhizae, Bacteria and Trichoderma, 8 oz (1/2 Pound) | D12: 1/2lb | E12: {=XLOOKUP(A12, production_planning!L:L, production_planning!AI:AI, "")} -> 0
A13: B07CWQNYYC | B13: TPS Nutrients | C13: TPS NUTRIENTS Organic Cal-Mag OAC Plant Nutrient and Supplement, Plus Iron and Micronutrients 1 Quart (32 oz) | D13: Quart | E13: {=XLOOKUP(A13, production_planning!L:L, production_planning!AI:AI, "")} -> 987
... A23: B0C6R56WK1 | B23: TPS Plant Foods | C23: Bonsai Fertilizer, Liquid Plant Food for Healthy Growth & Strong Roots in All Bonsai Trees, by TPS Plant Foods, 8 oz (250 mL) | D23: 8oz | E23: {=XLOOKUP(A23, production_planning!L:L, production_planning!AI:AI, "")} -> 4551
A24: B097F8WJ3H | C24: Silica Gold Plant Strength Nutrient and Supplement with Bioavailable Silicon by TPS Nutrients, 1 Pint (16 oz) | E24: {=XLOOKUP(A24, production_planning!L:L, production_planning!AI:AI, "")}
A25: B097FF39YJ | C25: Signal Terpene Enhancer Plant Nutrient and Supplement, Flower Hardener and Increases Flavor by TPS Nutrients, 1 Pint (16 oz) | E25: {=XLOOKUP(A25, production_planning!L:L, production_planning!AI:AI, "")}
A26: B0C6R6KYGM | B26: TPS Plant Foods | C26: TPS NUTRIENTS Cactus Fertilizer for Cacti and All Desert Plants, Liquid Plant Food 8 oz (250mL) | D26: 8oz | E26: {=XLOOKUP(A26, production_planning!L:L, production_planning!AI:AI, "")} -> 1893
A27: B0C73RDD6N | B27: TPS Plant Foods | C27: Hibiscus Fertilizer for Tropical and Flowering Plants, Liquid Plant Food 8 oz (250mL) | D27: 8oz | E27: {=XLOOKUP(A27, production_planning!L:L, production_planning!AI:AI, "")} -> 3694
A28: B07CWP4MWW | B28: TPS Nutrients | C28: TPS NUTRIENTS Bloom Bud Builder & Flower Hardener Plant Nutrient and Supplement, Triggers Fast Flowering 1 Quart (32 oz) | D28: Quart | E28: {=XLOOKUP(A28, production_planning!L:L, production_planning!AI:AI, "")} -> 1910
A29: B0BRTJ6V3D | B29: TPS Plant Foods | C29: TPS NUTRIENTS Indoor Plant Food for Houseplants, Liquid Fertilizer, 32 oz (1 Quart) | D29: Quart | E29: {=XLOOKUP(A29, production_planning!L:L, production_planning!AI:AI, "")} -> 2549
A30: B09P3L4ZPN | B30: TPS Nutrients | C30: TPS NUTRIENTS Billions Concentrated Microbial Root Enhancer, 100% Water-Soluble with Mycorrhizae, Bacteria and Trichoderma, 16 oz (1 Pound) | D30: 1lb | E30: {=XLOOKUP(A30, production_planning!L:L, production_planning!AI:AI, "")} -> 0
A31: B0BRTJJ987 | B31: TPS Plant Foods | C31: Fiddle Leaf Fig Plant Food for All Fig and Other Ficus Trees, Liquid Houseplant Fertilizer, 32 oz (1 Quart) | D31: Quart | E31: {=XLOOKUP(A31, production_planning!L:L, production_planning!AI:AI, "")} -> 768
A32: B097FFWVHN | C32: Bloom Bud Builder & Flower Hardener Plant Nutrient and Supplement, Triggers Fast Flowering by TPS Nutrients, 1 Pint (16 oz) | E32: {=XLOOKUP(A32, production_planning!L:L, production_planning!AI:AI, "")}
A33: B0C73PVKDR | B33: TPS Plant Foods | C33: Plumeria Fertilizer for All Frangipani and Tropical Plants, Liquid Plant Food 8 oz (250mL) | D33: 8oz | E33: {=XLOOKUP(A33, production_planning!L:L, production_planning!AI:AI, "")} -> 4418
A34: B097J2XJNN | C34: Cal-Mag Complete, Calcium Magnesium Iron and Micronutrients Fertilizer and Supplement by TPS Nutrients, 1 Pint (16 oz) | D34: 16oz | E34: {=XLOOKUP(A34, production_planning!L:L, production_planning!AI:AI, "")}
A35: B0BRTKX9QR | B35: TPS Plant Foods | C35: Monstera Plant Food for Monsteras and Philodendrons, Tropical Houseplant Liquid Fertilizer, 32 oz (1 Quart) | D35: Quart | E35: {=XLOOKUP(A35, production_planning!L:L, production_planning!AI:AI, "")} -> 1403
A36: B0C6Q69C7K | B36: TPS Plant Foods | C36: Snake Plant Fertilizer for Snake Plants and All Sansevieria, 8 oz (250mL) | D36: 8oz | E36: {=XLOOKUP(A36, production_planning!L:L, production_planning!AI:AI, "")} -> 2014
A37: B07CWQ4PXV | B37: TPS Nutrients | C37: TPS NUTRIENTS N-Primer Nitrogen Supplement for Fast Vegetative Growth, Promotes Dark Green Leaves Quart (32 oz) | D37: Quart | E37: {=XLOOKUP(A37, production_planning!L:L, production_planning!AI:AI, "")} -> 1348
A38: B095JFK9B8 | C38: 0 | E38: {=XLOOKUP(A38, production_planning!L:L, production_planning!AI:AI, "")}
A39: B0C6Q5F2HR | B39: TPS Plant Foods | C39: Gardenia Fertilizer for Gardenias, Camellia and Rhododendron Plants, Flowering Liquid Plant Food 8 oz (250mL) | D39: 8oz | E39: {=XLOOKUP(A39, production_planning!L:L, production_planning!AI:AI, "")} -> 3890
A40: B0C73SC6S6 | B40: TPS Plant Foods | C40: Fruit Tree Fertilizer for All Fruit Trees Peach, Apple, and Pear, Liquid Plant Food, 32 oz (1 Quart) | D40: Quart | E40: {=XLOOKUP(A40, production_planning!L:L, production_planning!AI:AI, "")} -> 1739
A41: B0C6R6RL7B | B41: TPS Plant Foods | C41: TPS NUTRIENTS Air Plant Fertilizer for All Tillandsia Air Plants, Use As Foliar Spray or for Soaking, Liquid Plant Food, 32 oz (1 Quart) | D41: Quart | E41: {=XLOOKUP(A41, production_planning!L:L, production_planning!AI:AI, "")} -> 924
A42: B0C73RXR9M | B42: TPS Plant Foods | C42: TPS NUTRIENTS Tree Fertilizer for All Trees and Shrubs, Liquid Plant Food 8 oz (250mL) | D42: 8oz | E42: {=XLOOKUP(A42, production_planning!L:L, production_planning!AI:AI, "")} -> 1625
A43: B01MR9WDW7 | B43: TPS Nutrients | C43: Cal-Mag Complete, Calcium Magnesium Iron and Micronutrients Fertilizer and Supplement by TPS Nutrients, 1 Quart (32 oz) | D43: Quart | E43: {=XLOOKUP(A43, production_planning!L:L, production_planning!AI:AI, "")} -> 440
A44: B0BRTJC59Q | B44: TPS Plant Foods | C44: Herb Plant Food for All Edible Herbs, Leafy Greens and Veggies, Liquid Houseplant Fertilizer, 32 oz (1 Quart) | D44: Quart | E44: {=XLOOKUP(A44, production_planning!L:L, production_planning!AI:AI, "")} -> 402
A45: B08176NTH7 | B45: TPS Nutrients | C45: TPS NUTRIENTS One Liquid One Part Plant Nutrient from Veg to Bloom, for Lush Growth and Dense Flowers 1 Quart (32 oz) | D45: Quart | E45: {=XLOOKUP(A45, production_planning!L:L, production_planning!AI:AI, "")} -> 856
A46: B0C73TNKXQ | B46: TPS Plant Foods | C46: Fruit Tree Fertilizer for All Fruit Trees Peach, Apple, and Pear, Liquid Plant Food 8 oz (250mL) | D46: 8oz | E46: {=XLOOKUP(A46, production_planning!L:L, production_planning!AI:AI, "")} -> 279
A47: B0C73R715R | B47: TPS Plant Foods | C47: Blueberry Fertilizer for Acid Loving Fruit and Berry Gardens, Liquid Plant Food, 32 oz (1 Quart) | D47: Quart | E47: {=XLOOKUP(A47, production_planning!L:L, production_planning!AI:AI, "")} -> 2288
A48: B0C73RF7GX | B48: TPS Plant Foods | C48: TPS NUTRIENTS Tree Fertilizer for All Trees and Shrubs, Liquid Plant Food, 32 oz (1 Quart) | D48: Quart | E48: {=XLOOKUP(A48, production_planning!L:L, production_planning!AI:AI, "")} -> 1552
A49: B07CWQ2V2G | B49: TPS Nutrients | C49: TPS NUTRIENTS Signal Terpene Enhancer Plant Nutrient and Supplement, Flower Hardener and Increases Flavor, 1 Gallon (128 oz) | D49: 1 Gallon | E49: {=XLOOKUP(A49, production_planning!L:L, production_planning!AI:AI, "")} -> 247
A50: B07CWQ7FPX | B50: TPS Nutrients | C50: Organic Cal-Mag OAC Plant Nutrient and Supplement, Plus Iron and Micronutrients by TPS Nutrients, 1 Gallon (128 oz) | D50: 1 Gallon | E50: {=XLOOKUP(A50, production_planning!L:L, production_planning!AI:AI, "")} -> 1233
... A52: B097FD4CTM | B52: TPS Nutrients | C52: TPS NUTRIENTS Root Boost Advanced Rooting Formula for Living Soil and White Roots, Plus Microbes 1/2 Pint (8 oz) | D52: 8oz | E52: {=XLOOKUP(A52, production_planning!L:L, production_planning!AI:AI, "")} -> 820
A53: B097FDZK8P | C53: Organic Cal-Mag OAC Plant Nutrient and Supplement, Plus Iron and Micronutrients by TPS Nutrients, 1 Pint (16 oz) | D53: 16oz | E53: {=XLOOKUP(A53, production_planning!L:L, production_planning!AI:AI, "")}
A54: B097FDGL6B | B54: TPS Nutrients | C54: Canopy Boost Foliar Spray for All Plants, Boosts Photosynthesis and Corrects Common Yellowing by TPS Nutrients, 1/2 Pint (8 oz) | D54: 8oz | E54: {=XLOOKUP(A54, production_planning!L:L, production_planning!AI:AI, "")} -> 535
A55: B0BRTHWDSZ | B55: TPS Plant Foods | C55: Orchid Plant Food for All Orchids and Acid Loving Houseplants, Promotes Growth and Blooms, Liquid Fertilizer, 32 oz (1 Quart) | D55: Quart | E55: {=XLOOKUP(A55, production_planning!L:L, production_planning!AI:AI, "")} -> 1134
A56: B0BW9Y9NF6 | B56: TPS Plant Foods | C56: Succulent Plant Food for Succulents, Cactus, Jade and Aloe, Liquid Houseplant Fertilizer, 32 oz (1 Quart) | D56: Quart | E56: {=XLOOKUP(A56, production_planning!L:L, production_planning!AI:AI, "")} -> 923
A57: B0C73SKHWB | B57: TPS Plant Foods | C57: Hibiscus Fertilizer for Tropical and Flowering Plants, Liquid Plant Food, 32 oz (1 Quart) | D57: Quart | E57: {=XLOOKUP(A57, production_planning!L:L, production_planning!AI:AI, "")} -> 1133
A58: B07CWPTGLV | B58: TPS Nutrients | C58: TPS NUTRIENTS Canopy Boost Foliar Spray for All Plants, Boosts Photosynthesis and Corrects Common Yellowing 1 Quart (32 oz) | D58: Quart | E58: {=XLOOKUP(A58, production_planning!L:L, production_planning!AI:AI, "")} -> 762
A59: B0C6K2PMKS | B59: TPS Plant Foods | C59: Liquid Plant Food for use in AeroGarden, IDOO and Hydroponic Growing Systems, Liquid Fertilizer 1 Gallon (128 oz) | D59: 1 Gallon | E59: {=XLOOKUP(A59, production_planning!L:L, production_planning!AI:AI, "")} -> 1075
A60: B0C73RC4V9 | B60: TPS Plant Foods | C60: African Violet Fertilizer for Indoor Flowering Plants, Liquid Plant Food, 32 oz (1 Quart) | D60: Quart | E60: {=XLOOKUP(A60, production_planning!L:L, production_planning!AI:AI, "")} -> 959
A61: B0C73RSZLD | B61: TPS Plant Foods | C61: Blueberry Fertilizer for Acid Loving Fruit and Berry Gardens, Liquid Plant Food 8 oz (250mL) | D61: 8oz | E61: {=XLOOKUP(A61, production_planning!L:L, production_planning!AI:AI, "")} -> 2924
A62: B01MTCXHIQ | B62: TPS Nutrients | C62: TPS NUTRIENTS Cal-Mag Complete, Calcium Magnesium Iron and Micronutrients Fertilizer and Supplement, 1 Gallon (128 oz) | D62: 1 Gallon | E62: {=XLOOKUP(A62, production_planning!L:L, production_planning!AI:AI, "")} -> 330
A63: B07CWPPS52 | B63: TPS Nutrients | C63: TPS NUTRIENTS Root Boost Advanced Rooting Formula for Living Soil and White Roots, Plus Microbes 1 Quart (32 oz) | D63: Quart | E63: {=XLOOKUP(A63, production_planning!L:L, production_planning!AI:AI, "")} -> 1158
A64: B07GRQS8PS | B64: TPS Nutrients | C64: TPS NUTRIENTS Base A+B Two Part Set Complete Plant Growing Nutrient Formula for All Plants, for Both Soil and Hydro, Quart Set (2 x 32 oz) | D64: Quart Kit | E64: {=XLOOKUP(A64, production_planning!L:L, production_planning!AI:AI, "")} -> 0
A65: B0C6R5T1TR | B65: TPS Plant Foods | C65: TPS NUTRIENTS Cactus Fertilizer for Cacti and All Desert Plants, Liquid Plant Food, 32 oz (1 Quart) | D65: Quart | E65: {=XLOOKUP(A65, production_planning!L:L, production_planning!AI:AI, "")} -> 1299
... A71: B0C73T7GD6 | B71: TPS Plant Foods | C71: Hydrangea Fertilizer for Acid Loving Plants, Liquid Plant Food, 32 oz (1 Quart) | D71: Quart | E71: {=XLOOKUP(A71, production_planning!L:L, production_planning!AI:AI, "")} -> 5497
A72: B07VXK223F | C72: TPS Nutrients Complete Plant Nutrient Starter Kit, Fertilizer for Veg Through Bloom - Plus Guide and Foliar Spray Bottle | E72: {=XLOOKUP(A72, production_planning!L:L, production_planning!AI:AI, "")}
A73: B0BSR9KZ24 | B73: TPS Nutrients | C73: TPS NUTRIENTS Ultra Grow One Part Veg Plant Fertilizer with All NPK Cal-Mag and Micros, 1 Quart (32 oz) | D73: Quart | E73: {=XLOOKUP(A73, production_planning!L:L, production_planning!AI:AI, "")} -> 512
A74: B07CWQ5YM1 | B74: TPS Nutrients | C74: TPS NUTRIENTS Bloom Bud Builder & Flower Hardener Plant Nutrient and Supplement, Triggers Fast Flowering, 1 Gallon (128 oz) | D74: 1 Gallon | E74: {=XLOOKUP(A74, production_planning!L:L, production_planning!AI:AI, "")} -> 630
A75: B0C6Q6F34F | B75: TPS Plant Foods | C75: Gardenia Fertilizer for Gardenias, Camellia and Rhododendron Plants, Flowering Liquid Plant Food, 32 oz (1 Quart) | D75: Quart | E75: {=XLOOKUP(A75, production_planning!L:L, production_planning!AI:AI, "")} -> 582
A76: B0C73SW1WM | B76: TPS Plant Foods | C76: Citrus Fertilizer for All Citrus and Fruiting Trees, Liquid Plant Food, 1 Gallon (128 oz) | D76: 1 Gallon | E76: {=XLOOKUP(A76, production_planning!L:L, production_planning!AI:AI, "")} -> 289
A77: B0C73TDZCQ | B77: TPS Plant Foods | C77: Hydrangea Fertilizer for Acid Loving Plants, Liquid Plant Food 8 oz (250mL) | D77: 8oz | E77: {=XLOOKUP(A77, production_planning!L:L, production_planning!AI:AI, "")} -> 17655
A78: B0C73V8Z6G | B78: TPS Plant Foods | C78: Apple Tree Fertilizer for All Apple, Pear, Nut and Fruit Trees, Liquid Plant Food, 32 oz (1 Quart) | D78: Quart | E78: {=XLOOKUP(A78, production_planning!L:L, production_planning!AI:AI, "")} -> 1254
A79: B07CWP26VY | B79: TPS Nutrients | C79: TPS NUTRIENTS N-Primer Nitrogen Supplement for Fast Vegetative Growth, Promotes Dark Green Leaves Gallon (128 oz) | D79: 1 Gallon | E79: {=XLOOKUP(A79, production_planning!L:L, production_planning!AI:AI, "")} -> 300
A80: B08175HHGY | B80: TPS Nutrients | C80: TPS NUTRIENTS One Liquid One Part Plant Nutrient from Veg to Bloom, for Lush Growth and Dense Flowers, 1 Gallon (128 oz) | D80: 1 Gallon | E80: {=XLOOKUP(A80, production_planning!L:L, production_planning!AI:AI, "")} -> 809
A81: B0C6Q6GN8H | B81: TPS Plant Foods | C81: Palm Tree Fertilizer for All Palms and Ferns, Liquid Plant Food, 1 Gallon (128 oz) | D81: 1 Gallon | E81: {=XLOOKUP(A81, production_planning!L:L, production_planning!AI:AI, "")} -> 251
A82: B0C6R75HBB | B82: TPS Plant Foods | C82: Bonsai Fertilizer for All Bonsai Trees, Great for Root Soaks, Liquid Plant Food, 32 oz (1 Quart) | D82: Quart | E82: {=XLOOKUP(A82, production_planning!L:L, production_planning!AI:AI, "")} -> 435
A83: B0C73R3GKS | B83: TPS Plant Foods | C83: Azalea Fertilizer for Evergreen Shrubs Azalea, Rhododendron and Camellias, Liquid Plant Food 8 oz (250mL) | D83: 8oz | E83: {=XLOOKUP(A83, production_planning!L:L, production_planning!AI:AI, "")} -> 1939
A84: B0C73S6NFW | B84: TPS Plant Foods | C84: TPS NUTRIENTS Tree Fertilizer for All Trees and Shrubs, Liquid Plant Food, 1 Gallon (128 oz) | D84: 1 Gallon | E84: {=XLOOKUP(A84, production_planning!L:L, production_planning!AI:AI, "")} -> 981
... A88: B07CWNRS9C | B88: TPS Nutrients | C88: TPS NUTRIENTS Root Boost Advanced Rooting Formula for Living Soil and White Roots, Plus Microbes, 1 Gallon (128 oz) | D88: 1 Gallon | E88: {=XLOOKUP(A88, production_planning!L:L, production_planning!AI:AI, "")} -> 376
A89: B07CWQF744 | C89: N-Primer Nitrogen Supplement for Fast Vegetative Growth, Promotes Dark Green Leaves by TPS Nutrients, 5 Gallon (640 oz) | E89: {=XLOOKUP(A89, production_planning!L:L, production_planning!AI:AI, "")}
A90: B07CX4642R | C90: Silica Gold Plant Strength Nutrient and Supplement with Bioavailable Silicon by TPS Nutrients, 5 Gallon (640 oz) | E90: {=XLOOKUP(A90, production_planning!L:L, production_planning!AI:AI, "")}
A91: B08175HR5F | C91: TPS-One Liquid One Part Plant Nutrient from Veg to Bloom, for Lush Growth and Dense Flowers by TPS Nutrients, 5 Gallon (640 oz) | E91: {=XLOOKUP(A91, production_planning!L:L, production_planning!AI:AI, "")}
A92: B09P2CTKKS | C92: TPS Proper-Pour Spouts 3/4" Jug Faucet for Quick Drip Free Dosing, Two Pack | D92: 2 Pack | E92: {=XLOOKUP(A92, production_planning!L:L, production_planning!AI:AI, "")}
A93: B09P3DDFJT | C93: TPS Proper-Pour Spouts 3/4" Jug Faucet for Quick Drip Free Dosing, Five Pack | D93: 5 Pack | E93: {=XLOOKUP(A93, production_planning!L:L, production_planning!AI:AI, "")}
A94: B0BSR9XSVH | C94: TPS NUTRIENTS Ultra Grow and Ultra Bloom Set Complete Cycle Veg and Flowering Plant Fertilizer with All NPK Cal-Mag and Micros, Gallons (2X 128 oz) | D94: 1 Gallon Kit | E94: {=XLOOKUP(A94, production_planning!L:L, production_planning!AI:AI, "")}
A95: B0C6JYR3R8 | B95: TPS Plant Foods | C95: TPS NUTRIENTS Indoor Plant Food for Houseplants, Liquid Fertilizer, 1 Gallon (128 oz) | D95: 1 Gallon | E95: {=XLOOKUP(A95, production_planning!L:L, production_planning!AI:AI, "")} -> 158
A96: B0C6K2PMKL | B96: TPS Plant Foods | C96: Plant Food for Monsteras and Philodendrons, Tropical Houseplant Liquid Fertilizer, 1 Gallon (128 oz) | D96: 1 Gallon | E96: {=XLOOKUP(A96, production_planning!L:L, production_planning!AI:AI, "")} -> 159
A97: B0C6R9RTRS | B97: TPS Plant Foods | C97: Bonsai Fertilizer for All Bonsai Trees, Great for Root Soaks, Liquid Plant Food 1 Gallon (128 oz) | D97: 1 Gallon | E97: {=XLOOKUP(A97, production_planning!L:L, production_planning!AI:AI, "")} -> 208
A98: B0C73SGLGQ | B98: TPS Plant Foods | C98: Hibiscus Fertilizer for Tropical and Flowering Plants, Liquid Plant Food, 1 Gallon (128 oz) | D98: 1 Gallon | E98: {=XLOOKUP(A98, production_planning!L:L, production_planning!AI:AI, "")} -> 1015
A99: B0C73SWFZP | B99: TPS Plant Foods | C99: TPS NUTRIENTS Lawn Fertilizer for All Grass and Lawn Types, Liquid Plant Food, 32 oz (1 Quart) | D99: Quart | E99: {=XLOOKUP(A99, production_planning!L:L, production_planning!AI:AI, "")} -> 759
A100: B0C73T7JMQ | B100: TPS Plant Foods | C100: Lawn Fertilizer for All Grass and Lawn Types, Liquid Plant Food 8 oz (250mL) | D100: 8oz | E100: {=XLOOKUP(A100, production_planning!L:L, production_planning!AI:AI, "")} -> 892
A101: B0C73TZHF9 | B101: TPS Plant Foods | C101: TPS NUTRIENTS Rose Fertilizer for Flowering Plants, Liquid Plant Food 8 oz (250mL) | D101: 8oz | E101: {=XLOOKUP(A101, production_planning!L:L, production_planning!AI:AI, "")} -> 469
A102: B0CLTHSH4N | C102: TPS NUTRIENTS Bloom Bud Builder & Flower Hardener Plant Nutrient and Supplement, Triggers Fast Flowering 4 Gallon Pro Pack (4 x 128 oz) | E102: {=XLOOKUP(A102, production_planning!L:L, production_planning!AI:AI, "")}
A103: B01MSBD8XO | C103: Cal-Mag Complete, Calcium Magnesium Iron and Micronutrients Fertilizer and Supplement by TPS Nutrients, 2.5 Gallon (320 oz) | E103: {=XLOOKUP(A103, production_planning!L:L, production_planning!AI:AI, "")}
A104: B07CWNRYQD | C104: TPS Base A+B Two Part Set Complete Plant Growing Nutrient Formula for All Plants, for Both Soil and Hydro, 2.5 Gallon Set (2 x 320 oz) | E104: {=XLOOKUP(A104, production_planning!L:L, production_planning!AI:AI, "")}
A105: B07CWP2LWS | C105: Organic Cal-Mag OAC Plant Nutrient and Supplement, Plus Iron and Micronutrients by TPS Nutrients, 2.5 Gallon (320 oz) | E105: {=XLOOKUP(A105, production_planning!L:L, production_planning!AI:AI, "")}
A106: B07CWPJS94 | C106: LiquidSoil Living Soil Formula Salt Binding Flushing Agent and Beneficial Microbe Booster by TPS Nutrients, 5 Gallon (640 oz) | E106: {=XLOOKUP(A106, production_planning!L:L, production_planning!AI:AI, "")}
A107: B07CWPNZRM | C107: Root Boost Advanced Rooting Formula for Living Soil and White Roots, Plus Microbes by TPS Nutrients, 5 Gallon (640 oz) | E107: {=XLOOKUP(A107, production_planning!L:L, production_planning!AI:AI, "")}
A108: B07CWPS22R | C108: Organic Cal-Mag OAC Plant Nutrient and Supplement, Plus Iron and Micronutrients by TPS Nutrients, 5 Gallon (640 oz) | E108: {=XLOOKUP(A108, production_planning!L:L, production_planning!AI:AI, "")}
A109: B07CWQ1FP3 | C109: TPS NUTRIENTS Canopy Boost Foliar Spray for All Plants, Boosts Photosynthesis and Corrects Common Yellowing 5 Gallon (640 oz) | E109: {=XLOOKUP(A109, production_planning!L:L, production_planning!AI:AI, "")}
A110: B07CWQBKX1 | C110: Root Boost Advanced Rooting Formula for Living Soil and White Roots, Plus Microbes by TPS Nutrients, 2.5 Gallon (320 oz) | E110: {=XLOOKUP(A110, production_planning!L:L, production_planning!AI:AI, "")}
A111: B07CWQFGWN | C111: N-Primer Nitrogen Supplement for Fast Vegetative Growth, Promotes Dark Green Leaves by TPS Nutrients, 2.5 Gallon (320 oz) | E111: {=XLOOKUP(A111, production_planning!L:L, production_planning!AI:AI, "")}
A112: B07CXB72F7 | C112: Silica Gold Plant Strength Nutrient and Supplement with Bioavailable Silicon by TPS Nutrients, 2.5 Gallon (320 oz) | E112: {=XLOOKUP(A112, production_planning!L:L, production_planning!AI:AI, "")}
A113: B07HRC4C8V | C113: Cal-Mag Complete, Calcium Magnesium Iron and Micronutrients Fertilizer and Supplement by TPS Nutrients, 5 Gallon (640 oz) | E113: {=XLOOKUP(A113, production_planning!L:L, production_planning!AI:AI, "")}
... A115: B08175TC8F | C115: TPS-One Liquid One Part Plant Nutrient from Veg to Bloom, for Lush Growth and Dense Flowers by TPS Nutrients, 2.5 Gallon (320 oz) | E115: {=XLOOKUP(A115, production_planning!L:L, production_planning!AI:AI, "")}
A116: B09P2RPNHF | C116: TPS Proper-Pour Spout 3/4" Jug Faucet for Quick Drip Free Dosing, One Pack | D116: 1 Pack | E116: {=XLOOKUP(A116, production_planning!L:L, production_planning!AI:AI, "")}
A117: B0B33WCTHN | B117: TPS Nutrients | C117: TPS NUTRIENTS Billions Concentrated Microbial Root Enhancer, 100% Water-Soluble with Mycorrhizae, Bacteria and Trichoderma, 25 Pound | D117: 25lb | E117: {=XLOOKUP(A117, production_planning!L:L, production_planning!AI:AI, "")} -> 0
A118: B0BSR8P3XY | C118: Ultra Grow by TPS Nutrients, One Part Veg Plant Fertilizer with All NPK Cal-Mag and Micros, 5 Gallon (640 oz) | E118: {=XLOOKUP(A118, production_planning!L:L, production_planning!AI:AI, "")}
A119: B0BSR8TRGD | B119: TPS Nutrients | C119: Ultra Bloom by TPS Nutrients, One Part Flowering and Fruiting Plant Fertilizer with All NPK Cal-Mag and Micros, 1 Gallon (128 oz) | D119: 1 Gallon | E119: {=XLOOKUP(A119, production_planning!L:L, production_planning!AI:AI, "")} -> 281
...

Sheet production_planning
J1: Formula | N1: Formula | O1: Formula | T1: Formula | U1: Formula | V1: Formula | AB1: Formula | AC1: Formula | AE1: Formula | AF1: Formula | AH1: Formula | AI1: Formula | AJ1: Formula | AK1: Formula | AL1: Formula | AM1: Formula | AN1: Formula | AO1: Formula | AP1: Formula | AQ1: Formula | AR1: Formula | AX1: Formula | AY1: Formula | AZ1: Formula | BA1: Formula | BB1: Formula | BC1: Formula | BD1: Formula | BE1: Formula | BF1: Formula | BG1: Formula | BJ1: Formula | BK1: Formula | BO1: Formula | BP1: Formula | BQ1: Formula | BR1: Formula | BS1: Formula | BT1: Formula | BU1: Formula | BV1: Formula | BW1: Formula | BX1: Formula | BY1: Formula | BZ1: Formula | CA1: Formula | CB1: Formula | CC1: Formula | CD1: Formula | CE1: Formula | CJ1: Formula | CK1: Formula | CL1: Formula | CM1: Formula | CN1: Formula | CO1: Formula | CP1: Formula | CQ1: Formula | CR1: Formula | CS1: Formula | CT1: Formula | CU1: Formula | CV1: Formula
B2: # | C2: Release Date | D2: Act | E2: MarketPlace | F2: Brand | G2: Product | H2: Size | I2: Quantity | J2: Case Qty | K2: Sku | L2: Item # | M2: Formula | N2: # per Case | O2: Case Size | P2: Label Location | Q2: Caps | R2: Type | S2: Filter | T2: Volume (Gal) | U2: Price | V2: Total $ | W2: Status Locked | X2: Status Printed | Y2: Status Added to Production Order | Z2: Status Added to Manufacturing Plan | AA2: Note | AB2: Forecast New Products / Accelerate | AC2: 120/140 actual Days Total | AD2: 30 Days Available x Velocity | AE2: Forecast Standard Multiplier | AF2: Forecast Standard Multiplier Revenue | AG2: Label Printed | AH2: Label % of Production | AI2: Label Current Inventory | AJ2: Inventory Total Amazon Units | AK2: Inventory Total (Days) | AL2: Inventory FBA Available (Days) | AM2: Inventory Available Boxes AWD | AN2: MOVE FROM AWD (Boxes) | AO2: Inventory Inbound FBA | AP2: Shipment Pallet Qty | AQ2: Shipment Weight | AR2: Shipment Time (hrs) | AS2: Shipment TPS Shipment # | AT2: Shipment Type (AWD, FBA, Parcel) | AU2: Shipment # | AV2: Shipment Ref ID | AW2: Seven Day Over 30 Day Percentage | AX2: Sales Units Sold last 7 days | AY2: Sales Units Sold last 14 days | AZ2: Sales Units Sold last 28 days | BA2: Sales Units Sold last 42 days | BB2: Sales Units Sold last 4 months | BC2: Sales SUMMER '23 Units Sold Jun1-Sept30 2023 | BD2: Sales WINTER ' 23 Units Sold Oct1-Jan31 2023 | BE2: Sales SPRING '24 Units Sold Feb1-May31 2024 | BF2: Sales SUMMER '24 Units Sold Jun1-Sept30 2024 | BG2: Sales WINTER ' 24 Units Sold Oct1-Jan31 2024 | BH2: Vine Date | BI2: Vine Units Claimed | BJ2: 20 Weeks of Inventory(Weighted) | BK2: Label Current Inventory | BL2: Label Status | BM2: Label File | BN2: Label Size | BO2: Label Last Date Ordered | BP2: Label # to Order 12 MONTH OLDER | BQ2: Label # to Order NEW PRODUCTS | BR2: Label Days of Inventory | BS2: Label Inbound | BT2: Inventory Total In Stock $ | BU2: Inventory Days of Prime (based on 7 day sales) | BV2: Inventory Days of FBA (from Amazon) | BW2: Inventory Date Last Produced | BX2: Inventory Quantity Shipped | BY2: Inventory Available FBA | BZ2: Inventory Reserved FBA | CA2: Inventory Inbound FBA | CB2: Inventory Available AWD | CC2: Inventory Reserved AWD | CD2: Inventory Inbound AWD | CE2: Inventory AWD Outbound to FBA | CF2: MISSED AWD PRODUCTION | CG2: MISSED FBA PRODUCTION | CH2: Secondary Item# (GTIN) | CI2: Listed Name | CJ2: Product Stat Launch Date | CK2: Product Stat Age (mths) | CL2: Product Stat Expires? | CM2: Product Stat Age Category | CN2: Product Stat Product Category | CO2: Product Stat Seasonality Category | CP2: Forecast Needed Accelerating | CQ2: FBA Bandaid to 45 Days | CR2: Forecast Units Needed Multiplier | CS2: Forecast SUMMER OF DREAMS | CT2: Multiplier Auto Pull | CU2: Forecast Spring 24 | CV2: Forecast Fall/Winter 23
A3: Forecast | D3: TPS | E3: Amazon | F3: TPS Plant Foods | G3: 10-10-10 Fertilizer | H3: 8oz | I3: 0 | J3: 0 | K3: TRIPLE10GEN8OZ | L3: B0D4JHN9KK | M3: F.10-10-10 | N3: 60 | O3: 12x10x12 | P3: LBL-PLANT-001 | Q3: Aptar Pour | R3: Liquid | S3: 75 | T3: 0 | U3: 11.99 | V3: 0 | W3: FALSE | X3: FALSE | Y3: FALSE | Z3: FALSE | AB3: 120 | AC3: 0 | AD3: 0 | AE3: 60 | AF3: 719 | AH3: 0 | AI3: 2063 | AJ3: 637 | AK3: 1098 | AL3: 1005 | AM3: 0 | AN3: 0 | AO3: 0 | AP3: 0 | AQ3: 0 | AR3: 0 | AW3: 0 | AX3: 0 | AY3: 14 | AZ3: 19 | BA3: 27 | BB3: 92 | BC3: 0 | BD3: 0 | BE3: 0 | BF3: 196 | BG3: 139 | BJ3: 70 | BK3: 2063 | BL3: Current | BM3: https://drive.google.com/open?id=12kkUJSNpkStvU1iGFPHgXm0-PC4Sb91j&usp=drive_fs | BN3: 5" x 8" | BP3: 0 | BQ3: Established | BR3: 7865 | BT3: 7638 | BU3: 0 | BV3: 144 | BW3: 45896 | BX3: 420 | BY3: 583 | BZ3: 54 | CA3: 0 | CB3: 0 | CC3: 0 | CD3: 0 | CE3: 0 | CJ3: 45444 | CK3: 20 | CL3: No | CM3: Established | CN3: Garden | CO3: Seasonal | CP3: 115 | CQ3: 0 | CR3: 42 | CS3: -429 | CT3: 66.7 | CU3: 0 | CV3: 0
A4: Forecast | D4: TPS | E4: Amazon | F4: TPS Plant Foods | G4: 10-10-10 Fertilizer | H4: Quart | I4: 0 | J4: 0 | K4: TRIPLE10GEN1Q | L4: B0D4JHVBDQ | M4: F.10-10-10 | N4: 12 | O4: 13x13x10 | P4: LBL-PLANT-226 | Q4: Aptar Pour | R4: Liquid | S4: 75 | T4: 0 | U4: 24.99 | V4: 0 | W4: FALSE | X4: FALSE | Y4: FALSE | Z4: FALSE | AB4: 48 | AC4: 0 | AD4: 0 | AE4: 12 | AF4: 300 | AH4: 0 | AI4: 1577 | AJ4: 172 | AK4: 980 | AL4: 222 | AM4: 0 | AN4: 0 | AO4: 0 | AP4: 0 | AQ4: 0 | AR4: 0 | AW4: 0 | AX4: 0 | AY4: 5 | AZ4: 5 | BA4: 7 | BB4: 30 | BC4: 0 | BD4: 0 | BE4: 0 | BF4: 81 | BG4: 60 | BJ4: 22 | BK4: 1577 | BL4: Current | BM4: https://drive.google.com/open?id=12kkUJSNpkStvU1iGFPHgXm0-PC4Sb91j&usp=drive_fs | BN4: 5" x 8" | BP4: 0 | BQ4: Established | BR4: 17494 | BT4: 4298 | BU4: 0 | BV4: 66 | BW4: 46044 | BX4: 132 | BY4: 39 | BZ4: 1 | CA4: 0 | CB4: 0 | CC4: 0 | CD4: 132 | CE4: 0 | CJ4: 45444 | CK4: 20 | CL4: No | CM4: Established | CN4: Garden | CO4: Seasonal | CP4: 38 | CQ4: 0 | CR4: 11 | CS4: -96 | CT4: 66.7 | CU4: 0 | CV4: 0
A5: Forecast | D5: TPS | E5: Amazon | F5: TPS Plant Foods | G5: 10-10-10 Fertilizer | H5: 1 Gallon | I5: 0 | J5: 0 | K5: TRIPLE10GEN1G | L5: B0D4JGCSM1 | M5: F.10-10-10 | N5: 4 | O5: 13x13x13 | P5: LBL-PLANT-483 | Q5: Berry Unvented | R5: Liquid | S5: 75 | T5: 0 | U5: 49.99 | V5: 0 | W5: FALSE | X5: FALSE | Y5: FALSE | Z5: FALSE | AB5: 24 | AC5: 0 | AD5: 0 | AE5: 8 | AF5: 400 | AH5: 0 | AI5: 402 | AJ5: 66 | AK5: 853 | AL5: 246 | AM5: 0 | AN5: 0 | AO5: 0 | AP5: 0 | AQ5: 0 | AR5: 0 | AW5: 0 | AX5: 0 | AY5: 2 | AZ5: 2 | BA5: 4 | BB5: 18 | BC5: 0 | BD5: 0 | BE5: 0 | BF5: 0 | BG5: 0 | BJ5: 9 | BK5: 402 | BL5: Current | BM5: https://drive.google.com/open?id=12kkUJSNpkStvU1iGFPHgXm0-PC4Sb91j&usp=drive_fs | BN5: 5" x 8" | BP5: 0 | BQ5: Established | BR5: 9359 | BT5: 3299 | BU5: 0 | BV5: 79 | BW5: 46042 | BX5: 44 | BY5: 19 | BZ5: 3 | CA5: 0 | CB5: 0 | CC5: 0 | CD5: 44 | CE5: 0 | CJ5: 45444 | CK5: 20 | CL5: No | CM5: Established | CN5: Garden | CO5: Seasonal | CP5: 23 | CQ5: 0 | CR5: 4 | CS5: -35 | CT5: 66.7 | CU5: 0 | CV5: 0
A6: Forecast | D6: TPS | E6: Amazon | F6: TPS Plant Foods | G6: 10-10-10 Fertilizer For Plants | H6: 8oz | I6: 0 | J6: 0 | K6: TRIPLE10PLANTS8OZ | L6: B0D4JGRK2C | M6: F.10-10-10 | N6: 60 | O6: 12x10x12 | P6: LBL-PLANT-002 | Q6: Aptar Pour | R6: Liquid | S6: 75 | T6: 0 | U6: 11.99 | V6: 0 | W6: FALSE | X6: FALSE | Y6: FALSE | Z6: FALSE | AB6: 180 | AC6: 0 | AD6: 0 | AE6: 120 | AF6: 1439 | AH6: 0 | AI6: 198 | AJ6: 882 | AK6: 1110 | AL6: 107 | AM6: 0 | AN6: 0 | AO6: 0 | AP6: 0 | AQ6: 0 | AR6: 0 | AW6: 0 | AX6: 0 | AY6: 15 | AZ6: 27 | BA6: 48 | BB6: 114 | BC6: 0 | BD6: 0 | BE6: 0 | BF6: 45 | BG6: 66 | BJ6: 88 | BK6: 198 | BL6: Current | BM6: https://drive.google.com/open?id=12tnHyKPWEETodS_CBrKGGcS1NveE9Nnr&usp=drive_fs | BN6: 5" x 8" | BP6: 0 | BQ6: Established | BR6: 2348 | BT6: 10575 | BU6: 0 | BV6: 46 | BW6: 46036 | BX6: 780 | BY6: 85 | BZ6: 17 | CA6: 0 | CB6: 0 | CC6: 0 | CD6: 780 | CE6: 0 | CJ6: 45444 | CK6: 20 | CL6: No | CM6: Established | CN6: Garden | CO6: Seasonal | CP6: 143 | CQ6: 0 | CR6: 60 | CS6: -688 | CT6: 66.7 | CU6: 0 | CV6: 0
A7: Forecast | D7: TPS | E7: Amazon | F7: TPS Plant Foods | G7: 10-10-10 Fertilizer For Plants | H7: Quart | I7: 0 | J7: 0 | K7: TRIPLE10PLANTS1Q | L7: B0D4JFLDK3 | M7: F.10-10-10 | N7: 12 | O7: 13x13x10 | P7: LBL-PLANT-227 | Q7: Aptar Pour | R7: Liquid | S7: 75 | T7: 0 | U7: 24.99 | V7: 0 | W7: FALSE | X7: FALSE | Y7: FALSE | Z7: FALSE | AB7: 72 | AC7: 0 | AD7: 0 | AE7: 36 | AF7: 900 | AH7: 0 | AI7: 617 | AJ7: 135 | AK7: 336 | AL7: 304 | AM7: 0 | AN7: 0 | AO7: 0 | AP7: 0 | AQ7: 0 | AR7: 0 | AW7: 0 | AX7: 0 | AY7: 9 | AZ7: 15 | BA7: 18 | BB7: 49 | BC7: 0 | BD7: 0 | BE7: 0 | BF7: 24 | BG7: 26 | BJ7: 48 | BK7: 617 | BL7: Current | BM7: https://drive.google.com/open?id=12tnHyKPWEETodS_CBrKGGcS1NveE9Nnr&usp=drive_fs | BN7: 5" x 8" | BP7: 0 | BQ7: Established | BR7: 3246 | BT7: 3374 | BU7: 0 | BV7: 87 | BW7: 45889 | BX7: 96 | BY7: 122 | BZ7: 13 | CA7: 0 | CB7: 0 | CC7: 0 | CD7: 0 | CE7: 0 | CJ7: 45444 | CK7: 20 | CL7: No | CM7: Established | CN7: Garden | CO7: Seasonal | CP7: 61 | CQ7: 0 | CR7: 33 | CS7: -52 | CT7: 66.7 | CU7: 0 | CV7: 0
A8: Forecast | D8: TPS | E8: Amazon | F8: TPS Plant Foods | G8: 10-10-10 Fertilizer For Plants | H8: 1 Gallon | I8: 0 | J8: 0 | K8: TRIPLE10PLANTS1G | L8: B0D4JDPWX5 | M8: F.10-10-10 | N8: 4 | O8: 13x13x13 | P8: LBL-PLANT-484 | Q8: Berry Unvented | R8: Liquid | S8: 75 | T8: 0 | U8: 49.99 | V8: 0 | W8: FALSE | X8: FALSE | Y8: FALSE | Z8: FALSE | AB8: 0 | AC8: 0 | AD8: #VALUE! | AE8: No Sales | AF8: 0 | AH8: 0 | AI8: 362 | AJ8: 50 | AK8: NO SALES | AL8: NO SALES | AM8: 0 | AN8: 0 | AO8: 0 | AP8: 0 | AQ8: 0 | AR8: 0 | AW8: 0 | AX8: 0 | AY8: 0 | AZ8: 0 | BA8: 0 | BB8: 0 | BC8: 0 | BD8: 0 | BE8: 0 | BF8: 0 | BG8: 0 | BJ8: 0 | BK8: 362 | BL8: Current | BM8: https://drive.google.com/open?id=12tnHyKPWEETodS_CBrKGGcS1NveE9Nnr&usp=drive_fs | BN8: 5" x 8" | BP8: 0 | BQ8: Established | BR8: NO SALES | BT8: 2500 | BU8: 0 | BV8: 0 | BW8: 45918 | BX8: 40 | BY8: 50 | BZ8: 0 | CA8: 0 | CB8: 0 | CC8: 0 | CD8: 0 | CE8: 0 | CJ8: 45444 | CK8: 20 | CL8: No | CM8: Established | CN8: Garden | CO8: Seasonal | CP8: 0 | CQ8: 0 | CR8: No Sales | CS8: -50 | CT8: 66.7 | CU8: 0 | CV8: 0
A9: Forecast | D9: TPS | E9: Amazon | F9: TPS Plant Foods | G9: 10-10-10 Fertilizer For Trees | H9: Quart | I9: 0 | J9: 0 | K9: TRIPLE10TREE1Q | L9: B0D4JGZRBH | M9: F.10-10-10 | N9: 12 | O9: 13x13x10 | P9: LBL-PLANT-228 | Q9: Aptar Pour | R9: Liquid | S9: 75 | T9: 0 | U9: 24.99 | V9: 0 | W9: FALSE | X9: FALSE | Y9: FALSE | Z9: FALSE | AB9: 276 | AC9: 0 | AD9: 0 | AE9: 96 | AF9: 2399 | AH9: 0 | AI9: 1209 | AJ9: 1131 | AK9: 914 | AL9: 439 | AM9: 0 | AN9: 0 | AO9: 0 | AP9: 0 | AQ9: 0 | AR9: 0 | AW9: 0 | AX9: 0 | AY9: 29 | AZ9: 38 | BA9: 64 | BB9: 216 | BC9: 0 | BD9: 0 | BE9: 0 | BF9: 124 | BG9: 221 | BJ9: 146 | BK9: 1209 | BL9: Current | BM9: https://drive.google.com/open?id=12jXhO0j6hs2AMo30JuNcgMpAiVcS4mkq&usp=drive_fs | BN9: 5" x 8" | BP9: 0 | BQ9: Established | BR9: 3162 | BT9: 28264 | BU9: 0 | BV9: 90 | BW9: 46044 | BX9: 576 | BY9: 543 | BZ9: 12 | CA9: 0 | CB9: 0 | CC9: 0 | CD9: 576 | CE9: 0 | CJ9: 45444 | CK9: 20 | CL9: No | CM9: Established | CN9: Garden | CO9: Seasonal | CP9: 270 | CQ9: 0 | CR9: 84 | CS9: -764 | CT9: 66.7 | CU9: 0 | CV9: 0
A10: Forecast | D10: TPS | E10: Amazon | F10: TPS Plant Foods | G10: 10-10-10 Fertilizer For Trees | H10: 8oz | I10: 0 | J10: 0 | K10: TRIPLE10TREE8OZ | L10: B0D4JFHCPP | M10: F.10-10-10 | N10: 60 | O10: 12x10x12 | P10: LBL-PLANT-003 | Q10: Aptar Pour | R10: Liquid | S10: 75 | T10: 0 | U10: 11.99 | V10: 0 | W10: FALSE | X10: FALSE | Y10: FALSE | Z10: FALSE | AB10: 120 | AC10: 0 | AD10: 0 | AE10: 120 | AF10: 1439 | AH10: 0 | AI10: 59 | AJ10: 816 | AK10: 650 | AL10: 107 | AM10: 2 | AN10: 0 | AO10: 0 | AP10: 0 | AQ10: 0 | AR10: 0 | AW10: 0 | AX10: 0 | AY10: 30 | AZ10: 42 | BA10: 58 | BB10: 200 | BC10: 0 | BD10: 0 | BE10: 0 | BF10: 12 | BG10: 75 | BJ10: 151 | BK10: 59 | BL10: Current | BM10: https://drive.google.com/open?id=12jXhO0j6hs2AMo30JuNcgMpAiVcS4mkq&usp=drive_fs | BN10: 5" x 8" | BP10: 500 | BQ10: Established | BR10: 1162 | BT10: 9784 | BU10: 0 | BV10: 58 | BW10: 46044 | BX10: 540 | BY10: 135 | BZ10: 21 | CA10: 0 | CB10: 120 | CC10: 0 | CD10: 540 | CE10: 0 | CJ10: 45444 | CK10: 20 | CL10: No | CM10: Established | CN10: Garden | CO10: Seasonal | CP10: 100 | CQ10: 0 | CR10: 93 | CS10: -476 | CT10: 66.7 | CU10: 0 | CV10: 0
A11: Forecast | D11: TPS | E11: Amazon | F11: TPS Plant Foods | G11: 10-10-10 Fertilizer For Trees | H11: 1 Gallon | I11: 0 | J11: 0 | K11: TRIPLE10TREE1G | L11: B0D4JKCJP6 | M11: F.10-10-10 | N11: 4 | O11: 13x13x13 | P11: LBL-PLANT-485 | Q11: Berry Unvented | R11: Liquid | S11: 75 | T11: 0 | U11: 49.99 | V11: 0 | W11: FALSE | X11: FALSE | Y11: FALSE | Z11: FALSE | AB11: 68 | AC11: 0 | AD11: 0 | AE11: 32 | AF11: 1600 | AH11: 0 | AI11: 68 | AJ11: 246 | AK11: 555 | AL11: 230 | AM11: 0 | AN11: 0 | AO11: 8 | AP11: 0 | AQ11: 0 | AR11: 0 | AW11: 0 | AX11: 0 | AY11: 11 | AZ11: 13 | BA11: 22 | BB11: 61 | BC11: 0 | BD11: 0 | BE11: 0 | BF11: 0 | BG11: 0 | BJ11: 53 | BK11: 68 | BL11: Current | BM11: https://drive.google.com/open?id=12jXhO0j6hs2AMo30JuNcgMpAiVcS4mkq&usp=drive_fs | BN11: 5" x 8" | BP11: 0 | BQ11: Established | BR11: 1355 | BT11: 12298 | BU11: 0 | BV11: 100 | BW11: 46052 | BX11: 332 | BY11: 102 | BZ11: 8 | CA11: 8 | CB11: 0 | CC11: 4 | CD11: 124 | CE11: 0 | CJ11: 45444 | CK11: 20 | CL11: No | CM11: Established | CN11: Garden | CO11: Seasonal | CP11: 66 | CQ11: 0 | CR11: 29 | CS11: -142 | CT11: 66.7 | CU11: 0 | CV11: 0
A12: Forecast | D12: TPS | E12: Amazon | F12: TPS Plant Foods | G12: 10-10-10 Fertilizer For Vegetables | H12: 8oz | I12: 0 | J12: 0 | K12: TRIPLE10VEG8OZ | L12: B0D4JHN28P | M12: F.10-10-10 | N12: 60 | O12: 12x10x12 | P12: LBL-HV-002 | Q12: Aptar Pour | R12: Liquid | S12: 75 | T12: 0 | U12: 11.99 | V12: 0 | W12: FALSE | X12: FALSE | Y12: FALSE | Z12: FALSE | AB12: 420 | AC12: 0 | AD12: 0 | AE12: 180 | AF12: 2158 | AH12: 0 | AI12: 3070 | AJ12: 469 | AK12: 201 | AL12: 150 | AM12: 0 | AN12: 0 | AO12: 60 | AP12: 0 | AQ12: 0 | AR12: 0 | AW12: 0 | AX12: 0 | AY12: 46 | AZ12: 80 | BA12: 134 | BB12: 353 | BC12: 0 | BD12: 0 | BE12: 0 | BF12: 9 | BG12: 12 | BJ12: 263 | BK12: 3070 | BL12: Current | BM12: https://drive.google.com/open?id=12l6aGFTfM3fx8OCHtThUDBcxxBNlaB_j&usp=drive_fs | BN12: 5" x 8" | BP12: 0 | BQ12: Established | BR12: 2549 | BT12: 5623 | BU12: 0 | BV12: 71 | BW12: 45924 | BX12: 600 | BY12: 350 | BZ12: 18 | CA12: 60 | CB12: 0 | CC12: 0 | CD12: -19 | CE12: 60 | CF12: 19 | CJ12: 45444 | CK12: 20 | CL12: No | CM12: Established | CN12: Garden | CO12: Seasonal | CP12: 366 | CQ12: 0 | CR12: 178 | CS12: 131 | CT12: 66.7 | CU12: 0 | CV12: 0
A13: Forecast | D13: TPS | E13: Amazon | F13: TPS Plant Foods | G13: 10-10-10 Fertilizer For Vegetables | H13: Quart | I13: 0 | J13: 0 | K13: TRIPLE10VEG1Q | L13: B0D4JHJM1R | M13: F.10-10-10 | N13: 12 | O13: 12x10x12 | P13: LBL-PLANT-229 | Q13: Aptar Pour | R13: Liquid | S13: 75 | T13: 0 | U13: 24.99 | V13: 0 | W13: FALSE | X13: FALSE | Y13: FALSE | Z13: FALSE | AB13: 0 | AC13: 0 | AD13: 0 | AE13: 60 | AF13: 1499 | AH13: 0 | AI13: 2021 | AJ13: 231 | AK13: 373 | AL13: 234 | AM13: 7 | AN13: 0 | AO13: 0 | AP13: 0 | AQ13: 0 | AR13: 0 | AW13: 0 | AX13: 0 | AY13: 13 | AZ13: 24 | BA13: 29 | BB13: 84 | BC13: 0 | BD13: 0 | BE13: 0 | BF13: 10 | BG13: 28 | BJ13: 73 | BK13: 2021 | BL13: Current | BM13: https://drive.google.com/open?id=12l6aGFTfM3fx8OCHtThUDBcxxBNlaB_j&usp=drive_fs | BN13: 5" x 8" | BP13: 0 | BQ13: Established | BR13: 5927 | BT13: 5773 | BU13: 0 | BV13: 74 | BW13: 45838 | BX13: 624 | BY13: 145 | BZ13: 2 | CA13: 0 | CB13: 84 | CC13: 0 | CD13: 0 | CE13: 0 | CJ13: 45444 | CK13: 20 | CL13: No | CM13: Established | CN13: Garden | CO13: Seasonal | CP13: 0 | CQ13: 0 | CR13: 53 | CS13: -88 | CT13: 66.7 | CU13: 0 | CV13: 0
A14: Forecast | D14: TPS | E14: Amazon | F14: TPS Plant Foods | G14: 10-10-10 Fertilizer For Vegetables | H14: 1 Gallon | I14: 0 | J14: 0 | K14: TRIPLE10VEG1G | L14: B0D4JGQMQD | M14: F.10-10-10 | N14: 4 | O14: 13x13x13 | P14: LBL-PLANT-486 | Q14: Berry Unvented | R14: Liquid | S14: 75 | T14: 0 | U14: 49.99 | V14: 0 | W14: FALSE | X14: FALSE | Y14: FALSE | Z14: FALSE | AB14: 8 | AC14: 0 | AD14: 0 | AE14: 4 | AF14: 200 | AH14: 0 | AI14: 271 | AJ14: 108 | AK14: 5184 | AL14: 1728 | AM14: 0 | AN14: 0 | AO14: 0 | AP14: 0 | AQ14: 0 | AR14: 0 | AW14: 0 | AX14: 0 | AY14: 0 | AZ14: 1 | BA14: 2 | BB14: 4 | BC14: 0 | BD14: 0 | BE14: 0 | BF14: 0 | BG14: 0 | BJ14: 2 | BK14: 271 | BL14: Current | BM14: https://drive.google.com/open?id=12l6aGFTfM3fx8OCHtThUDBcxxBNlaB_j&usp=drive_fs | BN14: 5" x 8" | BP14: 0 | BQ14: Established | BR14: 22752 | BT14: 5399 | BU14: 0 | BV14: 163 | BW14: 46049 | BX14: 68 | BY14: 36 | BZ14: 4 | CA14: 0 | CB14: 0 | CC14: 0 | CD14: 68 | CE14: 0 | CJ14: 45444 | CK14: 20 | CL14: No | CM14: Established | CN14: Garden | CO14: Seasonal | CP14: 5 | CQ14: 0 | CR14: 2 | CS14: -101 | CT14: 66.7 | CU14: 0 | CV14: 0
A15: Forecast | C15: 45870 | D15: TPS | E15: Amazon | F15: TPS Plant Foods | G15: 4-4-4 Fertilizer | H15: Quart | I15: 0 | J15: 0 | K15: TPS-4-4-4FERT-QUART | L15: B0FKSX9Y7M | M15: F.5-5-5 | N15: 12 | O15: 13x10x10 | P15: LBL-PLANT-230 | Q15: Aptar Pour | R15: Liquid | S15: 75 | T15: 0 | U15: 24.99 | V15: 0 | W15: FALSE | X15: FALSE | Y15: FALSE | Z15: FALSE | AB15: #N/A | AC15: 0 | AD15: 0 | AE15: 48 | AF15: 1200 | AH15: 0 | AI15: 389 | AJ15: 120 | AK15: 216 | AL15: 41 | AM15: 0 | AN15: 0 | AO15: 0 | AP15: 0 | AQ15: 0 | AR15: 0 | AW15: 0 | AX15: 0 | AY15: 17 | AZ15: 17 | BA15: 17 | BB15: 23 | BC15: 0 | BD15: 0 | BE15: 0 | BF15: 0 | BG15: 0 | BJ15: 74 | BK15: 389 | BL15: Current | BM15: https://drive.google.com/file/d/1RSjf9yzQZxBLDGTtNE4k8nJhg0izAVEa/view?usp=drive_link | BN15: 5" x 8" | BP15: 0 | BQ15: 0 | BR15: 2443 | BT15: 2999 | BU15: 0 | BV15: 30 | BW15: 46042 | BY15: 23 | BZ15: 1 | CA15: 0 | CB15: 0 | CC15: 0 | CD15: 96 | CE15: 0 | CJ15: 45870 | CK15: 6 | CM15: #N/A | CN15: Garden | CO15: Seasonal | CP15: #N/A | CR15: 38 | CS15: -81 | CT15: 66.7 | CU15: 0 | CV15: 0
A16: Forecast | C16: 45870 | D16: TPS | E16: Amazon | F16: TPS Plant Foods | G16: 4-4-4 Fertilizer | H16: 1 Gallon | I16: 0 | J16: 0 | K16: TPS-4-4-4FERT-1GALLON | L16: B0FKSBSMW8 | M16: F.5-5-5 | N16: 4 | O16: 13x13x13 | P16: LBL-PLANT-487 | Q16: Berry Unvented | R16: Liquid | S16: 75 | T16: 0 | U16: 39.99 | V16: 0 | W16: FALSE | X16: FALSE | Y16: FALSE | Z16: FALSE | AB16: #N/A | AC16: 0 | AD16: #VALUE! | AE16: 24 | AF16: 960 | AH16: 0 | AI16: 296 | AJ16: 0 | AK16: SOLD OUT | AL16: SOLD OUT | AM16: 0 | AN16: 0 | AO16: 0 | AP16: 0 | AQ16: 0 | AR16: 0 | AW16: 0 | AX16: 0 | AY16: 10 | AZ16: 10 | BA16: 10 | BB16: 10 | BC16: 0 | BD16: 0 | BE16: 0 | BF16: 0 | BG16: 0 | BJ16: 43 | BK16: 296 | BL16: Current | BM16: https://drive.google.com/file/d/1RSjf9yzQZxBLDGTtNE4k8nJhg0izAVEa/view?usp=drive_link | BN16: 5" x 8" | BP16: 0 | BQ16: 0 | BR16: SOLD OUT | BT16: 0 | BU16: 0 | BV16: 0 | BW16: 45946 | BY16: 0 | BZ16: 0 | CA16: 0 | CB16: 0 | CC16: 0 | CD16: 0 | CE16: 0 | CJ16: 45870 | CK16: 6 | CM16: #N/A | CN16: Garden | CO16: Seasonal | CP16: #N/A | CR16: 22 | CS16: 17 | CT16: 66.7 | CU16: 10 | CV16: 0
A17: Forecast | C17: 45870 | D17: TPS | E17: Amazon | F17: TPS Plant Foods | G17: 4-4-4 Fertilizer | H17: 8oz | I17: 0 | J17: 0 | K17: TPS-4-4-4FERT-8OZ | L17: B0FKSCPNVJ | M17: F.5-5-5 | N17: 60 | O17: 12x10x12 | P17: LBL-PLANT-004 | Q17: Aptar Pour | R17: Liquid | S17: 75 | T17: 0 | U17: 11.99 | V17: 0 | W17: FALSE | X17: FALSE | Y17: FALSE | Z17: FALSE | AB17: #N/A | AC17: 0 | AD17: 0 | AE17: 60 | AF17: 719 | AH17: 0 | AI17: 772 | AJ17: 237 | AK17: 1810 | AL17: 428 | AM17: 0 | AN17: 0 | AO17: 1 | AP17: 0 | AQ17: 0 | AR17: 0 | AW17: 0 | AX17: 0 | AY17: 4 | AZ17: 4 | BA17: 4 | BB17: 4 | BC17: 0 | BD17: 0 | BE17: 0 | BF17: 0 | BG17: 0 | BJ17: 17 | BK17: 772 | BL17: Current | BM17: https://drive.google.com/file/d/1RSjf9yzQZxBLDGTtNE4k8nJhg0izAVEa/view?usp=drive_link | BN17: 5" x 8" | BP17: 0 | BQ17: 0 | BR17: 21613 | BT17: 2842 | BU17: 0 | BV17: 89 | BW17: 46041 | BY17: 56 | BZ17: 0 | CA17: 1 | CB17: 0 | CC17: 0 | CD17: 180 | CE17: 0 | CJ17: 45870 | CK17: 6 | CM17: #N/A | CN17: Garden | CO17: Seasonal | CP17: #N/A | CR17: 9 | CS17: -230 | CT17: 66.7 | CU17: 0 | CV17: 0
A18: Forecast | C18: 45870 | D18: TPS | E18: Amazon | F18: TPS Plant Foods | G18: 5-10-10 Fertilizer | H18: Quart | I18: 0 | J18: 0 | K18: TPS-5-10-10FERT-QUART | L18: B0FKT82XBK | M18: F.5-10-10 | N18: 12 | O18: 13x10x10 | P18: LBL-PLANT-231 | Q18: Aptar Pour | R18: Liquid | S18: 75 | T18: 0 | U18: 24.99 | V18: 0 | W18: FALSE | X18: FALSE | Y18: FALSE | Z18: FALSE | AB18: #N/A | AC18: 0 | AD18: 0 | AE18: 72 | AF18: 1799 | AH18: 0 | AI18: 1040 | AJ18: 440 | AK18: 505 | AL18: 15 | AM18: 0 | AN18: 0 | AO18: 0 | AP18: 0 | AQ18: 0 | AR18: 0 | AW18: 0 | AX18: 0 | AY18: 25 | AZ18: 27 | BA18: 31 | BB18: 79 | BC18: 0 | BD18: 0 | BE18: 0 | BF18: 0 | BG18: 0 | BJ18: 112 | BK18: 1040 | BL18: Current | BM18: https://drive.google.com/file/d/1AHwQ4g_70dqAVmkFiUBr8GDQ7L-2_5xS/view?usp=drive_link | BN18: 5" x 8" | BP18: 0 | BQ18: 0 | BR18: 3685 | BT18: 10996 | BU18: 0 | BV18: 24 | BW18: 46050 | BY18: 13 | BZ18: 31 | CA18: 0 | CB18: 0 | CC18: 0 | CD18: 396 | CE18: 0 | CJ18: 45870 | CK18: 6 | CM18: #N/A | CN18: Garden | CO18: Seasonal | CP18: #N/A | CR18: 60 | CS18: -306 | CT18: 66.7 | CU18: 0 | CV18: 0
A19: Forecast | C19: 45870 | D19: TPS | E19: Amazon | F19: TPS Plant Foods | G19: 5-10-10 Fertilizer | H19: 8oz | I19: 0 | J19: 0 | K19: TPS-5-10-10FERT-8OZ | L19: B0FKS8HL6H | M19: F.5-10-10 | N19: 60 | O19: 12x10x12 | P19: LBL-PLANT-005 | Q19: Aptar Pour | R19: Liquid | S19: 75 | T19: 0 | U19: 11.99 | V19: 0 | W19: FALSE | X19: FALSE | Y19: FALSE | Z19: FALSE | AB19: #N/A | AC19: 0 | AD19: 0 | AE19: 60 | AF19: 719 | AH19: 0 | AI19: 476 | AJ19: 152 | AK19: 228 | AL19: 29 | AM19: 0 | AN19: 0 | AO19: 0 | AP19: 0 | AQ19: 0 | AR19: 0 | AW19: 0 | AX19: 0 | AY19: 16 | AZ19: 24 | BA19: 28 | BB19: 68 | BC19: 0 | BD19: 0 | BE19: 0 | BF19: 0 | BG19: 0 | BJ19: 81 | BK19: 476 | BL19: Current | BM19: https://drive.google.com/file/d/1AHwQ4g_70dqAVmkFiUBr8GDQ7L-2_5xS/view?usp=drive_link | BN19: 5" x 8" | BP19: 0 | BQ19: 0 | BR19: 1777 | BT19: 1822 | BU19: 0 | BV19: 14 | BW19: 46051 | BY19: 19 | BZ19: 13 | CA19: 0 | CB19: 0 | CC19: 0 | CD19: 120 | CE19: 0 | CJ19: 45870 | CK19: 6 | CM19: #N/A | CN19: Garden | CO19: Seasonal | CP19: #N/A | CR19: 53 | CS19: -36 | CT19: 66.7 | CU19: 0 | CV19: 0
A20: Forecast | C20: 45870 | D20: TPS | E20: Amazon | F20: TPS Plant Foods | G20: 5-10-10 Fertilizer | H20: 1 Gallon | I20: 0 | J20: 0 | K20: TPS-5-10-10FERT-1GALLON | L20: B0FKSH6N7Y | M20: F.5-10-10 | N20: 4 | O20: 13x13x13 | P20: LBL-PLANT-488 | Q20: Berry Unvented | R20: Liquid | S20: 75 | T20: 0 | U20: 49.99 | V20: 0 | W20: FALSE | X20: FALSE | Y20: FALSE | Z20: FALSE | AB20: #N/A | AC20: 0 | AD20: 0 | AE20: 16 | AF20: 800 | AH20: 0 | AI20: 213 | AJ20: 81 | AK20: 567 | AL20: 224 | AM20: 0 | AN20: 0 | AO20: 0 | AP20: 0 | AQ20: 0 | AR20: 0 | AW20: 0 | AX20: 0 | AY20: 2 | AZ20: 6 | BA20: 9 | BB20: 16 | BC20: 0 | BD20: 0 | BE20: 0 | BF20: 0 | BG20: 0 | BJ20: 15 | BK20: 213 | BL20: Current | BM20: https://drive.google.com/file/d/1AHwQ4g_70dqAVmkFiUBr8GDQ7L-2_5xS/view?usp=drive_link | BN20: 5" x 8" | BP20: 0 | BQ20: 0 | BR20: 3397 | BT20: 4049 | BU20: 0 | BV20: 116 | BW20: 46030 | BY20: 32 | BZ20: 41 | CA20: 0 | CB20: 0 | CC20: 0 | CD20: 0 | CE20: 8 | CJ20: 45870 | CK20: 6 | CM20: #N/A | CN20: Garden | CO20: Seasonal | CP20: #N/A | CR20: 13 | CS20: -54 | CT20: 66.7 | CU20: 0 | CV20: 0
A21: Forecast | C21: 45870 | D21: TPS | E21: Amazon | F21: TPS Plant Foods | G21: 5-10-5 Fertilizer | H21: 8oz | I21: 0 | J21: 0 | K21: TPS-5-10-5FERT-8OZ | L21: B0FKSCB6RH | M21: F.5-10-5 | N21: 60 | O21: 12x10x12 | P21: LBL-PLANT-006 | Q21: Aptar Pour | R21: Liquid | S21: 75 | T21: 0 | U21: 11.99 | V21: 0 | W21: FALSE | X21: FALSE | Y21: FALSE | Z21: FALSE | AB21: #N/A | AC21: 0 | AD21: 0 | AE21: 60 | AF21: 719 | AH21: 0 | AI21: 776 | AJ21: 237 | AK21: 2413 | AL21: 580 | AM21: 0 | AN21: 0 | AO21: 0 | AP21: 0 | AQ21: 0 | AR21: 0 | AW21: 0 | AX21: 0 | AY21: 3 | AZ21: 3 | BA21: 3 | BB21: 6 | BC21: 0 | BD21: 0 | BE21: 0 | BF21: 0 | BG21: 0 | BJ21: 13 | BK21: 776 | BL21: Current | BM21: https://drive.google.com/file/d/11iR9jt_7x6LGPdpyT_QRWjSsvCOJtEJK/view?usp=drive_link | BN21: 5" x 8" | BP21: 0 | BQ21: 0 | BR21: 25333 | BT21: 2842 | BU21: 0 | BV21: 106 | BW21: 46041 | BY21: 57 | BZ21: 0 | CA21: 0 | CB21: 0 | CC21: 0 | CD21: 180 | CE21: 0 | CJ21: 45870 | CK21: 6 | CM21: #N/A | CN21: Garden | CO21: Seasonal | CP21: #N/A | CR21: 7 | CS21: -227 | CT21: 66.7 | CU21: 0 | CV21: 0
A22: Forecast | C22: 45870 | D22: TPS | E22: Amazon | F22: TPS Plant Foods | G22: 5-10-5 Fertilizer | H22: 1 Gallon | I22: 0 | J22: 0 | K22: TPS-5-10-5FERT-1GAL | L22: B0FKSWBYCT | M22: F.5-10-5 | N22: 4 | O22: 13x13x13 | P22: LBL-PLANT-489 | Q22: Berry Unvented | R22: Liquid | S22: 75 | T22: 0 | U22: 49.99 | V22: 0 | W22: FALSE | X22: FALSE | Y22: FALSE | Z22: FALSE | AB22: #N/A | AC22: 0 | AD22: 0 | AE22: 8 | AF22: 400 | AH22: 0 | AI22: 277 | AJ22: 23 | AK22: 483 | AL22: 147 | AM22: 0 | AN22: 0 | AO22: 0 | AP22: 0 | AQ22: 0 | AR22: 0 | AW22: 0 | AX22: 0 | AY22: 1 | AZ22: 2 | BA22: 2 | BB22: 2 | BC22: 0 | BD22: 0 | BE22: 0 | BF22: 0 | BG22: 0 | BJ22: 6 | BK22: 277 | BL22: Current | BM22: https://drive.google.com/file/d/11iR9jt_7x6LGPdpyT_QRWjSsvCOJtEJK/view?usp=drive_link | BN22: 5" x 8" | BP22: 0 | BQ22: 0 | BR22: 12876 | BT22: 1150 | BU22: 0 | BV22: 42 | BW22: 46043 | BY22: 7 | BZ22: 0 | CA22: 0 | CB22: 0 | CC22: 0 | CD22: 16 | CE22: 0 | CF22: 4 | CJ22: 45870 | CK22: 6 | CM22: #N/A | CN22: Garden | CO22: Seasonal | CP22: #N/A | CR22: 4 | CS22: -20 | CT22: 66.7 | CU22: 0 | CV22: 0
A23: Forecast | C23: 45870 | D23: TPS | E23: Amazon | F23: TPS Plant Foods | G23: 5-10-5 Fertilizer | H23: Quart | I23: 0 | J23: 0 | K23: TPS-5-10-5FERT-QUART | L23: B0FKT3R2DS | M23: F.5-10-5 | N23: 12 | O23: 13x10x10 | P23: LBL-PLANT-232 | Q23: Aptar Pour | R23: Liquid | S23: 75 | T23: 0 | U23: 24.99 | V23: 0 | W23: FALSE | X23: FALSE | Y23: FALSE | Z23: FALSE | AB23: #N/A | AC23: 0 | AD23: #VALUE! | AE23: No Sales | AF23: 0 | AH23: 0 | AI23: 388 | AJ23: 132 | AK23: NO SALES | AL23: NO SALES | AM23: 0 | AN23: 0 | AO23: 0 | AP23: 0 | AQ23: 0 | AR23: 0 | AW23: 0 | AX23: 0 | AY23: 0 | AZ23: 0 | BA23: 0 | BB23: 0 | BC23: 0 | BD23: 0 | BE23: 0 | BF23: 0 | BG23: 0 | BJ23: 0 | BK23: 388 | BL23: Current | BM23: https://drive.google.com/file/d/11iR9jt_7x6LGPdpyT_QRWjSsvCOJtEJK/view?usp=drive_link | BN23: 5" x 8" | BP23: 0 | BQ23: 0 | BR23: NO SALES | BT23: 3299 | BU23: 0 | BV23: 127 | BW23: 46042 | BY23: 36 | BZ23: 0 | CA23: 0 | CB23: 0 | CC23: 0 | CD23: 96 | CE23: 0 | CJ23: 45870 | CK23: 6 | CM23: #N/A | CN23: Garden | CO23: Seasonal | CP23: #N/A | CR23: No Sales | CS23: -132 | CT23: 66.7 | CU23: 0 | CV23: 0
A24: Forecast | C24: 45870 | D24: TPS | E24: Amazon | F24: TPS Plant Foods | G24: 5-5-5 Fertilizer | H24: 1 Gallon | I24: 0 | J24: 0 | K24: TPS-5-5-5FERTILIZER-1GAL | L24: B0FKSJ4JG2 | M24: F.5-5-5 | N24: 4 | O24: 13x13x13 | P24: LBL-PLANT-490 | Q24: Berry Unvented | R24: Liquid | S24: 75 | T24: 0 | U24: 39.99 | V24: 0 | W24: FALSE | X24: FALSE | Y24: FALSE | Z24: FALSE | AB24: #N/A | AC24: 0 | AD24: #VALUE! | AE24: No Sales | AF24: 0 | AH24: 0 | AI24: 269 | AJ24: 35 | AK24: NO SALES | AL24: NO SALES | AM24: 0 | AN24: 0 | AO24: 0 | AP24: 0 | AQ24: 0 | AR24: 0 | AW24: 0 | AX24: 0 | AY24: 0 | AZ24: 0 | BA24: 0 | BB24: 0 | BC24: 0 | BD24: 0 | BE24: 0 | BF24: 0 | BG24: 0 | BJ24: 0 | BK24: 269 | BL24: Current | BM24: https://drive.google.com/file/d/1U5eZgvbVmvNkEtQPTQBXJhBjgcU4dOTK/view?usp=drive_link | BN24: 5" x 8" | BP24: 0 | BQ24: #N/A | BR24: NO SALES | BT24: 1400 | BU24: 0 | BV24: 119 | BW24: 46043 | BY24: 11 | BZ24: 0 | CA24: 0 | CB24: 0 | CC24: 0 | CD24: 24 | CE24: 0 | CJ24: 45870 | CK24: 6 | CM24: #N/A | CN24: Garden | CO24: Seasonal | CP24: #N/A | CR24: No Sales | CS24: -35 | CT24: 66.7 | CU24: 0 | CV24: 0
A25: Forecast | C25: 45870 | D25: TPS | E25: Amazon | F25: TPS Plant Foods | G25: 5-5-5 fertilizer | H25: 8oz | I25: 0 | J25: 0 | K25: TPS-5-5-5FERTILIZER-8OZ | L25: B0FKSWG5VR | M25: F.5-5-5 | N25: 60 | O25: 12x10x12 | P25: LBL-PLANT-007 | Q25: Aptar Pour | R25: Liquid | S25: 75 | T25: 0 | U25: 11.99 | V25: 0 | W25: FALSE | X25: FALSE | Y25: FALSE | Z25: FALSE | AB25: #N/A | AC25: 0 | AD25: #VALUE! | AE25: No Sales | AF25: 0 | AH25: 0 | AI25: 820 | AJ25: 219 | AK25: NO SALES | AL25: NO SALES | AM25: 0 | AN25: 0 | AO25: 0 | AP25: 0 | AQ25: 0 | AR25: 0 | AW25: 0 | AX25: 0 | AY25: 0 | AZ25: 0 | BA25: 0 | BB25: 0 | BC25: 0 | BD25: 0 | BE25: 0 | BF25: 0 | BG25: 0 | BJ25: 0 | BK25: 820 | BL25: Current | BM25: https://drive.google.com/file/d/1U5eZgvbVmvNkEtQPTQBXJhBjgcU4dOTK/view?usp=drive_link | BN25: 5" x 8" | BP25: 0 | BQ25: #N/A | BR25: NO SALES | BT25: 2626 | BU25: 0 | BV25: 42 | BW25: 46041 | BY25: 32 | BZ25: 7 | CA25: 0 | CB25: 0 | CC25: 0 | CD25: 180 | CE25: 0 | CJ25: 45870 | CK25: 6 | CM25: #N/A | CN25: Garden | CO25: Seasonal | CP25: #N/A | CR25: No Sales | CS25: -219 | CT25: 66.7 | CU25: 0 | CV25: 0
A26: Forecast | C26: 45870 | D26: TPS | E26: Amazon | F26: TPS Plant Foods | G26: 5-5-5 fertilizer | H26: Quart | I26: 0 | J26: 0 | K26: TPS-5-5-5FERTILIZER-QUART | L26: B0FKS85TJP | M26: F.5-5-5 | N26: 12 | O26: 13x10x10 | P26: LBL-PLANT-233 | Q26: Aptar Pour | R26: Liquid | S26: 75 | T26: 0 | U26: 24.99 | V26: 0 | W26: FALSE | X26: FALSE | Y26: FALSE | Z26: FALSE | AB26: #N/A | AC26: 0 | AD26: #VALUE! | AE26: No Sales | AF26: 0 | AH26: 0 | AI26: 443 | AJ26: 72 | AK26: NO SALES | AL26: NO SALES | AM26: 0 | AN26: 0 | AO26: 0 | AP26: 0 | AQ26: 0 | AR26: 0 | AW26: 0 | AX26: 0 | AY26: 0 | AZ26: 0 | BA26: 0 | BB26: 0 | BC26: 0 | BD26: 0 | BE26: 0 | BF26: 0 | BG26: 0 | BJ26: 0 | BK26: 443 | BL26: Current | BM26: https://drive.google.com/file/d/1U5eZgvbVmvNkEtQPTQBXJhBjgcU4dOTK/view?usp=drive_link | BN26: 5" x 8" | BP26: 0 | BQ26: #N/A | BR26: NO SALES | BT26: 1799 | BU26: 0 | BV26: 135 | BW26: 46042 | BY26: 24 | BZ26: 0 | CA26: 0 | CB26: 0 | CC26: 0 | CD26: 48 | CE26: 0 | CJ26: 45870 | CK26: 6 | CM26: #N/A | CN26: Garden | CO26: Seasonal | CP26: #N/A | CR26: No Sales | CS26: -72 | CT26: 66.7 | CU26: 0 | CV26: 0
A27: Forecast | C27: 45870 | D27: TPS | E27: Amazon | F27: TPS Plant Foods | G27: 7-7-7 Fertilizer | H27: 1 Gallon | I27: 0 | J27: 0 | K27: TPS-7-7-7FERT-1GALLON | L27: B0FKSL8XQ8 | M27: F.8-8-8 | N27: 4 | O27: 13x13x13 | P27: LBL-PLANT-491 | Q27: Berry Unvented | R27: Liquid | S27: 75 | T27: 0 | U27: 49.99 | V27: 0 | W27: FALSE | X27: FALSE | Y27: FALSE | Z27: FALSE | AB27: #N/A | AC27: 0 | AD27: 0 | AE27: 4 | AF27: 200 | AH27: 0 | AI27: 208 | AJ27: 90 | AK27: 1779 | AL27: 296 | AM27: 0 | AN27: 0 | AO27: 0 | AP27: 0 | AQ27: 0 | AR27: 0 | AW27: 0 | AX27: 0 | AY27: 1 | AZ27: 1 | BA27: 4 | BB27: 6 | BC27: 0 | BD27: 0 | BE27: 0 | BF27: 0 | BG27: 0 | BJ27: 5 | BK27: 208 | BL27: Current | BM27: https://drive.google.com/file/d/1WbNtYLKkm39rDwsFYF4rPeGhz3VDyFt8/view?usp=drive_link | BN27: 5" x 8" | BP27: 0 | BQ27: 0 | BR27: 14923 | BT27: 4499 | BU27: 0 | BV27: 241 | BW27: 46042 | BY27: 15 | BZ27: 39 | CA27: 0 | CB27: 0 | CC27: 0 | CD27: 36 | CE27: 0 | CJ27: 45870 | CK27: 6 | CM27: #N/A | CN27: Garden | CO27: Seasonal | CP27: #N/A | CR27: 2 | CS27: -80 | CT27: 66.7 | CU27: 0 | CV27: 0
A28: Forecast | C28: 45870 | D28: TPS | E28: Amazon | F28: TPS Plant Foods | G28: 7-7-7 Fertilizer | H28: 8oz | I28: 0 | J28: 0 | K28: TPS-7-7-7FERT-8OZ | L28: B0FKSFPF2R | M28: F.8-8-8 | N28: 60 | O28: 12x10x12 | P28: LBL-PLANT-008 | Q28: Aptar Pour | R28: Liquid | S28: 75 | T28: 0 | U28: 11.99 | V28: 0 | W28: FALSE | X28: FALSE | Y28: FALSE | Z28: FALSE | AB28: #N/A | AC28: 0 | AD28: #VALUE! | AE28: No Sales | AF28: 0 | AH28: 0 | AI28: 782 | AJ28: 240 | AK28: NO SALES | AL28: NO SALES | AM28: 0 | AN28: 0 | AO28: 0 | AP28: 0 | AQ28: 0 | AR28: 0 | AW28: 0 | AX28: 0 | AY28: 0 | AZ28: 0 | BA28: 0 | BB28: 0 | BC28: 0 | BD28: 0 | BE28: 0 | BF28: 0 | BG28: 0 | BJ28: 0 | BK28: 782 | BL28: Current | BM28: https://drive.google.com/file/d/1WbNtYLKkm39rDwsFYF4rPeGhz3VDyFt8/view?usp=drive_link | BN28: 5" x 8" | BP28: 0 | BQ28: 0 | BR28: NO SALES | BT28: 2878 | BU28: 0 | BV28: 0 | BW28: 46041 | BY28: 60 | BZ28: 0 | CA28: 0 | CB28: 0 | CC28: 0 | CD28: 180 | CE28: 0 | CJ28: 45870 | CK28: 6 | CM28: #N/A | CN28: Garden | CO28: Seasonal | CP28: #N/A | CR28: No Sales | CS28: -240 | CT28: 66.7 | CU28: 0 | CV28: 0
A29: Forecast | C29: 45870 | D29: TPS | E29: Amazon | F29: TPS Plant Foods | G29: 7-7-7 Fertilizer | H29: Quart | I29: 0 | J29: 0 | K29: TPS-7-7-7FERT-QUART | L29: B0FKT3RRQ2 | M29: F.8-8-8 | N29: 12 | O29: 13x10x10 | P29: LBL-PLANT-234 | Q29: Aptar Pour | R29: Liquid | S29: 75 | T29: 0 | U29: 24.99 | V29: 0 | W29: FALSE | X29: FALSE | Y29: FALSE | Z29: FALSE | AB29: #N/A | AC29: 0 | AD29: #VALUE! | AE29: No Sales | AF29: 0 | AH29: 0 | AI29: 435 | AJ29: 84 | AK29: NO SALES | AL29: NO SALES | AM29: 0 | AN29: 0 | AO29: 0 | AP29: 0 | AQ29: 0 | AR29: 0 | AW29: 0 | AX29: 0 | AY29: 0 | AZ29: 0 | BA29: 0 | BB29: 0 | BC29: 0 | BD29: 0 | BE29: 0 | BF29: 0 | BG29: 0 | BJ29: 0 | BK29: 435 | BL29: Current | BM29: https://drive.google.com/file/d/1WbNtYLKkm39rDwsFYF4rPeGhz3VDyFt8/view?usp=drive_link | BN29: 5" x 8" | BP29: 0 | BQ29: 0 | BR29: NO SALES | BT29: 2099 | BU29: 0 | BV29: 0 | BW29: 46042 | BY29: 36 | BZ29: 0 | CA29: 0 | CB29: 0 | CC29: 0 | CD29: 48 | CE29: 0 | CJ29: 45870 | CK29: 6 | CM29: #N/A | CN29: Garden | CO29: Seasonal | CP29: #N/A | CR29: No Sales | CS29: -84 | CT29: 66.7 | CU29: 0 | CV29: 0
A30: Forecast | C30: 45870 | D30: TPS | E30: Amazon | F30: TPS Plant Foods | G30: 8-8-8 fertilizer | H30: Quart | I30: 0 | J30: 0 | K30: TPS-8-8-8FERT-QUART | L30: B0FKSYTZBJ | M30: F.8-8-8 | N30: 12 | O30: 13x10x10 | P30: LBL-PLANT-235 | Q30: Aptar Pour | R30: Liquid | S30: 75 | T30: 0 | U30: 24.99 | V30: 0 | W30: FALSE | X30: FALSE | Y30: FALSE | Z30: FALSE | AB30: #N/A | AC30: 0 | AD30: 0 | AE30: No Sales | AF30: 0 | AH30: 0 | AI30: 391 | AJ30: 131 | AK30: 22008 | AL30: 5880 | AM30: 0 | AN30: 0 | AO30: 0 | AP30: 0 | AQ30: 0 | AR30: 0 | AW30: 0 | AX30: 0 | AY30: 0 | AZ30: 0 | BA30: 1 | BB30: 1 | BC30: 0 | BD30: 0 | BE30: 0 | BF30: 0 | BG30: 0 | BJ30: 0 | BK30: 391 | BL30: Current | BM30: https://drive.google.com/file/d/1bKMPptO4VQdWhMYrdyvZ5jQqzJtIcs9T/view?usp=drive_link | BN30: 5" x 8" | BP30: 0 | BQ30: 0 | BR30: 313333 | BT30: 3274 | BU30: 0 | BV30: 127 | BW30: 46042 | BY30: 35 | BZ30: 0 | CA30: 0 | CB30: 0 | CC30: 0 | CD30: 96 | CE30: 0 | CJ30: 45870 | CK30: 6 | CM30: #N/A | CN30: Garden | CO30: Seasonal | CP30: #N/A | CR30: No Sales | CS30: -129 | CT30: 66.7 | CU30: 0 | CV30: 0
A31: Forecast | C31: 45870 | D31: TPS | E31: Amazon | F31: TPS Plant Foods | G31: 8-8-8 fertilizer | H31: 1 Gallon | I31: 0 | J31: 0 | K31: TPS-8-8-8FERT-1GALLON | L31: B0FKSFH249 | M31: F.8-8-8 | N31: 4 | O31: 13x13x13 | P31: LBL-PLANT-492 | Q31: Berry Unvented | R31: Liquid | S31: 75 | T31: 0 | U31: 49.99 | V31: 0 | W31: FALSE | X31: FALSE | Y31: FALSE | Z31: FALSE | AB31: #N/A | AC31: 0 | AD31: #VALUE! | AE31: No Sales | AF31: 0 | AH31: 0 | AI31: 293 | AJ31: 12 | AK31: NO SALES | AL31: NO SALES | AM31: 0 | AN31: 0 | AO31: 0 | AP31: 0 | AQ31: 0 | AR31: 0 | AW31: 0 | AX31: 0 | AY31: 0 | AZ31: 0 | BA31: 0 | BB31: 0 | BC31: 0 | BD31: 0 | BE31: 0 | BF31: 0 | BG31: 0 | BJ31: 0 | BK31: 293 | BL31: Current | BM31: https://drive.google.com/file/d/1bKMPptO4VQdWhMYrdyvZ5jQqzJtIcs9T/view?usp=drive_link | BN31: 5" x 8" | BP31: 0 | BQ31: 0 | BR31: NO SALES | BT31: 600 | BU31: 0 | BV31: 0 | BW31: 45946 | BY31: 12 | BZ31: 0 | CA31: 0 | CB31: 0 | CC31: 0 | CD31: 0 | CE31: 0 | CJ31: 45870 | CK31: 6 | CM31: #N/A | CN31: Garden | CO31: Seasonal | CP31: #N/A | CR31: No Sales | CS31: -12 | CT31: 66.7 | CU31: 0 | CV31: 0
A32: Forecast | C32: 45870 | D32: TPS | E32: Amazon | F32: TPS Plant Foods | G32: 8-8-8 fertilizer | H32: 8oz | I32: 0 | J32: 0 | K32: TPS-8-8-8FERT-8OZ | L32: B0FKS81ZNW | M32: F.8-8-8 | N32: 60 | O32: 12x10x12 | P32: LBL-PLANT-009 | Q32: Aptar Pour | R32: Liquid | S32: 75 | T32: 0 | U32: 11.99 | V32: 0 | W32: FALSE | X32: FALSE | Y32: FALSE | Z32: FALSE | AB32: #N/A | AC32: 0 | AD32: #VALUE! | AE32: No Sales | AF32: 0 | AH32: 0 | AI32: 777 | AJ32: 240 | AK32: NO SALES | AL32: NO SALES | AM32: 0 | AN32: 0 | AO32: 0 | AP32: 0 | AQ32: 0 | AR32: 0 | AW32: 0 | AX32: 0 | AY32: 0 | AZ32: 0 | BA32: 0 | BB32: 0 | BC32: 0 | BD32: 0 | BE32: 0 | BF32: 0 | BG32: 0 | BJ32: 0 | BK32: 777 | BL32: Current | BM32: https://drive.google.com/file/d/1bKMPptO4VQdWhMYrdyvZ5jQqzJtIcs9T/view?usp=drive_link | BN32: 5" x 8" | BP32: 0 | BQ32: 0 | BR32: NO SALES | BT32: 2878 | BU32: 0 | BV32: 136 | BW32: 46041 | BY32: 60 | BZ32: 0 | CA32: 0 | CB32: 0 | CC32: 0 | CD32: 180 | CE32: 0 | CJ32: 45870 | CK32: 6 | CM32: #N/A | CN32: Garden | CO32: Seasonal | CP32: #N/A | CR32: No Sales | CS32: -240 | CT32: 66.7 | CU32: 0 | CV32: 0
A33: Forecast | D33: TPS | E33: Amazon | F33: Bloom City | G33: Acid Loving Plants | H33: Quart | I33: 0 | J33: 0 | K33: BACIDLOVING1Q-0224 | L33: B0C4ZW6QQP | M33: F.Tomato Veggie | N33: 12 | O33: 13x13x10 | P33: LBL-PLANT-464 | Q33: VENTED Berry | R33: Liquid | S33: 150 | T33: 0 | U33: 24.99 | V33: 0 | W33: FALSE | X33: FALSE | Y33: FALSE | Z33: FALSE | AB33: 0 | AC33: 0 | AD33: 0 | AE33: 96 | AF33: 2399 | AH33: 0 | AI33: 1196 | AJ33: 361 | AK33: 292 | AL33: 100 | AM33: 17 | AN33: 0 | AO33: 0 | AP33: 0 | AQ33: 0 | AR33: 0 | AW33: 0 | AX33: 0 | AY33: 29 | AZ33: 42 | BA33: 58 | BB33: 202 | BC33: 152 | BD33: 50 | BE33: 105 | BF33: 321 | BG33: 232 | BJ33: 148 | BK33: 1196 | BL33: Current | BM33: https://drive.google.com/open?id=1v8Pdw5RZxgLrNWi4jukYeYf-w9BAkKxh&usp=drive_fs | BN33: 5" x 8" | BP33: 0 | BQ33: Established | BR33: 2058 | BT33: 9021 | BU33: 0 | BV33: 45 | BW33: 45875 | BX33: 720 | BY33: 124 | BZ33: 33 | CA33: 0 | CB33: 204 | CC33: 0 | CD33: 0 | CE33: 0 | CJ33: 45108 | CK33: 31 | CL33: No | CM33: Established | CN33: Garden | CO33: Seasonal | CP33: 0 | CQ33: 0 | CR33: 93 | CS33: -147 | CT33: 66.7 | CU33: 0 | CV33: 0
A34: Forecast | D34: TPS | E34: Amazon | F34: Bloom City | G34: Acid Loving Plants | H34: 1 Gallon | I34: 0 | J34: 0 | K34: BACIDLOVING1G-0224 | L34: B0BZB814JM | M34: F.Tomato Veggie | N34: 4 | O34: 13x13x13 | P34: LBL-PLANT-641 | Q34: VENTED Berry | R34: Liquid | S34: 150 | T34: 0 | V34: 0 | W34: FALSE | X34: FALSE | Y34: FALSE | Z34: FALSE | AB34: 0 | AC34: 0 | AD34: 0 | AE34: 16 | AF34: 0 | AH34: 0 | AI34: 469 | AJ34: 123 | AK34: 498 | AL34: 117 | AM34: 18 | AN34: 0 | AO34: 8 | AP34: 0 | AQ34: 0 | AR34: 0 | AW34: 0 | AX34: 0 | AY34: 6 | AZ34: 7 | BA34: 13 | BB34: 27 | BC34: 26 | BD34: 15 | BE34: 28 | BF34: 49 | BG34: 42 | BJ34: 29 | BK34: 469 | BL34: Current | BM34: https://drive.google.com/open?id=1v8Pdw5RZxgLrNWi4jukYeYf-w9BAkKxh&usp=drive_fs | BN34: 5" x 8" | BP34: 0 | BQ34: Established | BR34: 5150 | BT34: 0 | BU34: 0 | BV34: 0 | BW34: 45974 | BX34: 100 | BY34: 29 | BZ34: 6 | CA34: 8 | CB34: 72 | CC34: 0 | CD34: 0 | CE34: 8 | CJ34: 45108 | CK34: 31 | CL34: Yes | CM34: Established | CN34: Garden | CO34: Seasonal | CP34: 0 | CQ34: 0 | CR34: 16 | CS34: -90 | CT34: 66.7 | CU34: 0 | CV34: 0
A35: Forecast | C35: 45870 | D35: TPS | E35: Amazon | F35: TPS Plant Foods | G35: Acidic Fertilizer | H35: 8oz | I35: 0 | J35: 0 | K35: TPS-ACIDICFERT-8OZ | L35: B0FKSZ2261 | M35: F.Ultra Bloom | N35: 60 | O35: 12x10x12 | P35: LBL-PLANT-010 | Q35: Aptar Pour | R35: Liquid | S35: 75 | T35: 0 | U35: 11.99 | V35: 0 | W35: FALSE | X35: FALSE | Y35: FALSE | Z35: FALSE | AB35: #N/A | AC35: 0 | AD35: #VALUE! | AE35: 120 | AF35: 1439 | AH35: 0 | AI35: 419 | AJ35: 540 | AK35: 965 | AL35: SOLD OUT | AM35: 0 | AN35: 0 | AO35: 0 | AP35: 0 | AQ35: 0 | AR35: 0 | AW35: 0 | AX35: 0 | AY35: 1 | AZ35: 34 | BA35: 40 | BB35: 50 | BC35: 0 | BD35: 0 | BE35: 0 | BF35: 0 | BG35: 0 | BJ35: 50 | BK35: 419 | BL35: Current | BM35: https://drive.google.com/file/d/1Of2Tz3LkTV8WqEEZR0Q9VnsT5pGWqsSf/view?usp=drive_link | BN35: 5" x 8" | BP35: 0 | BQ35: 0 | BR35: 2266 | BT35: 6475 | BU35: 0 | BV35: 0 | BW35: 46048 | BY35: 0 | BZ35: 0 | CA35: 0 | CB35: 0 | CC35: 0 | CD35: 540 | CE35: 0 | CJ35: 45870 | CK35: 6 | CM35: #N/A | CN35: Garden | CO35: Seasonal | CP35: #N/A | CR35: 76 | CS35: -455 | CT35: 66.7 | CU35: 0 | CV35: 0
A36: Forecast | C36: 45870 | D36: TPS | E36: Amazon | F36: TPS Plant Foods | G36: Acidic Fertilizer | H36: 1 Gallon | I36: 0 | J36: 0 | K36: TPS-ACIDICFERT-1GALLON | L36: B0FKSQK91K | M36: F.Ultra Bloom | N36: 4 | O36: 13x13x13 | P36: LBL-PLANT-493 | Q36: Berry Unvented | R36: Liquid | S36: 75 | T36: 0 | U36: 49.99 | V36: 0 | W36: FALSE | X36: FALSE | Y36: FALSE | Z36: FALSE | AB36: #N/A | AC36: 0 | AD36: 0 | AE36: 4 | AF36: 200 | AH36: 0 | AI36: 176 | AJ36: 53 | AK36: 1619 | AL36: 275 | AM36: 0 | AN36: 0 | AO36: -4 | AP36: 0 | AQ36: 0 | AR36: 0 | AW36: 0 | AX36: 0 | AY36: 1 | AZ36: 1 | BA36: 1 | BB36: 3 | BC36: 0 | BD36: 0 | BE36: 0 | BF36: 0 | BG36: 0 | BJ36: 4 | BK36: 176 | BL36: Current | BM36: https://drive.google.com/file/d/1Of2Tz3LkTV8WqEEZR0Q9VnsT5pGWqsSf/view?usp=drive_link | BN36: 5" x 8" | BP36: 0 | BQ36: 0 | BR36: 15282 | BT36: 2649 | BU36: 0 | BV36: 95 | BW36: 46049 | BY36: 9 | BZ36: 0 | CA36: -4 | CB36: 0 | CC36: 0 | CD36: 48 | CE36: 0 | CG36: 4 | CJ36: 45870 | CK36: 6 | CM36: #N/A | CN36: Garden | CO36: Seasonal | CP36: #N/A | CR36: 2 | CS36: -48 | CT36: 66.7 | CU36: 0 | CV36: 0
A37: Forecast | C37: 45870 | D37: TPS | E37: Amazon | F37: TPS Plant Foods | G37: Acidic Fertilizer | H37: Quart | I37: 0 | J37: 0 | K37: TPS-ACIDICFERT-QUART | L37: B0FKSSDRX9 | M37: F.Ultra Bloom | N37: 12 | O37: 13x10x10 | P37: LBL-PLANT-236 | Q37: Aptar Pour | R37: Liquid | S37: 75 | T37: 0 | U37: 24.99 | V37: 0 | W37: FALSE | X37: FALSE | Y37: FALSE | Z37: FALSE | AB37: #N/A | AC37: 0 | AD37: 0 | AE37: 12 | AF37: 300 | AH37: 0 | AI37: 469 | AJ37: 18 | AK37: 1210 | AL37: 1210 | AM37: 0 | AN37: 0 | AO37: 0 | AP37: 0 | AQ37: 0 | AR37: 0 | AW37: 0 | AX37: 0 | AY37: 0 | AZ37: 1 | BA37: 1 | BB37: 2 | BC37: 0 | BD37: 0 | BE37: 0 | BF37: 0 | BG37: 0 | BJ37: 1 | BK37: 469 | BL37: Current | BM37: https://drive.google.com/file/d/1Of2Tz3LkTV8WqEEZR0Q9VnsT5pGWqsSf/view?usp=drive_link | BN37: 5" x 8" | BP37: 0 | BQ37: 0 | BR37: 36542 | BT37: 450 | BU37: 0 | BV37: 164 | BW37: 45875 | BY37: 18 | BZ37: 0 | CA37: 0 | CB37: 0 | CC37: 0 | CD37: 0 | CE37: 0 | CJ37: 45870 | CK37: 6 | CM37: #N/A | CN37: Garden | CO37: Seasonal | CP37: #N/A | CR37: 2 | CS37: -15 | CT37: 66.7 | CU37: 0 | CV37: 0
A38: Forecast | D38: TPS | E38: Amazon | F38: TPS Plant Foods | G38: African Violet Fertilizer | H38: 8oz | I38: 0 | J38: 0 | K38: AFVIOLET8OZ-FBA-UPC-0523 | L38: B0C73TS2P2 | M38: F.Succulent | N38: 60 | O38: 12x10x12 | P38: LBL-PLANT-011 | Q38: Aptar Pour | R38: Liquid | S38: 75 | T38: 0 | U38: 11.99 | V38: 0 | W38: FALSE | X38: FALSE | Y38: FALSE | Z38: FALSE | AB38: 720 | AC38: 0 | AD38: 0 | AE38: 300 | AF38: 3597 | AH38: 0 | AI38: 302 | AJ38: 1551 | AK38: 363 | AL38: 61 | AM38: 0 | AN38: 0 | AO38: 120 | AP38: 0 | AQ38: 0 | AR38: 0 | AW38: 0 | AX38: 0 | AY38: 97 | AZ38: 140 | BA38: 217 | BB38: 615 | BC38: 576 | BD38: 695 | BE38: 899 | BF38: 1057 | BG38: 1051 | BJ38: 503 | BK38: 302 | BL38: Critical Changes Made | BM38: https://drive.google.com/open?id=1JnGu0H9zRaRnzreYoWN4Wp78L8BT6Z4o&usp=drive_fs | BN38: 5" x 8" | BP38: 0 | BQ38: Established | BR38: 764 | BT38: 18596 | BU38: 0 | BV38: 56 | BW38: 46034 | BX38: 1080 | BY38: 259 | BZ38: 32 | CA38: 120 | CB38: 0 | CC38: 60 | CD38: 1080 | CE38: 0 | CJ38: 45108 | CK38: 31 | CL38: No | CM38: Established | CN38: Houseplant | CO38: Flat | CP38: 719 | CQ38: 0 | CR38: 275 | CS38: -254 | CT38: 59 | CU38: 0 | CV38: 0
A39: Forecast | D39: TPS | E39: Amazon | F39: TPS Plant Foods | G39: African Violet Fertilizer | H39: Quart | I39: 0 | J39: 0 | K39: AFVIOLET1Q-FBA-UPC-0523 | L39: B0C73RC4V9 | M39: F.Succulent | N39: 12 | O39: 13x13x10 | P39: LBL-PLANT-237 | Q39: Aptar Pour | R39: Liquid | S39: 75 | T39: 0 | U39: 24.99 | V39: 0 | W39: FALSE | X39: FALSE | Y39: FALSE | Z39: FALSE | AB39: 0 | AC39: 0 | AD39: 0 | AE39: 12 | AF39: 300 | AH39: 0 | AI39: 959 | AJ39: 196 | AK39: 1291 | AL39: 488 | AM39: 10 | AN39: 0 | AO39: 0 | AP39: 0 | AQ39: 0 | AR39: 0 | AW39: 0 | AX39: 0 | AY39: 4 | AZ39: 5 | BA39: 6 | BB39: 31 | BC39: 89 | BD39: 87 | BE39: 33 | BF39: 22 | BG39: 39 | BJ39: 19 | BK39: 959 | BL39: Critical Changes Made | BM39: https://drive.google.com/open?id=1JnGu0H9zRaRnzreYoWN4Wp78L8BT6Z4o&usp=drive_fs | BN39: 5" x 8" | BP39: 0 | BQ39: Established | BR39: 11363 | BT39: 4898 | BU39: 0 | BV39: 0 | BY39: 74 | BZ39: 2 | CA39: 0 | CB39: 120 | CC39: 0 | CD39: 0 | CE39: 0 | CJ39: 45108 | CK39: 31 | CL39: No | CM39: Established | CN39: Houseplant | CO39: Flat | CP39: 0 | CQ39: 0 | CR39: 10 | CS39: -180 | CT39: 59 | CU39: 0 | CV39: 0
A40: Forecast | D40: TPS | E40: Amazon | F40: TPS Plant Foods | G40: African Violet Fertilizer | H40: 1 Gallon | I40: 0 | J40: 0 | K40: AFVIOLET1G-FBA-UPC-0523 | L40: B0C73TDLPX | M40: F.Succulent | N40: 4 | O40: 13x13x13 | P40: LBL-PLANT-494 | Q40: Berry Unvented | R40: Liquid | S40: 75 | T40: 0 | U40: 59.99 | V40: 0 | W40: FALSE | X40: FALSE | Y40: FALSE | Z40: FALSE | AB40: 4 | AC40: 0 | AD40: #DIV/0! | AE40: No Sales | AF40: 0 | AH40: 0 | AI40: 245 | AJ40: 10 | AK40: NO SALES | AL40: #DIV/0! | AM40: 0 | AN40: #DIV/0! | AO40: 0 | AP40: 0 | AQ40: 0 | AR40: 0 | AW40: 0 | AX40: 0 | AY40: 0 | AZ40: 0 | BA40: 0 | BB40: 1 | BC40: 5 | BD40: 0 | BE40: 2 | BF40: 1 | BG40: 1 | BJ40: 0 | BK40: 245 | BL40: Critical Changes Made | BM40: https://drive.google.com/open?id=1JnGu0H9zRaRnzreYoWN4Wp78L8BT6Z4o&usp=drive_fs | BN40: 5" x 8" | BP40: 0 | BQ40: Established | BR40: 153176 | BT40: 600 | BU40: 0 | BV40: 0 | BW40: 45945 | BX40: 12 | BY40: 10 | BZ40: 0 | CA40: 0 | CB40: 0 | CC40: 0 | CD40: 0 | CE40: 0 | CJ40: 45108 | CK40: 31 | CL40: No | CM40: Established | CN40: Houseplant | CO40: Flat | CP40: 1 | CQ40: 0 | CR40: No Sales | CS40: -9 | CT40: 59 | CU40: 0 | CV40: 0
A41: Forecast | D41: TPS | E41: Amazon | F41: TPS Plant Foods | G41: Air Plant Fertilizer | H41: 8oz | I41: 0 | J41: 0 | K41: AIRPLANT8OZ-FBA-UPC-0523 | L41: B0C6R6KQSZ | M41: F.Succulent | N41: 60 | O41: 12x10x12 | P41: LBL-HV-057 | Q41: Aptar Pour | R41: Liquid | S41: 75 | T41: 0 | U41: 11.99 | V41: 0 | W41: FALSE | X41: FALSE | Y41: FALSE | Z41: FALSE | AB41: 1380 | AC41: 0 | AD41: 0 | AE41: 420 | AF41: 5036 | AH41: 0 | AI41: 2047 | AJ41: 798 | AK41: 145 | AL41: 110 | AM41: 0 | AN41: 0 | AO41: 1 | AP41: 0 | AQ41: 0 | AR41: 0 | AW41: 0 | AX41: 0 | AY41: 115 | AZ41: 186 | BA41: 298 | BB41: 876 | BC41: 616 | BD41: 1065 | BE41: 1095 | BF41: 840 | BG41: 763 | BJ41: 630 | BK41: 2047 | BL41: Critical Changes Made | BM41: https://drive.google.com/open?id=1H5RWSEELmgoI5vHUBrTqNa5b8Re6E8PC&usp=drive_fs | BN41: 5" x 8" | BP41: 0 | BQ41: Established | BR41: 857 | BT41: 9568 | BU41: 0 | BV41: 67 | BW41: 45966 | BX41: 720 | BY41: 604 | BZ41: 132 | CA41: 1 | CB41: 0 | CC41: 0 | CD41: 60 | CE41: 1 | CJ41: 45108 | CK41: 31 | CL41: No | CM41: Established | CN41: Houseplant | CO41: Flat | CP41: 1330 | CQ41: 0 | CR41: 366 | CS41: 794 | CT41: 59 | CU41: 297 | CV41: 0
A42: Forecast | D42: TPS | E42: Amazon | F42: TPS Plant Foods | G42: Air Plant Fertilizer | H42: Quart | I42: 0 | J42: 0 | K42: AIRPLANT1Q-FBA-UPC-0523 | L42: B0C6R6RL7B | M42: F.Succulent | N42: 12 | O42: 13x13x10 | P42: LBL-PLANT-238 | Q42: Aptar Pour | R42: Liquid | S42: 75 | T42: 0 | U42: 24.99 | V42: 0 | W42: FALSE | X42: FALSE | Y42: FALSE | Z42: FALSE | AB42: 156 | AC42: 0 | AD42: 0 | AE42: 48 | AF42: 1200 | AH42: 0 | AI42: 924 | AJ42: 152 | AK42: 247 | AL42: 62 | AM42: 5 | AN42: 0 | AO42: 2 | AP42: 0 | AQ42: 0 | AR42: 0 | AW42: 0 | AX42: 0 | AY42: 14 | AZ42: 21 | BA42: 30 | BB42: 99 | BC42: 93 | BD42: 185 | BE42: 118 | BF42: 90 | BG42: 88 | BJ42: 73 | BK42: 924 | BL42: Critical Changes Made | BM42: https://drive.google.com/open?id=1H5RWSEELmgoI5vHUBrTqNa5b8Re6E8PC&usp=drive_fs | BN42: 5" x 8" | BP42: 0 | BQ42: Established | BR42: 2868 | BT42: 3798 | BU42: 0 | BV42: 63 | BW42: 45986 | BX42: 132 | BY42: 38 | BZ42: 28 | CA42: 2 | CB42: 60 | CC42: 0 | CD42: 0 | CE42: 24 | CJ42: 45108 | CK42: 31 | CL42: No | CM42: Established | CN42: Houseplant | CO42: Flat | CP42: 154 | CQ42: 0 | CR42: 41 | CS42: 9 | CT42: 59 | CU42: 0 | CV42: 0
A43: Forecast | D43: TPS | E43: Amazon | F43: TPS Plant Foods | G43: Air Plant Fertilizer | H43: 1 Gallon | I43: 0 | J43: 0 | K43: AIRPLANT1G-FBA-UPC-0523 | L43: B0C6R6J9WW | M43: F.Succulent | N43: 4 | O43: 13x13x13 | P43: LBL-PLANT-495 | Q43: Berry Unvented | R43: Liquid | S43: 75 | T43: 0 | U43: 59.99 | V43: 0 | W43: FALSE | X43: FALSE | Y43: FALSE | Z43: FALSE | AB43: 12 | AC43: 0 | AD43: 0 | AE43: 8 | AF43: 480 | AH43: 0 | AI43: 181 | AJ43: 28 | AK43: 303 | AL43: 238 | AM43: 8 | AN43: 0 | AO43: 0 | AP43: 0 | AQ43: 0 | AR43: 0 | AW43: 0 | AX43: 0 | AY43: 2 | AZ43: 3 | BA43: 5 | BB43: 17 | BC43: 1 | BD43: 0 | BE43: 3 | BF43: 10 | BG43: 4 | BJ43: 11 | BK43: 181 | BL43: Critical Changes Made | BM43: https://drive.google.com/open?id=1H5RWSEELmgoI5vHUBrTqNa5b8Re6E8PC&usp=drive_fs | BN43: 5" x 8" | BP43: 0 | BQ43: Established | BR43: 3582 | BT43: 1680 | BU43: 0 | BV43: 179 | BW43: 45958 | BX43: 32 | BY43: 22 | BZ43: 2 | CA43: 0 | CB43: 8 | CC43: 0 | CD43: -4 | CE43: 0 | CF43: 4 | CJ43: 45108 | CK43: 31 | CL43: No | CM43: Established | CN43: Houseplant | CO43: Flat | CP43: 11 | CQ43: 0 | CR43: 6 | CS43: -22 | CT43: 59 | CU43: 0 | CV43: 0
A44: Forecast | C44: 45870 | D44: TPS | E44: Amazon | F44: TPS Plant Foods | G44: Air Plant Fertilizer Spray | H44: 16oz Round Spray White | I44: 0 | J44: 0 | K44: TPS-AIRPLANTSPRAY-16OZ | L44: B0FLWTJ4XT | M44: F.Plant Spray | N44: 25 | O44: 13x13x10 | P44: LBL-PLANT-663 | Q44: 16oz Trigger No-Foam | R44: Liquid | S44: 75 | T44: 0 | U44: 11.99 | V44: 0 | W44: FALSE | X44: FALSE | Y44: FALSE | Z44: FALSE | AB44: #N/A | AC44: 0 | AD44: 0 | AE44: 25 | AF44: 300 | AH44: 0 | AI44: 773 | AJ44: 183 | AK44: 436 | AL44: 122 | AM44: 25 | AN44: 0 | AO44: 0 | AP44: 0 | AQ44: 0 | AR44: 0 | AW44: 0 | AX44: 0 | AY44: 11 | AZ44: 11 | BA44: 21 | BB44: 61 | BC44: 0 | BD44: 0 | BE44: 0 | BF44: 0 | BG44: 0 | BJ44: 51 | BK44: 773 | BL44: Current | BM44: https://drive.google.com/file/d/10_HPcK5pk5BT8NHUy8oRsevsCZyP3UHp/view?usp=drive_link | BN44: 7.5" x 6" | BP44: 0 | BQ44: 0 | BR44: 4516 | BT44: 2194 | BU44: 0 | BV44: 54 | BW44: 46050 | BY44: 51 | BZ44: 7 | CA44: 0 | CB44: 25 | CC44: 0 | CD44: 100 | CE44: 0 | CJ44: 45870 | CK44: 6 | CM44: #N/A | CN44: Garden | CO44: Seasonal | CP44: #N/A | CR44: 24 | CS44: -79 | CT44: 66.7 | CU44: 0 | CV44: 0
A45: Forecast | C45: 46096 | D45: TPS | E45: Amazon | F45: TPS Plant Foods | G45: Air Plant Fertilizer Spray | H45: 16oz | M45: F.Plant Spray | N45: 28 | R45: Liquid | T45: 0 | W45: FALSE | X45: FALSE | Y45: FALSE | AC45: 0 | AD45: #VALUE! | AE45: No Sales | AF45: 0 | AI45: 0 | AJ45: 0 | AK45: NEW PRODUCT | AL45: NEW PRODUCT | AN45: 0 | AO45: 0 | AW45: 0 | AX45: 0 | AY45: 0 | AZ45: 0 | BA45: 0 | BB45: 0 | BJ45: 0 | BK45: 0 | BL45: Current | BM45: https://drive.google.com/file/d/10_HPcK5pk5BT8NHUy8oRsevsCZyP3UHp/view?usp=drive_link | BP45: 0 | BQ45: Established | BR45: NEW PRODUCT | BV45: 0 | BY45: 0 | BZ45: 0 | CA45: 0 | CC45: 0 | CD45: 0 | CE45: 0 | CQ45: 0 | CR45: No Sales | CT45: #N/A
A46: Forecast | C46: 46096 | D46: TPS | E46: Amazon | F46: TPS Plant Foods | G46: Air Plant Fertilizer Spray | H46: 8oz | I46: 0 | J46: 0 | M46: F.Plant Spray | N46: 60 | O46: 12x10x12 | P46: LBL-PLANT-011.5 | Q46: Aptar Pour | R46: Liquid | S46: 75 | T46: 0 | V46: 0 | W46: FALSE | X46: FALSE | Y46: FALSE | Z46: FALSE | AB46: 0 | AC46: 0 | AD46: #VALUE! | AE46: No Sales | AF46: 0 | AH46: 0 | AI46: 0 | AJ46: 0 | AK46: NEW PRODUCT | AL46: NEW PRODUCT | AM46: 0 | AN46: 0 | AO46: 0 | AP46: 0 | AQ46: 0 | AR46: 0 | AW46: 0 | AX46: 0 | AY46: 0 | AZ46: 0 | BA46: 0 | BB46: 0 | BC46: 0 | BD46: 0 | BE46: 0 | BF46: 0 | BG46: 0 | BJ46: 0 | BK46: 0 | BL46: Current | BN46: 5" x 8" | BP46: 0 | BQ46: Established | BR46: NEW PRODUCT | BT46: 0 | BU46: 0 | BV46: 0 | BY46: 0 | BZ46: 0 | CA46: 0 | CB46: 0 | CC46: 0 | CD46: 0 | CE46: 0 | CK46: 1513 | CL46: No | CM46: Established | CN46: Garden | CO46: Seasonal | CP46: 0 | CQ46: 0 | CR46: No Sales | CS46: 0 | CT46: 66.7 | CU46: 0 | CV46: 0
A47: Forecast | C47: 46096 | D47: TPS | E47: Amazon | F47: TPS Plant Foods | G47: Air Plant Fertilizer Spray | H47: Quart | I47: 0 | J47: 0 | M47: F.Plant Spray | N47: 12 | O47: 13x13x10 | P47: LBL-PLANT-239 | Q47: Aptar Pour | R47: Liquid | S47: 75 | T47: 0 | V47: 0 | W47: FALSE | X47: FALSE | Y47: FALSE | Z47: FALSE | AB47: 0 | AC47: 0 | AD47: #VALUE! | AE47: No Sales | AF47: 0 | AH47: 0 | AI47: 0 | AJ47: 0 | AK47: NEW PRODUCT | AL47: NEW PRODUCT | AM47: 0 | AN47: 0 | AO47: 0 | AP47: 0 | AQ47: 0 | AR47: 0 | AW47: 0 | AX47: 0 | AY47: 0 | AZ47: 0 | BA47: 0 | BB47: 0 | BC47: 0 | BD47: 0 | BE47: 0 | BF47: 0 | BG47: 0 | BJ47: 0 | BK47: 0 | BL47: Current | BN47: 5" x 8" | BP47: 0 | BQ47: Established | BR47: NEW PRODUCT | BT47: 0 | BU47: 0 | BV47: 0 | BY47: 0 | BZ47: 0 | CA47: 0 | CB47: 0 | CC47: 0 | CD47: 0 | CE47: 0 | CK47: 1513 | CL47: No | CM47: Established | CN47: Garden | CO47: Seasonal | CP47: 0 | CQ47: 0 | CR47: No Sales | CS47: 0 | CT47: 66.7 | CU47: 0 | CV47: 0
A48: Forecast | C48: 46039 | D48: TPS | E48: Amazon | F48: TPS Plant Foods | G48: All Purpose Fertilizer | H48: 8oz | I48: 0 | J48: 0 | K48: TPS-ALLPURPOSE-8OZ | L48: B0DPGYQ244 | M48: F.Ultra Grow | N48: 60 | O48: 12x10x12 | P48: LBL-PLANT-012 | Q48: Aptar Pour | R48: Liquid | S48: 75 | T48: 0 | U48: 11.99 | V48: 0 | W48: FALSE | X48: FALSE | Y48: FALSE | Z48: FALSE | AB48: 0 | AC48: 0 | AD48: 0 | AE48: 60 | AF48: 719 | AH48: 0 | AI48: 311 | AJ48: 167 | AK48: 2672 | AL48: 736 | AM48: 2 | AN48: 0 | AO48: 0 | AP48: 0 | AQ48: 0 | AR48: 0 | AW48: 0 | AX48: 0 | AY48: 1 | AZ48: 3 | BA48: 3 | BB48: 6 | BC48: 0 | BD48: 0 | BE48: 0 | BF48: 0 | BG48: 0 | BJ48: 7 | BK48: 311 | BL48: Current | BM48: https://drive.google.com/file/d/1FG-feEhRSN7LdUHfrIZ3_4AA5_gfaMlF/view?usp=sharing | BN48: 5" x 8" | BP48: 0 | BQ48: Established | BR48: 11953 | BT48: 2002 | BU48: 0 | BV48: 0 | BW48: 45646 | BX48: 60 | BY48: 46 | BZ48: 1 | CA48: 0 | CB48: 120 | CC48: 0 | CD48: 0 | CE48: 0 | CJ48: 45658 | CK48: 13 | CL48: No | CM48: Emerging | CN48: Garden | CO48: Seasonal | CP48: 0 | CQ48: 0 | CR48: 5 | CS48: -157 | CT48: 66.7 | CU48: 0 | CV48: 0
A49: Forecast | C49: 46039 | D49: TPS | E49: Amazon | F49: TPS Plant Foods | G49: All Purpose Fertilizer | H49: Quart | I49: 0 | J49: 0 | K49: TPS-ALLPURPOSE-QUART | L49: B0DPGZQDML | M49: F.Ultra Grow | N49: 12 | O49: 13x13x10 | P49: LBL-PLANT-240 | Q49: Aptar Pour | R49: Liquid | S49: 75 | T49: 0 | U49: 24.99 | V49: 0 | W49: FALSE | X49: FALSE | Y49: FALSE | Z49: FALSE | AB49: 0 | AC49: 0 | AD49: 0 | AE49: 12 | AF49: 300 | AH49: 0 | AI49: 1202 | AJ49: 39 | AK49: 1191 | AL49: 825 | AM49: 1 | AN49: 0 | AO49: 0 | AP49: 0 | AQ49: 0 | AR49: 0 | AW49: 0 | AX49: 0 | AY49: 1 | AZ49: 1 | BA49: 1 | BB49: 1 | BC49: 0 | BD49: 0 | BE49: 0 | BF49: 0 | BG49: 0 | BJ49: 4 | BK49: 1202 | BL49: Current | BM49: https://drive.google.com/file/d/1FHpiWq_rYlPfvOA34kAyDjfnZM_-WOQh/view?usp=drive_link | BN49: 5" x 8" | BP49: 0 | BQ49: Established | BR49: 106400 | BT49: 975 | BU49: 0 | BV49: 0 | BW49: 45646 | BX49: 12 | BY49: 27 | BZ49: 0 | CA49: 0 | CB49: 12 | CC49: 0 | CD49: 0 | CE49: 0 | CJ49: 45658 | CK49: 13 | CL49: No | CM49: Emerging | CN49: Garden | CO49: Seasonal | CP49: 0 | CQ49: 0 | CR49: 2 | CS49: -37 | CT49: 66.7 | CU49: 0 | CV49: 0
A50: Forecast | D50: TPS | E50: Amazon | F50: TPS Plant Foods | G50: All Purpose Fertilizer | H50: 1lb | I50: 0 | J50: 0 | K50: TPS-ALLPURPOSEDRY-1LB | L50: B0DQV6S1PD | M50: F.Grow/Bloom Granular | N50: 25 | O50: 12x10x12 | P50: BAG-PLANT-011 | Q50: None | R50: Dry | S50: None | T50: 0 | U50: 11.99 | V50: 0 | W50: FALSE | X50: FALSE | Y50: FALSE | Z50: FALSE | AB50: 0 | AC50: 0 | AD50: #VALUE! | AE50: No Sales | AF50: 0 | AH50: 0 | AI50: 0 | AJ50: 0 | AK50: NEW PRODUCT | AL50: NEW PRODUCT | AM50: 0 | AN50: 0 | AO50: 0 | AP50: 0 | AQ50: 0 | AR50: 0 | AW50: 0 | AX50: 0 | AY50: 0 | AZ50: 0 | BA50: 0 | BB50: 0 | BC50: 0 | BD50: 0 | BE50: 0 | BF50: 0 | BG50: 0 | BJ50: 0 | BK50: 0 | BL50: Current | BP50: 0 | BQ50: Established | BR50: NEW PRODUCT | BT50: 0 | BU50: 0 | BV50: 0 | BY50: 0 | BZ50: 0 | CA50: 0 | CB50: 0 | CC50: 0 | CD50: 0 | CE50: 0 | CJ50: 45658 | CK50: 13 | CL50: No | CM50: Emerging | CN50: Houseplant | CO50: Flat | CP50: 0 | CQ50: 0 | CR50: No Sales | CS50: 0 | CT50: 59 | CU50: 0 | CV50: 0
A51: Forecast | D51: TPS | E51: Amazon | F51: TPS Plant Foods | G51: All Purpose Fertilizer | H51: 6oz | I51: 0 | J51: 0 | K51: TPS-ALLPURPOSEDRY-6OZ | L51: B0DQV74GRP | M51: F.Grow/Bloom Granular | N51: 40 | O51: 12x10x12 | P51: BAG-PLANT-001 | Q51: None | R51: Dry | S51: None | T51: 0 | U51: 24.99 | V51: 0 | W51: FALSE | X51: FALSE | Y51: FALSE | Z51: FALSE | AB51: 0 | AC51: 0 | AD51: #VALUE! | AE51: No Sales | AF51: 0 | AH51: 0 | AI51: 0 | AJ51: 0 | AK51: NEW PRODUCT | AL51: NEW PRODUCT | AM51: 0 | AN51: 0 | AO51: 0 | AP51: 0 | AQ51: 0 | AR51: 0 | AW51: 0 | AX51: 0 | AY51: 0 | AZ51: 0 | BA51: 0 | BB51: 0 | BC51: 0 | BD51: 0 | BE51: 0 | BF51: 0 | BG51: 0 | BJ51: 0 | BK51: 0 | BL51: Current | BP51: 0 | BQ51: Established | BR51: NEW PRODUCT | BT51: 0 | BU51: 0 | BV51: 0 | BY51: 0 | BZ51: 0 | CA51: 0 | CB51: 0 | CC51: 0 | CD51: 0 | CE51: 0 | CJ51: 45658 | CK51: 13 | CL51: No | CM51: Emerging | CN51: Houseplant | CO51: Flat | CP51: 0 | CQ51: 0 | CR51: No Sales | CS51: 0 | CT51: 59 | CU51: 0 | CV51: 0
A52: Forecast | C52: 46039 | D52: TPS | E52: Amazon | F52: TPS Plant Foods | G52: All Purpose Fertilizer | H52: 1 Gallon | I52: 0 | J52: 0 | K52: TPS-ALLPURPOSE-1GAL | L52: B0DPGZ14YZ | M52: F.Ultra Grow | N52: 4 | O52: 13x13x13 | P52: LBL-PLANT-496 | Q52: Berry Unvented | R52: Liquid | S52: 75 | T52: 0 | U52: 49.99 | V52: 0 | W52: FALSE | X52: FALSE | Y52: FALSE | Z52: FALSE | AB52: 0 | AC52: 0 | AD52: #VALUE! | AE52: No Sales | AF52: 0 | AH52: 0 | AI52: 91 | AJ52: 10 | AK52: NO SALES | AL52: NO SALES | AM52: 0 | AN52: 0 | AO52: 0 | AP52: 0 | AQ52: 0 | AR52: 0 | AW52: 0 | AX52: 0 | AY52: 0 | AZ52: 0 | BA52: 0 | BB52: 0 | BC52: 0 | BD52: 0 | BE52: 0 | BF52: 0 | BG52: 0 | BJ52: 0 | BK52: 91 | BL52: Current | BM52: https://drive.google.com/file/d/1FfLS6HCiKhBYic_HPOdWcz6cUyXWhiia/view?usp=drive_link | BN52: 5" x 8" | BP52: 0 | BQ52: Established | BR52: NO SALES | BT52: 500 | BU52: 0 | BV52: 0 | BW52: 45646 | BX52: 4 | BY52: 10 | BZ52: 0 | CA52: 0 | CB52: 0 | CC52: 0 | CD52: 0 | CE52: 0 | CJ52: 45658 | CK52: 13 | CL52: No | CM52: Emerging | CN52: Garden | CO52: Seasonal | CP52: 0 | CQ52: 0 | CR52: No Sales | CS52: -10 | CT52: 66.7 | CU52: 0 | CV52: 0
A53: Forecast | C53: 46039 | D53: TPS | E53: Amazon | F53: TPS Plant Foods | G53: All Purpose NPK Fertilizer | H53: 8oz | I53: 0 | J53: 0 | K53: TPS-ALLPURPOSENPK-8OZ | L53: B0DPH4KVYT | M53: F.10-10-10 | N53: 60 | O53: 12x10x12 | P53: LBL-PLANT-013 | Q53: Aptar Pour | R53: Liquid | S53: 75 | T53: 0 | U53: 11.99 | V53: 0 | W53: FALSE | X53: FALSE | Y53: FALSE | Z53: FALSE | AB53: 180 | AC53: 0 | AD53: 0 | AE53: 120 | AF53: 1439 | AH53: 0 | AI53: 404 | AJ53: 546 | AK53: 651 | AL53: 139 | AM53: 0 | AN53: 0 | AO53: 0 | AP53: 0 | AQ53: 0 | AR53: 0 | AW53: 0 | AX53: 0 | AY53: 21 | AZ53: 28 | BA53: 36 | BB53: 132 | BC53: 0 | BD53: 0 | BE53: 0 | BF53: 0 | BG53: 0 | BJ53: 103 | BK53: 404 | BL53: Current | BM53: https://drive.google.com/drive/folders/1Tin5LVJLgmru3Fd4ahUjeBqqBaloOtzS?usp=drive_link | BN53: 5" x 8" | BP53: 0 | BQ53: Established | BR53: 1900 | BT53: 6547 | BU53: 0 | BV53: 60 | BW53: 46044 | BX53: 420 | BY53: 117 | BZ53: 9 | CA53: 0 | CB53: 0 | CC53: 0 | CD53: 420 | CE53: 0 | CJ53: 45658 | CK53: 13 | CL53: No | CM53: Emerging | CN53: Garden | CO53: Seasonal | CP53: 140 | CQ53: 0 | CR53: 62 | CS53: -322 | CT53: 66.7 | CU53: 0 | CV53: 0
A54: Forecast | C54: 46039 | D54: TPS | E54: Amazon | F54: TPS Plant Foods | G54: All Purpose NPK Fertilizer | H54: Quart | I54: 0 | J54: 0 | K54: TPS-ALLPURPOSENPK-QUART | L54: B0DPH3V4C5 | M54: F.10-10-10 | N54: 12 | O54: 13x13x10 | P54: LBL-PLANT-241 | Q54: Aptar Pour | R54: Liquid | S54: 75 | T54: 0 | U54: 24.99 | V54: 0 | W54: FALSE | X54: FALSE | Y54: FALSE | Z54: FALSE | AB54: 0 | AC54: 0 | AD54: 0 | AE54: No Sales | AF54: 0 | AH54: 0 | AI54: 106 | AJ54: 73 | AK54: 4088 | AL54: 1400 | AM54: 4 | AN54: 0 | AO54: 0 | AP54: 0 | AQ54: 0 | AR54: 0 | AW54: 0 | AX54: 0 | AY54: 0 | AZ54: 0 | BA54: 3 | BB54: 4 | BC54: 0 | BD54: 0 | BE54: 0 | BF54: 0 | BG54: 0 | BJ54: 1 | BK54: 106 | BL54: Current | BM54: https://drive.google.com/drive/folders/1Tin5LVJLgmru3Fd4ahUjeBqqBaloOtzS?usp=drive_link | BN54: 5" x 8" | BP54: 0 | BQ54: Established | BR54: 26879 | BT54: 1824 | BU54: 0 | BV54: 112 | BW54: 45846 | BX54: 96 | BY54: 25 | BZ54: 0 | CA54: 0 | CB54: 48 | CC54: 0 | CD54: 0 | CE54: 0 | CJ54: 45658 | CK54: 13 | CL54: No | CM54: Emerging | CN54: Garden | CO54: Seasonal | CP54: 0 | CQ54: 0 | CR54: No Sales | CS54: -66 | CT54: 66.7 | CU54: 0 | CV54: 0
A55: Forecast | C55: 46039 | D55: TPS | E55: Amazon | F55: TPS Plant Foods | G55: All Purpose NPK Fertilizer | H55: 1 Gallon | I55: 0 | J55: 0 | K55: TPS-ALLPURPOSENPK-1GAL | L55: B0DPH3N6G6 | M55: F.10-10-10 | N55: 4 | O55: 13x13x13 | P55: LBL-PLANT-497 | Q55: Berry Unvented | R55: Liquid | S55: 75 | T55: 0 | U55: 49.99 | V55: 0 | W55: FALSE | X55: FALSE | Y55: FALSE | Z55: FALSE | AB55: 8 | AC55: 0 | AD55: 0 | AE55: 4 | AF55: 200 | AH55: 0 | AI55: 528 | AJ55: 32 | AK55: 977 | AL55: 977 | AM55: 0 | AN55: 0 | AO55: 0 | AP55: 0 | AQ55: 0 | AR55: 0 | AW55: 0 | AX55: 0 | AY55: 1 | AZ55: 1 | BA55: 1 | BB55: 5 | BC55: 0 | BD55: 0 | BE55: 0 | BF55: 0 | BG55: 0 | BJ55: 4 | BK55: 528 | BL55: Current | BM55: https://drive.google.com/drive/folders/1Tin5LVJLgmru3Fd4ahUjeBqqBaloOtzS?usp=drive_link | BN55: 5" x 8" | BP55: 0 | BQ55: Established | BR55: 30558 | BT55: 1600 | BU55: 0 | BV55: 224 | BW55: 45918 | BX55: 40 | BY55: 32 | BZ55: 0 | CA55: 0 | CB55: 0 | CC55: 0 | CD55: 0 | CE55: 0 | CJ55: 45658 | CK55: 13 | CL55: No | CM55: Emerging | CN55: Garden | CO55: Seasonal | CP55: 5 | CQ55: 0 | CR55: 2 | CS55: -24 | CT55: 66.7 | CU55: 0 | CV55: 0
A56: Forecast | C56: 46039 | D56: TPS | E56: Amazon | F56: TPS Plant Foods | G56: Alocasia Fertilizer | H56: 8oz | I56: 0 | J56: 0 | K56: TPS-ALOCASIA-8OZ | L56: B0DPH6ZD9H | M56: F.Indoor Plant Food | N56: 60 | O56: 12x10x12 | P56: LBL-PLANT-014 | Q56: Aptar Pour | R56: Liquid | S56: 75 | T56: 0 | U56: 11.99 | V56: 0 | W56: FALSE | X56: FALSE | Y56: FALSE | Z56: FALSE | AB56: 300 | AC56: 0 | AD56: 0 | AE56: 180 | AF56: 2158 | AH56: 0 | AI56: 608 | AJ56: 551 | AK56: 241 | AL56: 156 | AM56: 1 | AN56: 0 | AO56: 60 | AP56: 0 | AQ56: 0 | AR56: 0 | AW56: 0 | AX56: 0 | AY56: 48 | AZ56: 81 | BA56: 119 | BB56: 376 | BC56: 0 | BD56: 0 | BE56: 0 | BF56: 0 | BG56: 3 | BH56: 45789 | BI56: 14 | BJ56: 265 | BK56: 608 | BL56: Current | BM56: https://drive.google.com/drive/folders/1FDeU8OIvWimvyHNPh5MuxDCLZOkQvm6t?usp=drive_link | BN56: 5" x 8" | BP56: 0 | BQ56: Established | BR56: 806 | BT56: 6606 | BU56: 0 | BV56: 88 | BW56: 45995 | BX56: 480 | BY56: 356 | BZ56: 15 | CA56: 60 | CB56: 60 | CC56: 0 | CD56: 0 | CE56: 60 | CJ56: 45658 | CK56: 13 | CL56: No | CM56: Emerging | CN56: Houseplant | CO56: Flat | CP56: 255 | CQ56: 0 | CR56: 159 | CS56: 88 | CT56: 59 | CU56: 0 | CV56: 0
A57: Forecast | C57: 46039 | D57: TPS | E57: Amazon | F57: TPS Plant Foods | G57: Alocasia Fertilizer | H57: Quart | I57: 0 | J57: 0 | K57: TPS-ALOCASIA-QUART | L57: B0DPH8FSGH | M57: F.Indoor Plant Food | N57: 12 | O57: 13x13x10 | P57: LBL-PLANT-242 | Q57: Aptar Pour | R57: Liquid | S57: 75 | T57: 0 | U57: 24.99 | V57: 0 | W57: FALSE | X57: FALSE | Y57: FALSE | Z57: FALSE | AB57: 36 | AC57: 0 | AD57: 0 | AE57: 24 | AF57: 600 | AH57: 0 | AI57: 931 | AJ57: 75 | AK57: 255 | AL57: 176 | AM57: 1 | AN57: 0 | AO57: 0 | AP57: 0 | AQ57: 0 | AR57: 0 | AW57: 0 | AX57: 0 | AY57: 6 | AZ57: 9 | BA57: 18 | BB57: 53 | BC57: 0 | BD57: 0 | BE57: 0 | BF57: 0 | BG57: 6 | BJ57: 33 | BK57: 931 | BL57: Current | BM57: https://drive.google.com/drive/folders/1FDeU8OIvWimvyHNPh5MuxDCLZOkQvm6t?usp=drive_link | BN57: 5" x 8" | BP57: 0 | BQ57: Established | BR57: 5638 | BT57: 1874 | BU57: 0 | BV57: 97 | BW57: 46052 | BX57: 60 | BY57: 52 | BZ57: 11 | CA57: 0 | CB57: 12 | CC57: 0 | CD57: 0 | CE57: 0 | CJ57: 45658 | CK57: 13 | CL57: No | CM57: Emerging | CN57: Houseplant | CO57: Flat | CP57: 30 | CQ57: 0 | CR57: 18 | CS57: 15 | CT57: 59 | CU57: 0 | CV57: 0
A58: Forecast | D58: TPS | E58: Amazon | F58: TPS Plant Foods | G58: Aloe Vera Plant Food | H58: 8oz | I58: 0 | J58: 0 | K58: ALOE8OZ-FBA-UPC-1123 | L58: B0CPGJR3N1 | M58: F.Succulent | N58: 60 | O58: 12x10x12 | P58: LBL-PLANT-016 | Q58: Aptar Pour | R58: Liquid | S58: 75 | T58: 0 | U58: 11.99 | V58: 0 | W58: FALSE | X58: FALSE | Y58: FALSE | Z58: FALSE | AB58: 240 | AC58: 0 | AD58: 0 | AE58: 180 | AF58: 2158 | AH58: 0 | AI58: 469 | AJ58: 252 | AK58: 135 | AL58: 68 | AM58: 0 | AN58: 0 | AO58: 60 | AP58: 0 | AQ58: 0 | AR58: 0 | AW58: 0 | AX58: 0 | AY58: 41 | AZ58: 65 | BA58: 92 | BB58: 207 | BC58: 0 | BD58: 0 | BE58: 31 | BF58: 190 | BG58: 188 | BJ58: 219 | BK58: 469 | BL58: Current | BM58: https://drive.google.com/open?id=12kz31C37U1-6DzbZKqi11pRRDuAgIYbr&usp=drive_fs | BN58: 5" x 8" | BP58: 0 | BQ58: Established | BR58: 725 | BT58: 3021 | BU58: 0 | BV58: 64 | BW58: 45834 | BX58: 540 | BY58: 127 | BZ58: 5 | CA58: 60 | CB58: 0 | CC58: 0 | CD58: 0 | CE58: 60 | CJ58: 45352 | CK58: 23 | CL58: No | CM58: Established | CN58: Houseplant | CO58: Flat | CP58: 184 | CQ58: 0 | CR58: 128 | CS58: 100 | CT58: 59 | CU58: 0 | CV58: 0
A59: Forecast | D59: TPS | E59: Amazon | F59: TPS Plant Foods | G59: Aloe Vera Plant Food | H59: Quart | I59: 0 | J59: 0 | K59: ALOE1Q-FBA-UPC-1123 | L59: B0CPGHS2TP | M59: F.Succulent | N59: 12 | O59: 13x13x10 | P59: LBL-PLANT-243 | Q59: Aptar Pour | R59: Liquid | S59: 75 | T59: 0 | U59: 24.99 | V59: 0 | W59: FALSE | X59: FALSE | Y59: FALSE | Z59: FALSE | AB59: 24 | AC59: 0 | AD59: 0 | AE59: 12 | AF59: 300 | AH59: 0 | AI59: 174 | AJ59: 29 | AK59: 207 | AL59: 172 | AM59: 0 | AN59: 0 | AO59: 0 | AP59: 0 | AQ59: 0 | AR59: 0 | AW59: 0 | AX59: 0 | AY59: 3 | AZ59: 5 | BA59: 7 | BB59: 14 | BC59: 0 | BD59: 0 | BE59: 1 | BF59: 3 | BG59: 8 | BJ59: 16 | BK59: 174 | BL59: Current | BM59: https://drive.google.com/open?id=12kz31C37U1-6DzbZKqi11pRRDuAgIYbr&usp=drive_fs | BN59: 5" x 8" | BP59: 0 | BQ59: Established | BR59: 2775 | BT59: 725 | BU59: 0 | BV59: 106 | BY59: 24 | BZ59: 5 | CA59: 0 | CB59: 0 | CC59: 0 | CD59: 0 | CE59: 0 | CJ59: 45352 | CK59: 23 | CL59: No | CM59: Established | CN59: Houseplant | CO59: Flat | CP59: 18 | CQ59: 0 | CR59: 10 | CS59: -5 | CT59: 59 | CU59: 0 | CV59: 0
A60: Forecast | D60: TPS | E60: Amazon | F60: TPS Plant Foods | G60: Aloe Vera Plant Food | H60: 1 Gallon | I60: 0 | J60: 0 | K60: ALOE1G-FBA-UPC-1123 | L60: B0CPGCB25H | M60: F.Succulent | N60: 4 | O60: 13x13x13 | P60: LBL-PLANT-498 | Q60: Berry Unvented | R60: Liquid | S60: 75 | T60: 0 | U60: 59.99 | V60: 0 | W60: FALSE | X60: FALSE | Y60: FALSE | Z60: FALSE | AB60: 0 | AC60: 0 | AD60: #VALUE! | AE60: No Sales | AF60: 0 | AH60: 0 | AI60: 175 | AJ60: 0 | AK60: NEW PRODUCT | AL60: NEW PRODUCT | AM60: 0 | AN60: 0 | AO60: 0 | AP60: 0 | AQ60: 0 | AR60: 0 | AW60: 0 | AX60: 0 | AY60: 0 | AZ60: 0 | BA60: 0 | BB60: 0 | BC60: 0 | BD60: 0 | BE60: 0 | BF60: 0 | BG60: 0 | BJ60: 0 | BK60: 175 | BL60: Current | BM60: https://drive.google.com/open?id=12kz31C37U1-6DzbZKqi11pRRDuAgIYbr&usp=drive_fs | BN60: 5" x 8" | BP60: 0 | BQ60: Established | BR60: NEW PRODUCT | BT60: 0 | BU60: 0 | BV60: 0 | BY60: 0 | BZ60: 0 | CA60: 0 | CB60: 0 | CC60: 0 | CD60: 0 | CE60: 0 | CJ60: 45352 | CK60: 23 | CL60: No | CM60: Established | CN60: Houseplant | CO60: Flat | CP60: 0 | CQ60: 0 | CR60: No Sales | CS60: 0 | CT60: 59 | CU60: 0 | CV60: 0
A61: Forecast | C61: 45870 | D61: TPS | E61: Amazon | F61: TPS Plant Foods | G61: Amaryllis Fertilizer | H61: 8oz | I61: 0 | J61: 0 | K61: TPS-AMARYLLISFERTILIZER-8OZ | L61: B0FLWXQ5XY | M61: F.Aquarium | N61: 60 | O61: 12x10x12 | P61: LBL-PLANT-017 | Q61: Aptar Pour | R61: Liquid | S61: 75 | T61: 0 | U61: 12.99 | V61: 0 | W61: FALSE | X61: FALSE | Y61: FALSE | Z61: FALSE | AB61: #N/A | AC61: 0 | AD61: 0 | AE61: 420 | AF61: 5456 | AH61: 0 | AI61: 1181 | AJ61: 1322 | AK61: 236 | AL61: 38 | AM61: 0 | AN61: 0 | AO61: 0 | AP61: 0 | AQ61: 0 | AR61: 0 | AW61: 0 | AX61: 0 | AY61: 126 | AZ61: 188 | BA61: 283 | BB61: 628 | BC61: 0 | BD61: 0 | BE61: 0 | BF61: 0 | BG61: 0 | BJ61: 660 | BK61: 1181 | BL61: Current | BM61: https://drive.google.com/file/d/1j36YKz0ZZx-Ez8sbAtwimoxgyDnJTXIS/view?usp=drive_link | BN61: 5" x 8" | BP61: 0 | BQ61: 0 | BR61: 855 | BT61: 17173 | BU61: 0 | BV61: 24 | BW61: 46034 | BY61: 211 | BZ61: 31 | CA61: 0 | CB61: 0 | CC61: 0 | CD61: 1080 | CE61: 0 | CJ61: 45870 | CK61: 6 | CM61: #N/A | CN61: Garden | CO61: Seasonal | CP61: #N/A | CR61: 418 | CS61: -254 | CT61: 66.7 | CU61: 0 | CV61: 0
A62: Forecast | C62: 45870 | D62: TPS | E62: Amazon | F62: TPS Plant Foods | G62: Amaryllis Fertilizer | H62: Quart | I62: 0 | J62: 0 | K62: TPS-AMARYLLISFERTILIZER-QUART | L62: B0FLWYJ1S7 | M62: F.Aquarium | N62: 12 | O62: 13x10x10 | P62: LBL-PLANT-244 | Q62: Aptar Pour | R62: Liquid | S62: 75 | T62: 0 | U62: 19.99 | V62: 0 | W62: FALSE | X62: FALSE | Y62: FALSE | Z62: FALSE | AB62: #N/A | AC62: 0 | AD62: 0 | AE62: 108 | AF62: 2159 | AH62: 0 | AI62: 742 | AJ62: 211 | AK62: 142 | AL62: 97 | AM62: 1 | AN62: 0 | AO62: 0 | AP62: 0 | AQ62: 0 | AR62: 0 | AW62: 0 | AX62: 0 | AY62: 37 | AZ62: 47 | BA62: 69 | BB62: 176 | BC62: 0 | BD62: 0 | BE62: 0 | BF62: 0 | BG62: 0 | BJ62: 181 | BK62: 742 | BL62: Current | BM62: https://drive.google.com/file/d/1j36YKz0ZZx-Ez8sbAtwimoxgyDnJTXIS/view?usp=drive_link | BN62: 5" x 8" | BP62: 0 | BQ62: 0 | BR62: 1249 | BT62: 4218 | BU62: 0 | BV62: 83 | BW62: 45996 | BY62: 144 | BZ62: 55 | CA62: 0 | CB62: 12 | CC62: 0 | CD62: 0 | CE62: 0 | CJ62: 45870 | CK62: 6 | CM62: #N/A | CN62: Garden | CO62: Seasonal | CP62: #N/A | CR62: 104 | CS62: 88 | CT62: 66.7 | CU62: 0 | CV62: 0
A63: Forecast | C63: 46096 | D63: TPS | E63: Amazon | F63: TPS Plant Foods | G63: amaryllis fertilizer | H63: 8oz | M63: F.Ultra Bloom | N63: 60 | O63: 12x10x12 | P63: LBL-PLANT-019 | R63: Liquid | T63: 0 | W63: FALSE | X63: FALSE | Y63: FALSE | Z63: FALSE | AC63: 0 | AD63: #VALUE! | AE63: No Sales | AF63: 0 | AI63: 0 | AJ63: 0 | AK63: NEW PRODUCT | AL63: NEW PRODUCT | AN63: 0 | AO63: 0 | AW63: 0 | AX63: 0 | AY63: 0 | AZ63: 0 | BA63: 0 | BB63: 0 | BJ63: 0 | BK63: 0 | BL63: Current | BM63: https://drive.google.com/file/d/1j36YKz0ZZx-Ez8sbAtwimoxgyDnJTXIS/view?usp=drive_link | BN63: 5" x 8" | BP63: 0 | BQ63: Established | BR63: NEW PRODUCT | BV63: 0 | BY63: 0 | BZ63: 0 | CA63: 0 | CC63: 0 | CD63: 0 | CE63: 0 | CP63: #N/A | CQ63: 0 | CR63: No Sales | CT63: #N/A
A64: Forecast | C64: 46096 | D64: TPS | E64: Amazon | F64: TPS Plant Foods | G64: amaryllis fertilizer | H64: Quart | M64: F.Ultra Bloom | N64: 12 | O64: 13x13x10 | R64: Liquid | T64: 0 | W64: FALSE | X64: FALSE | Y64: FALSE | Z64: FALSE | AC64: 0 | AD64: #VALUE! | AE64: No Sales | AF64: 0 | AI64: 0 | AJ64: 0 | AK64: NEW PRODUCT | AL64: NEW PRODUCT | AN64: 0 | AO64: 0 | AW64: 0 | AX64: 0 | AY64: 0 | AZ64: 0 | BA64: 0 | BB64: 0 | BJ64: 0 | BK64: 0 | BL64: Current | BM64: https://drive.google.com/file/d/1j36YKz0ZZx-Ez8sbAtwimoxgyDnJTXIS/view?usp=drive_link | BN64: 5" x 8" | BP64: 0 | BQ64: Established | BR64: NEW PRODUCT | BV64: 0 | BY64: 0 | BZ64: 0 | CA64: 0 | CC64: 0 | CD64: 0 | CE64: 0 | CP64: #N/A | CQ64: 0 | CR64: No Sales | CT64: #N/A
A65: Forecast | C65: 46039 | D65: TPS | E65: Amazon | F65: TPS Plant Foods | G65: Ammonium Nitrate Fertilizer | H65: 1 Gallon | I65: 0 | J65: 0 | K65: TPS-AMMONIUMNITRATE-1GAL | L65: B0DPH56FQZ | M65: F.TPS Nitrogen Fertilizer | N65: 4 | O65: 13x13x13 | P65: LBL-PLANT-499 | Q65: Berry Unvented | R65: Liquid | S65: 75 | T65: 0 | V65: 0 | W65: FALSE | X65: FALSE | Y65: FALSE | Z65: FALSE | AB65: 0 | AC65: 0 | AD65: #VALUE! | AE65: No Sales | AF65: 0 | AH65: 0 | AI65: 0 | AJ65: 0 | AK65: NEW PRODUCT | AL65: NEW PRODUCT | AM65: 0 | AN65: 0 | AO65: 0 | AP65: 0 | AQ65: 0 | AR65: 0 | AW65: 0 | AX65: 0 | AY65: 0 | AZ65: 0 | BA65: 0 | BB65: 0 | BC65: 0 | BD65: 0 | BE65: 0 | BF65: 0 | BG65: 0 | BJ65: 0 | BK65: 0 | BL65: Current | BM65: https://drive.google.com/drive/folders/1K0mmbp2QlCE9UDHB-14pQvvo_DEsQ1O2 | BN65: 5" x 8" | BP65: 0 | BQ65: Established | BR65: NEW PRODUCT | BT65: 0 | BU65: 0 | BV65: 0 | BY65: 0 | BZ65: 0 | CA65: 0 | CB65: 0 | CC65: 0 | CD65: 0 | CE65: 0 | CJ65: 45658 | CK65: 13 | CL65: No | CM65: Emerging | CN65: Garden | CO65: Seasonal | CP65: 0 | CQ65: 0 | CR65: No Sales | CS65: 0 | CT65: 66.7 | CU65: 0 | CV65: 0
A66: Forecast | C66: 46039 | D66: TPS | E66: Amazon | F66: TPS Plant Foods | G66: Ammonium Nitrate Fertilizer | H66: 8oz | I66: 0 | J66: 0 | K66: TPS-AMMONIUMNITRATE-8OZ | L66: B0DPH4JR3R | M66: F.TPS Nitrogen Fertilizer | N66: 60 | O66: 12x10x12 | P66: LBL-PLANT-018 | Q66: Aptar Pour | R66: Liquid | S66: 75 | T66: 0 | V66: 0 | W66: FALSE | X66: FALSE | Y66: FALSE | Z66: FALSE | AB66: 0 | AC66: 0 | AD66: #VALUE! | AE66: No Sales | AF66: 0 | AH66: 0 | AI66: 0 | AJ66: 0 | AK66: NEW PRODUCT | AL66: NEW PRODUCT | AM66: 0 | AN66: 0 | AO66: 0 | AP66: 0 | AQ66: 0 | AR66: 0 | AW66: 0 | AX66: 0 | AY66: 0 | AZ66: 0 | BA66: 0 | BB66: 0 | BC66: 0 | BD66: 0 | BE66: 0 | BF66: 0 | BG66: 0 | BJ66: 0 | BK66: 0 | BL66: Current | BM66: https://drive.google.com/drive/folders/1K0mmbp2QlCE9UDHB-14pQvvo_DEsQ1O2 | BN66: 5" x 8" | BP66: 0 | BQ66: Established | BR66: NEW PRODUCT | BT66: 0 | BU66: 0 | BV66: 0 | BY66: 0 | BZ66: 0 | CA66: 0 | CB66: 0 | CC66: 0 | CD66: 0 | CE66: 0 | CJ66: 45658 | CK66: 13 | CL66: No | CM66: Emerging | CN66: Garden | CO66: Seasonal | CP66: 0 | CQ66: 0 | CR66: No Sales | CS66: 0 | CT66: 66.7 | CU66: 0 | CV66: 0
A67: Forecast | C67: 46039 | D67: TPS | E67: Amazon | F67: TPS Plant Foods | G67: Ammonium Nitrate Fertilizer | H67: Quart | I67: 0 | J67: 0 | K67: TPS-AMMONIUMNITRATE-QUART | L67: B0DPH4JCVQ | M67: F.TPS Nitrogen Fertilizer | N67: 12 | O67: 13x13x10 | P67: LBL-PLANT-245 | Q67: Aptar Pour | R67: Liquid | S67: 75 | T67: 0 | V67: 0 | W67: FALSE | X67: FALSE | Y67: FALSE | Z67: FALSE | AB67: 0 | AC67: 0 | AD67: #VALUE! | AE67: No Sales | AF67: 0 | AH67: 0 | AI67: 0 | AJ67: 0 | AK67: NEW PRODUCT | AL67: NEW PRODUCT | AM67: 0 | AN67: 0 | AO67: 0 | AP67: 0 | AQ67: 0 | AR67: 0 | AW67: 0 | AX67: 0 | AY67: 0 | AZ67: 0 | BA67: 0 | BB67: 0 | BC67: 0 | BD67: 0 | BE67: 0 | BF67: 0 | BG67: 0 | BJ67: 0 | BK67: 0 | BL67: Current | BM67: https://drive.google.com/drive/folders/1K0mmbp2QlCE9UDHB-14pQvvo_DEsQ1O2 | BN67: 5" x 8" | BP67: 0 | BQ67: Established | BR67: NEW PRODUCT | BT67: 0 | BU67: 0 | BV67: 0 | BY67: 0 | BZ67: 0 | CA67: 0 | CB67: 0 | CC67: 0 | CD67: 0 | CE67: 0 | CJ67: 45658 | CK67: 13 | CL67: No | CM67: Emerging | CN67: Garden | CO67: Seasonal | CP67: 0 | CQ67: 0 | CR67: No Sales | CS67: 0 | CT67: 66.7 | CU67: 0 | CV67: 0
A68: Forecast | C68: 46067 | D68: Total Pest Supply | E68: Amazon | F68: NatureStop | G68: Animal Repellent Outdoor | H68: 16oz Square Spray White | I68: 0 | J68: 0 | K68: NS-ANIMALREPOUTDOOR-16OZ | L68: B0F2MLFYDT | M68: F.Animal Repel | N68: 25 | O68: 13x13x10 | P68: LBL-PEST-001 | Q68: 16oz Trigger No-Foam | R68: Spray | S68: 75 | T68: 0 | U68: 15.99 | V68: 0 | W68: FALSE | X68: FALSE | Y68: FALSE | Z68: FALSE | AB68: 25 | AC68: 0 | AD68: 0 | AE68: 25 | AF68: 400 | AH68: 0 | AI68: 965 | AJ68: 48 | AK68: 1466 | AL68: 1436 | AM68: 0 | AN68: 0 | AO68: 0 | AP68: 0 | AQ68: 0 | AR68: 0 | AW68: 0 | AX68: 0 | AY68: 1 | AZ68: 1 | BA68: 1 | BB68: 4 | BC68: 0 | BD68: 0 | BE68: 0 | BF68: 0 | BG68: 0 | BJ68: 4 | BK68: 965 | BL68: Critical Changes Made | BM68: https://drive.google.com/drive/folders/1NbKEHj3kBmmxJE34u3k9HN6gi-oQl3MR?usp=drive_link | BN68: 7.5" x 6" | BP68: 0 | BQ68: 0 | BR68: 60752 | BT68: 768 | BU68: 0 | BV68: 0 | BW68: 46007 | BY68: 47 | BZ68: 1 | CA68: 0 | CB68: 0 | CC68: 0 | CD68: 0 | CE68: 1 | CJ68: 45715 | CK68: 11 | CM68: Emerging | CO68: Seasonal | CP68: 5 | CR68: 2.2233825 | CS68: -41.2 | CT68: 66.7 | CU68: 0 | CV68: 0
A69: Forecast | C69: 46067 | D69: Total Pest Supply | E69: Amazon | F69: Mint+ | G69: Ant Killer | H69: 16oz Round Spray White | I69: 0 | J69: 0 | K69: MINT-ANTKILLER-16OZ | L69: B0F3WFWT1G | M69: F.Ant Out | N69: 25 | O69: 13x13x10 | P69: LBL-PEST-037 | Q69: 16oz Trigger No-Foam | R69: Spray | S69: 75 | T69: 0 | U69: 15.99 | V69: 0 | W69: FALSE | X69: FALSE | Y69: FALSE | Z69: FALSE | AB69: 0 | AC69: 0 | AD69: 0 | AE69: 125 | AF69: 1999 | AH69: 0 | AI69: 1117 | AJ69: 574 | AK69: 468 | AL69: 144 | AM69: 12 | AN69: 0 | AO69: 1 | AP69: 0 | AQ69: 0 | AR69: 0 | AW69: 0 | AX69: 0 | AY69: 20 | AZ69: 46 | BA69: 77 | BB69: 224 | BC69: 0 | BD69: 0 | BE69: 0 | BF69: 0 | BG69: 0 | BJ69: 132 | BK69: 1117 | BL69: Current | BM69: https://drive.google.com/drive/folders/1Zv1VJsW-LX4UFshFcTnoqtw8jBS5t-tU | BN69: 7.5" x 6" | BP69: 0 | BQ69: 0 | BR69: 2030 | BT69: 9178 | BU69: 0 | BV69: 97 | BW69: 45993 | BY69: 177 | BZ69: 96 | CA69: 1 | CB69: 300 | CC69: 0 | CD69: 0 | CE69: 1 | CJ69: 45715 | CK69: 11 | CM69: Emerging | CO69: Seasonal | CP69: 0 | CR69: 102.27559 | CS69: -193.2 | CT69: 66.7 | CU69: 0 | CV69: 0
A70: Forecast | C70: 46067 | D70: Total Pest Supply | E70: Amazon | F70: NatureStop | G70: Ant Killer | H70: 16oz Square Spray White | I70: 0 | J70: 0 | K70: NS-ANTKILLER-16OZ | L70: B0F3JLWF2M | M70: F.Ant Out | N70: 25 | O70: 13x13x10 | P70: LBL-PEST-002 | Q70: 16oz Trigger No-Foam | R70: Spray | S70: 75 | T70: 0 | U70: 15.99 | V70: 0 | W70: FALSE | X70: FALSE | Y70: FALSE | Z70: FALSE | AB70: 25 | AC70: 0 | AD70: 0 | AE70: 25 | AF70: 400 | AH70: 0 | AI70: 1610 | AJ70: 423 | AK70: 3841 | AL70: 3832 | AM70: 0 | AN70: 0 | AO70: 0 | AP70: 0 | AQ70: 0 | AR70: 0 | AW70: 0 | AX70: 0 | AY70: 3 | AZ70: 3 | BA70: 5 | BB70: 12 | BC70: 0 | BD70: 0 | BE70: 0 | BF70: 0 | BG70: 0 | BH70: 45873 | BI70: 15 | BJ70: 14 | BK70: 1610 | BL70: Current | BM70: https://drive.google.com/drive/folders/1O8l0CLJhDIe8CriyyTeWzPHtD9ZrJXMN?usp=drive_link | BN70: 7.5" x 6" | BP70: 0 | BQ70: 0 | BR70: 40650 | BT70: 6764 | BU70: 0 | BV70: 0 | BW70: 45841 | BY70: 422 | BZ70: 1 | CA70: 0 | CB70: 0 | CC70: 0 | CD70: 0 | CE70: 0 | CJ70: 45715 | CK70: 11 | CM70: Emerging | CO70: Seasonal | CP70: 15 | CR70: 6.6701474 | CS70: -402.6 | CT70: 66.7 | CU70: 0 | CV70: 0
A71: Forecast | C71: 46067 | D71: Total Pest Supply | E71: Amazon | F71: NatureStop | G71: Ant Killer Indoor | H71: 16oz Square Spray White | I71: 0 | J71: 0 | K71: NS-ANTKILLERINDOOR-16OZ | L71: B0F3JL3N17 | M71: F.Ant Out | N71: 25 | O71: 13x13x10 | P71: LBL-PEST-HV-10 | Q71: 16oz Trigger No-Foam | R71: Spray | S71: 75 | T71: 0 | U71: 16.99 | V71: 0 | W71: FALSE | X71: FALSE | Y71: FALSE | Z71: FALSE | AB71: 1125 | AC71: 0 | AD71: 0 | AE71: 500 | AF71: 8495 | AH71: 0 | AI71: 5861 | AJ71: 865 | AK71: 133 | AL71: 126 | AM71: 0 | AN71: 0 | AO71: 0 | AP71: 0 | AQ71: 0 | AR71: 0 | AW71: 0 | AX71: 0 | AY71: 159 | AZ71: 224 | BA71: 283 | BB71: 853 | BC71: 0 | BD71: 0 | BE71: 0 | BF71: 0 | BG71: 0 | BH71: Complete | BJ71: 795 | BK71: 5861 | BL71: Current | BM71: https://drive.google.com/drive/folders/1P1A1T_H6OhgnY3nnCMhs5iBJ1MhzhEtz?usp=drive_link | BN71: 7.5" x 6" | BO71: 45839 | BP71: 0 | BQ71: 0 | BR71: 1837 | BT71: 14696 | BU71: 0 | BV71: 79 | BW71: 45979 | BY71: 821 | BZ71: 44 | CA71: 0 | CB71: 0 | CC71: 0 | CD71: 0 | CE71: 0 | CJ71: 45715 | CK71: 11 | CM71: Emerging | CO71: Seasonal | CP71: 1120 | CR71: 498.03767 | CS71: 585.1 | CT71: 66.7 | CU71: 0 | CV71: 0
A72: Forecast | C72: 46067 | D72: Total Pest Supply | E72: Amazon | F72: NatureStop | G72: Ant Killer Indoor | H72: 6oz Spray Bottle | I72: 0 | J72: 0 | K72: NS-ANTKILLERINDOOR-6OZ | L72: B0F3JHDQ4K | M72: F.Ant Out | N72: 64 | O72: 14x14x8 | P72: LBL-PEST-068 | Q72: 6oz Sprayer Top | R72: Spray | S72: 75 | T72: 0 | U72: 12.99 | V72: 0 | W72: FALSE | X72: FALSE | Y72: FALSE | Z72: FALSE | AB72: 192 | AC72: 0 | AD72: 0 | AE72: 64 | AF72: 831 | AH72: 0 | AI72: 2518 | AJ72: 342 | AK72: 405 | AL72: 265 | AM72: 0 | AN72: 0 | AO72: 0 | AP72: 0 | AQ72: 0 | AR72: 0 | AW72: 0 | AX72: 0 | AY72: 21 | AZ72: 26 | BA72: 40 | BB72: 212 | BC72: 0 | BD72: 0 | BE72: 0 | BF72: 0 | BG72: 0 | BH72: 45929 | BI72: 10 | BJ72: 102 | BK72: 2518 | BL72: Current | BM72: https://drive.google.com/drive/folders/1P1A1T_H6OhgnY3nnCMhs5iBJ1MhzhEtz?usp=drive_link | BN72: 5.375" x 4.5" | BP72: 0 | BQ72: 0 | BR72: 4663 | BT72: 4443 | BU72: 0 | BV72: 121 | BW72: 45853 | BY72: 224 | BZ72: 118 | CA72: 0 | CB72: 0 | CC72: 0 | CD72: 0 | CE72: 0 | CJ72: 45715 | CK72: 11 | CM72: Emerging | CO72: Seasonal | CP72: 130 | CR72: 57.807944 | CS72: 18.4 | CT72: 66.7 | CU72: 0 | CV72: 0
A73: Forecast | C73: 46067 | D73: Total Pest Supply | E73: Amazon | F73: NatureStop | G73: Ant Repellent Indoor | H73: 16oz Square Spray White | I73: 0 | J73: 0 | K73: NS-ANTREPINDOOR-16OZ | L73: B0F2MMCD73 | M73: F.Ant Out | N73: 25 | O73: 13x13x10 | P73: LBL-PEST-003 | Q73: 16oz Trigger No-Foam | R73: Spray | S73: 75 | T73: 0 | U73: 15.99 | V73: 0 | W73: FALSE | X73: FALSE | Y73: FALSE | Z73: FALSE | AB73: 0 | AC73: 0 | AD73: 0 | AE73: 100 | AF73: 1599 | AH73: 0 | AI73: 1318 | AJ73: 405 | AK73: 372 | AL73: 61 | AM73: 0 | AN73: 0 | AO73: 300 | AP73: 0 | AQ73: 0 | AR73: 0 | AW73: 0 | AX73: 0 | AY73: 21 | AZ73: 38 | BA73: 63 | BB73: 142 | BC73: 0 | BD73: 0 | BE73: 0 | BF73: 0 | BG73: 0 | BJ73: 122 | BK73: 1318 | BL73: Current | BM73: https://drive.google.com/drive/folders/1Nk7TewI7e5jnVCMC2srAaFm7CLiD3ejB | BN73: 7.5" x 6" | BP73: 0 | BQ73: 0 | BR73: 2794 | BT73: 6476 | BU73: 0 | BV73: 168 | BW73: 46037 | BY73: 66 | BZ73: 39 | CA73: 300 | CB73: 0 | CC73: 0 | CD73: 0 | CE73: 0 | CJ73: 45715 | CK73: 11 | CM73: Emerging | CO73: Seasonal | CP73: 0 | CR73: 84.488534 | CS73: -163.6 | CT73: 66.7 | CU73: 0 | CV73: 0
A74: Forecast | C74: 46067 | D74: Total Pest Supply | E74: Amazon | F74: Burke's | G74: Ant Spray | H74: 16oz Square Spray White | I74: 0 | J74: 0 | K74: BURKES-ANTSPRAY-16OZ | L74: B0F1DYC3FX | M74: F.Ant Out | N74: 25 | O74: 13x13x10 | P74: LBL-PEST-035 | Q74: 16oz Trigger No-Foam | R74: Spray | S74: 75 | T74: 0 | U74: 15.99 | V74: 0 | W74: FALSE | X74: FALSE | Y74: FALSE | Z74: FALSE | AB74: 0 | AC74: 0 | AD74: 0 | AE74: No Sales | AF74: 0 | AH74: 0 | AI74: 1463 | AJ74: 44 | AK74: 7392 | AL74: 7392 | AM74: 0 | AN74: 0 | AO74: 0 | AP74: 0 | AQ74: 0 | AR74: 0 | AW74: 0 | AX74: 0 | AY74: 0 | AZ74: 0 | BA74: 1 | BB74: 1 | BC74: 0 | BD74: 0 | BE74: 0 | BF74: 0 | BG74: 0 | BJ74: 0 | BK74: 1463 | BL74: Current | BM74: https://drive.google.com/drive/folders/1YOTV_w448W64Ev1_mYVjER7KzJYrh4f6 | BN74: 7.5" x 6" | BP74: 0 | BQ74: 0 | BR74: 904222 | BT74: 704 | BU74: 0 | BV74: 0 | BW74: 45775 | BY74: 44 | BZ74: 0 | CA74: 0 | CB74: 0 | CC74: 0 | CD74: 0 | CE74: 0 | CJ74: 45715 | CK74: 11 | CM74: Emerging | CO74: Seasonal | CP74: 0 | CR74: No Sales | CS74: -42.3 | CT74: 66.7 | CU74: 0 | CV74: 0
A75: Forecast | C75: 46039 | D75: TPS | E75: Amazon | F75: TPS Plant Foods | G75: anthurium fertilizer | H75: 8oz | I75: 0 | J75: 0 | K75: TPS-ANTHURIUM-8OZ | L75: B0DPH77GSG | M75: F.Succulent | N75: 60 | O75: 12x10x12 | P75: LBL-PLANT-019 | Q75: Aptar Pour | R75: Liquid | S75: 75 | T75: 0 | U75: 11.99 | V75: 0 | W75: FALSE | X75: FALSE | Y75: FALSE | Z75: FALSE | AB75: 240 | AC75: 0 | AD75: 0 | AE75: 120 | AF75: 1439 | AH75: 0 | AI75: 140 | AJ75: 96 | AK75: 97 | AL75: 32 | AM75: 0 | AN75: 0 | AO75: 0 | AP75: 0 | AQ75: 0 | AR75: 0 | AW75: 0 | AX75: 0 | AY75: 14 | AZ75: 47 | BA75: 53 | BB75: 91 | BC75: 0 | BD75: 0 | BE75: 0 | BF75: 0 | BG75: 1 | BH75: 45658 | BI75: 30 | BJ75: 107 | BK75: 140 | BL75: Current | BM75: https://drive.google.com/drive/folders/1qEvhWI0tTJbZK3_kN8qMB3sR4lxUka7E | BN75: 5" x 8" | BP75: 0 | BQ75: Established | BR75: 380 | BT75: 1151 | BU75: 0 | BV75: 30 | BW75: 46041 | BX75: 60 | BY75: 32 | BZ75: 4 | CA75: 0 | CB75: 0 | CC75: 0 | CD75: 60 | CE75: 0 | CJ75: 45658 | CK75: 13 | CL75: No | CM75: Emerging | CN75: Houseplant | CO75: Flat | CP75: 235 | CQ75: 0 | CR75: 92 | CS75: 59 | CT75: 59 | CU75: 0 | CV75: 0
A76: Forecast | C76: 46039 | D76: TPS | E76: Amazon | F76: TPS Plant Foods | G76: anthurium fertilizer | H76: Quart | I76: 0 | J76: 0 | K76: TPS-ANTHURIUM-QUART | L76: B0DPH8WB8H | M76: F.Succulent | N76: 12 | O76: 13x13x10 | P76: LBL-PLANT-246 | Q76: Aptar Pour | R76: Liquid | S76: 75 | T76: 0 | U76: 24.99 | V76: 0 | W76: FALSE | X76: FALSE | Y76: FALSE | Z76: FALSE | AB76: 0 | AC76: 0 | AD76: 0 | AE76: 12 | AF76: 300 | AH76: 0 | AI76: 238 | AJ76: 28 | AK76: 855 | AL76: 489 | AM76: 1 | AN76: 0 | AO76: 0 | AP76: 0 | AQ76: 0 | AR76: 0 | AW76: 0 | AX76: 0 | AY76: 1 | AZ76: 1 | BA76: 1 | BB76: 5 | BC76: 0 | BD76: 0 | BE76: 0 | BF76: 0 | BG76: 0 | BJ76: 4 | BK76: 238 | BL76: Current | BM76: https://drive.google.com/drive/folders/1qEvhWI0tTJbZK3_kN8qMB3sR4lxUka7E | BN76: 5" x 8" | BP76: 0 | BQ76: Established | BR76: 14509 | BT76: 700 | BU76: 0 | BV76: 182 | BW76: 45646 | BX76: 12 | BY76: 16 | BZ76: 0 | CA76: 0 | CB76: 12 | CC76: 0 | CD76: 0 | CE76: 0 | CJ76: 45658 | CK76: 13 | CL76: No | CM76: Emerging | CN76: Houseplant | CO76: Flat | CP76: 0 | CQ76: 0 | CR76: 2 | CS76: -20 | CT76: 59 | CU76: 0 | CV76: 0
A77: Forecast | C77: 45870 | D77: TPS | E77: Amazon | F77: TPS Plant Foods | G77: Anthurium Fertilizer Spray | H77: 16oz Round Spray White | I77: 0 | J77: 0 | K77: TPS-ANTHURIUMFERTSPRAY-16OZ | L77: B0FLWT9FSQ | M77: F.Plant Spray | N77: 25 | O77: 13x13x10 | P77: LBL-PLANT-664 | Q77: 16oz Trigger No-Foam | R77: Liquid | S77: 75 | T77: 0 | U77: 11.99 | V77: 0 | W77: FALSE | X77: FALSE | Y77: FALSE | Z77: FALSE | AB77: #N/A | AC77: 0 | AD77: 0 | AE77: 25 | AF77: 300 | AH77: 0 | AI77: 934 | AJ77: 71 | AK77: 723 | AL77: 723 | AM77: 0 | AN77: 0 | AO77: 0 | AP77: 0 | AQ77: 0 | AR77: 0 | AW77: 0 | AX77: 0 | AY77: 3 | AZ77: 3 | BA77: 3 | BB77: 10 | BC77: 0 | BD77: 0 | BE77: 0 | BF77: 0 | BG77: 0 | BJ77: 13 | BK77: 934 | BL77: Current | BM77: https://drive.google.com/file/d/1JlJNpwFn6p71QHIq_dMG26-CdbfZyj46/view?usp=drive_link | BN77: 7.5" x 6" | BP77: 0 | BQ77: 0 | BR77: 21531 | BT77: 851 | BU77: 0 | BV77: 0 | BW77: 45910 | BY77: 71 | BZ77: 0 | CA77: 0 | CB77: 0 | CC77: 0 | CD77: 0 | CE77: 0 | CJ77: 45870 | CK77: 6 | CM77: #N/A | CN77: Garden | CO77: Seasonal | CP77: #N/A | CR77: 7 | CS77: -54 | CT77: 66.7 | CU77: 0 | CV77: 0
A78: Forecast | D78: TPS | E78: Amazon | F78: TPS Plant Foods | G78: Apple Tree Fertilizer | H78: 8oz | I78: 0 | J78: 0 | K78: APPLETREE8OZ-FBA-UPC-0523 | L78: B0C73SYHXY | M78: F.Ultra Grow | N78: 60 | O78: 12x10x12 | P78: LBL-PLANT-020 | Q78: Aptar Pour | R78: Liquid | S78: 75 | T78: 0 | U78: 11.99 | V78: 0 | W78: FALSE | X78: FALSE | Y78: FALSE | Z78: FALSE | AB78: 120 | AC78: 0 | AD78: 0 | AE78: 60 | AF78: 719 | AH78: 0 | AI78: 2460 | AJ78: 315 | AK78: 971 | AL78: 595 | AM78: 2 | AN78: 0 | AO78: 0 | AP78: 0 | AQ78: 0 | AR78: 0 | AW78: 0 | AX78: 0 | AY78: 8 | AZ78: 9 | BA78: 17 | BB78: 78 | BC78: 91 | BD78: 52 | BE78: 517 | BF78: 424 | BG78: 149 | BJ78: 39 | BK78: 2460 | BL78: Current | BM78: https://drive.google.com/open?id=1RCT9_KNTJT-RH01yL2t0cer7jAsVfDSl&usp=drive_fs | BN78: 5" x 8" | BP78: 0 | BQ78: Established | BR78: 12615 | BT78: 3777 | BU78: 0 | BV78: 64 | BW78: 45902 | BX78: 180 | BY78: 193 | BZ78: 2 | CA78: 0 | CB78: 120 | CC78: 0 | CD78: 0 | CE78: 0 | CJ78: 45108 | CK78: 31 | CL78: No | CM78: Established | CN78: Garden | CO78: Seasonal - Tree | CP78: 103 | CQ78: 0 | CR78: 12 | CS78: 454 | CT78: 91.99 | CU78: 202 | CV78: 0
A79: Forecast | D79: TPS | E79: Amazon | F79: TPS Plant Foods | G79: Apple Tree Fertilizer | H79: Quart | I79: 0 | J79: 0 | K79: APPLETREE1Q-FBA-UPC-0523 | L79: B0C73V8Z6G | M79: F.Ultra Grow | N79: 12 | O79: 13x13x10 | P79: LBL-PLANT-247 | Q79: Aptar Pour | R79: Liquid | S79: 75 | T79: 0 | U79: 24.99 | V79: 0 | W79: FALSE | X79: FALSE | Y79: FALSE | Z79: FALSE | AB79: 0 | AC79: 0 | AD79: 0 | AE79: 12 | AF79: 300 | AH79: 0 | AI79: 1254 | AJ79: 714 | AK79: 3427 | AL79: 475 | AM79: 51 | AN79: 0 | AO79: 0 | AP79: 0 | AQ79: 0 | AR79: 0 | AW79: 0 | AX79: 0 | AY79: 4 | AZ79: 8 | BA79: 11 | BB79: 23 | BC79: 291 | BD79: 119 | BE79: 599 | BF79: 447 | BG79: 52 | BJ79: 24 | BK79: 1254 | BL79: Current | BM79: https://drive.google.com/open?id=1RCT9_KNTJT-RH01yL2t0cer7jAsVfDSl&usp=drive_fs | BN79: 5" x 8" | BP79: 0 | BQ79: Established | BR79: 16627 | BT79: 17843 | BU79: 0 | BV79: 88 | BW79: 45433 | BX79: 840 | BY79: 99 | BZ79: 3 | CA79: 0 | CB79: 612 | CC79: 0 | CD79: 0 | CE79: 0 | CJ79: 45108 | CK79: 31 | CL79: No | CM79: Established | CN79: Garden | CO79: Seasonal - Tree | CP79: 0 | CQ79: 0 | CR79: 11 | CS79: 86 | CT79: 91.99 | CU79: 0 | CV79: 0
A80: Forecast | D80: TPS | E80: Amazon | F80: TPS Plant Foods | G80: Apple Tree Fertilizer | H80: 1 Gallon | I80: 0 | J80: 0 | K80: APPLETREE1G-FBA-UPC-0523 | L80: B0C73S6SN3 | M80: F.Ultra Grow | N80: 4 | O80: 13x13x13 | P80: LBL-PLANT-500 | Q80: Berry Unvented | R80: Liquid | S80: 75 | T80: 0 | U80: 49.99 | V80: 0 | W80: FALSE | X80: FALSE | Y80: FALSE | Z80: FALSE | AB80: 0 | AC80: 0 | AD80: 0 | AE80: 4 | AF80: 200 | AH80: 0 | AI80: 206 | AJ80: 57 | AK80: 1741 | AL80: 733 | AM80: 7 | AN80: 0 | AO80: 0 | AP80: 0 | AQ80: 0 | AR80: 0 | AW80: 0 | AX80: 0 | AY80: 1 | AZ80: 1 | BA80: 1 | BB80: 8 | BC80: 43 | BD80: 12 | BE80: 39 | BF80: 63 | BG80: 9 | BJ80: 4 | BK80: 206 | BL80: Current | BM80: https://drive.google.com/open?id=1RCT9_KNTJT-RH01yL2t0cer7jAsVfDSl&usp=drive_fs | BN80: 5" x 8" | BP80: 0 | BQ80: Established | BR80: 11269 | BT80: 2849 | BU80: 0 | BV80: 92 | BW80: 45946 | BX80: 52 | BY80: 24 | BZ80: 5 | CA80: 0 | CB80: 28 | CC80: 0 | CD80: 0 | CE80: 0 | CJ80: 45108 | CK80: 31 | CL80: No | CM80: Established | CN80: Garden | CO80: Seasonal - Tree | CP80: 0 | CQ80: 0 | CR80: 1 | CS80: 10 | CT80: 91.99 | CU80: 0 | CV80: 0
A81: Forecast | C81: 46039 | D81: TPS | E81: Amazon | F81: TPS Plant Foods | G81: Aquarium Plant Fertilizer | H81: 8oz | I81: 0 | J81: 0 | K81: TPS-AQUARIUMPLANT-8OZ | L81: B0DQTLXG12 | M81: F.Aquarium | N81: 60 | O81: 12x10x12 | P81: LBL-PLANT-021 | Q81: Aptar Pour | R81: Liquid | S81: 75 | T81: 0 | U81: 11.99 | V81: 0 | W81: FALSE | X81: FALSE | Y81: FALSE | Z81: FALSE | AB81: 60 | AC81: 0 | AD81: 0 | AE81: 60 | AF81: 719 | AH81: 0 | AI81: 268 | AJ81: 108 | AK81: 206 | AL81: 80 | AM81: 1 | AN81: 0 | AO81: 0 | AP81: 0 | AQ81: 0 | AR81: 0 | AW81: 0 | AX81: 0 | AY81: 11 | AZ81: 16 | BA81: 31 | BB81: 61 | BC81: 0 | BD81: 0 | BE81: 0 | BF81: 0 | BG81: 0 | BJ81: 59 | BK81: 268 | BL81: Current | BM81: https://drive.google.com/drive/folders/1J-cJvK00es93lkYwyoq4LrvFuHlZWSG5 | BN81: 5" x 8" | BP81: 0 | BQ81: Established | BR81: 1438 | BT81: 1295 | BU81: 0 | BV81: 59 | BW81: 45726 | BX81: 60 | BY81: 42 | BZ81: 6 | CA81: 0 | CB81: 60 | CC81: 0 | CD81: 0 | CE81: 0 | CJ81: 45658 | CK81: 13 | CL81: No | CM81: Emerging | CN81: Garden | CO81: Seasonal | CP81: 5 | CQ81: 0 | CR81: 25 | CS81: -4 | CT81: 66.7 | CU81: 0 | CV81: 0
A82: Forecast | C82: 46039 | D82: TPS | E82: Amazon | F82: TPS Plant Foods | G82: Aquarium Plant Fertilizer | H82: Quart | I82: 0 | J82: 0 | K82: TPS-AQUARIUMPLANT-QUART | L82: B0DQTRJQJS | M82: F.Aquarium | N82: 12 | O82: 13x13x10 | P82: LBL-PLANT-248 | Q82: Aptar Pour | R82: Liquid | S82: 75 | T82: 0 | U82: 24.99 | V82: 0 | W82: FALSE | X82: FALSE | Y82: FALSE | Z82: FALSE | AB82: 0 | AC82: 0 | AD82: #DIV/0! | AE82: No Sales | AF82: 0 | AH82: 0 | AI82: 201 | AJ82: 20 | AK82: NO SALES | AL82: #DIV/0! | AM82: 0 | AN82: #DIV/0! | AO82: 0 | AP82: 0 | AQ82: 0 | AR82: 0 | AW82: 0 | AX82: 0 | AY82: 0 | AZ82: 0 | BA82: 0 | BB82: 1 | BC82: 0 | BD82: 0 | BE82: 0 | BF82: 0 | BG82: 0 | BJ82: 0 | BK82: 201 | BL82: Current | BM82: https://drive.google.com/drive/folders/1J-cJvK00es93lkYwyoq4LrvFuHlZWSG5 | BN82: 5" x 8" | BP82: 0 | BQ82: Established | BR82: 132364 | BT82: 500 | BU82: 0 | BV82: 0 | BW82: 45646 | BX82: 12 | BY82: 20 | BZ82: 0 | CA82: 0 | CB82: 0 | CC82: 0 | CD82: 0 | CE82: 0 | CJ82: 45658 | CK82: 13 | CL82: No | CM82: Emerging | CN82: Garden | CO82: Seasonal | CP82: 0 | CQ82: 0 | CR82: No Sales | CS82: -18 | CT82: 66.7 | CU82: 0 | CV82: 0
A83: Forecast | C83: 46039 | D83: TPS | E83: Amazon | F83: TPS Plant Foods | G83: Aquatic Plant Fertilizer | H83: 8oz | I83: 0 | J83: 0 | K83: TPS-AQUATICPLANT-8OZ | L83: B0DQT94SB2 | M83: F.Aquarium | N83: 60 | O83: 12x10x12 | P83: LBL-PLANT-022 | Q83: Aptar Pour | R83: Liquid | S83: 75 | T83: 0 | U83: 11.99 | V83: 0 | W83: FALSE | X83: FALSE | Y83: FALSE | Z83: FALSE | AB83: 180 | AC83: 0 | AD83: 0 | AE83: 60 | AF83: 719 | AH83: 0 | AI83: 2465 | AJ83: 662 | AK83: 843 | AL83: 145 | AM83: 0 | AN83: 0 | AO83: 0 | AP83: 0 | AQ83: 0 | AR83: 0 | AW83: 0 | AX83: 0 | AY83: 16 | AZ83: 28 | BA83: 42 | BB83: 130 | BC83: 0 | BD83: 0 | BE83: 0 | BF83: 0 | BG83: 6 | BJ83: 90 | BK83: 2465 | BL83: Current | BM83: https://drive.google.com/drive/folders/1J1obdhKqXYdNJL6GSiYmnBEAEv5-_XjA | BN83: 5" x 8" | BP83: 0 | BQ83: Established | BR83: 6296 | BT83: 7937 | BU83: 0 | BV83: 57 | BW83: 46041 | BX83: 540 | BY83: 114 | BZ83: 8 | CA83: 0 | CB83: 0 | CC83: 0 | CD83: 540 | CE83: 0 | CJ83: 45658 | CK83: 13 | CL83: No | CM83: Emerging | CN83: Garden | CO83: Seasonal | CP83: 140 | CQ83: 0 | CR83: 43 | CS83: -441 | CT83: 66.7 | CU83: 0 | CV83: 0
A84: Forecast | C84: 46039 | D84: TPS | E84: Amazon | F84: TPS Plant Foods | G84: Aquatic Plant Fertilizer | H84: Quart | I84: 0 | J84: 0 | K84: TPS-AQUATICPLANT-QUART | L84: B0DQTMQCVD | M84: F.Aquarium | N84: 12 | O84: 13x13x10 | P84: LBL-PLANT-249 | Q84: Aptar Pour | R84: Liquid | S84: 75 | T84: 0 | U84: 24.99 | V84: 0 | W84: FALSE | X84: FALSE | Y84: FALSE | Z84: FALSE | AB84: 0 | AC84: 0 | AD84: #DIV/0! | AE84: No Sales | AF84: 0 | AH84: 0 | AI84: 337 | AJ84: 46 | AK84: NO SALES | AL84: #DIV/0! | AM84: 0 | AN84: #DIV/0! | AO84: 0 | AP84: 0 | AQ84: 0 | AR84: 0 | AW84: 0 | AX84: 0 | AY84: 0 | AZ84: 0 | BA84: 0 | BB84: 6 | BC84: 0 | BD84: 0 | BE84: 0 | BF84: 0 | BG84: 0 | BJ84: 0 | BK84: 337 | BL84: Current | BM84: https://drive.google.com/drive/folders/1J1obdhKqXYdNJL6GSiYmnBEAEv5-_XjA | BN84: 5" x 8" | BP84: 0 | BQ84: Established | BR84: 38298 | BT84: 1150 | BU84: 0 | BV84: 142 | BW84: 46052 | BX84: 48 | BY84: 46 | BZ84: 0 | CA84: 0 | CB84: 0 | CC84: 0 | CD84: 0 | CE84: 0 | CJ84: 45658 | CK84: 13 | CL84: No | CM84: Emerging | CN84: Garden | CO84: Seasonal | CP84: 0 | CQ84: 0 | CR84: No Sales | CS84: -36 | CT84: 66.7 | CU84: 0 | CV84: 0
A85: Forecast | D85: TPS | E85: Amazon | F85: TPS Plant Foods | G85: Arborvitae Tree Fertilizer | H85: Quart | I85: 0 | J85: 0 | K85: ARBORVITAE1Q-FBA-UPC-1123 | L85: B0CPGR5T5W | M85: F.Ultra Grow | N85: 12 | O85: 13x13x10 | P85: LBL-HV-036 | Q85: Aptar Pour | R85: Liquid | S85: 75 | T85: 0 | U85: 24.99 | V85: 0 | W85: FALSE | X85: FALSE | Y85: FALSE | Z85: FALSE | AB85: 0 | AC85: 0 | AD85: 0 | AE85: 108 | AF85: 2699 | AH85: 0 | AI85: 8864 | AJ85: 2019 | AK85: 816 | AL85: 366 | AM85: 51 | AN85: 0 | AO85: 240 | AP85: 0 | AQ85: 0 | AR85: 0 | AW85: 0 | AX85: 0 | AY85: 53 | AZ85: 79 | BA85: 138 | BB85: 723 | BC85: 0 | BD85: 6 | BE85: 527 | BF85: 2700 | BG85: 1514 | BJ85: 284 | BK85: 8864 | BL85: Current | BM85: https://drive.google.com/open?id=1RM_9CilV1WLruR1gTHg0geQiPlsdX5Ly&usp=drive_fs | BN85: 5" x 8" | BP85: 0 | BQ85: Established | BR85: 5455 | BT85: 50455 | BU85: 0 | BV85: 72 | BW85: 45796 | BX85: 4380 | BY85: 905 | BZ85: 22 | CA85: 240 | CB85: 612 | CC85: 0 | CD85: 0 | CE85: 240 | CJ85: 45352 | CK85: 23 | CL85: No | CM85: Established | CN85: Garden | CO85: Seasonal - Tree | CP85: 0 | CQ85: 0 | CR85: 107 | CS85: 199 | CT85: 91.99 | CU85: 0 | CV85: 0
A86: Forecast | D86: TPS | E86: Amazon | F86: TPS Plant Foods | G86: Arborvitae Tree Fertilizer | H86: 1 Gallon | I86: 0 | J86: 0 | K86: ARBORVITAE1G-FBA-UPC-1123 | L86: B0CPGJR1FV | M86: F.Ultra Grow | N86: 4 | O86: 13x13x13 | P86: LBL-HV-066 | Q86: Berry Unvented | R86: Liquid | S86: 75 | T86: 0 | U86: 49.99 | V86: 0 | W86: FALSE | X86: FALSE | Y86: FALSE | Z86: FALSE | AB86: 248 | AC86: 0 | AD86: 0 | AE86: 84 | AF86: 4199 | AH86: 0 | AI86: 2162 | AJ86: 1028 | AK86: 618 | AL86: 478 | AM86: 50 | AN86: 0 | AO86: 0 | AP86: 0 | AQ86: 0 | AR86: 0 | AW86: 0 | AX86: 0 | AY86: 27 | AZ86: 61 | BA86: 107 | BB86: 398 | BC86: 0 | BD86: 0 | BE86: 0 | BF86: 128 | BG86: 19 | BJ86: 178 | BK86: 2162 | BL86: Current | BM86: https://drive.google.com/open?id=1RM_9CilV1WLruR1gTHg0geQiPlsdX5Ly&usp=drive_fs | BN86: 5" x 8" | BP86: 0 | BQ86: Established | BR86: 2506 | BT86: 51390 | BU86: 0 | BV86: 101 | BW86: 45958 | BX86: 200 | BY86: 796 | BZ86: 20 | CA86: 0 | CB86: 200 | CC86: 12 | CD86: 0 | CE86: 0 | CJ86: 45352 | CK86: 23 | CL86: No | CM86: Established | CN86: Garden | CO86: Seasonal - Tree | CP86: 248 | CQ86: 0 | CR86: 83 | CS86: -351 | CT86: 91.99 | CU86: 0 | CV86: 0
A87: Forecast | D87: TPS | E87: Amazon | F87: TPS Plant Foods | G87: Arborvitae Tree Fertilizer | H87: 8oz | I87: 0 | J87: 0 | K87: ARBORVITAE8OZ-FBA-UPC-1123 | L87: B0CPG28H8B | M87: F.Ultra Grow | N87: 60 | O87: 12x10x12 | P87: LBL-HV-003 | Q87: Aptar Pour | R87: Liquid | S87: 75 | T87: 0 | U87: 11.99 | V87: 0 | W87: FALSE | X87: FALSE | Y87: FALSE | Z87: FALSE | AB87: 660 | AC87: 0 | AD87: 0 | AE87: 120 | AF87: 1439 | AH87: 0 | AI87: 4254 | AJ87: 1012 | AK87: 554 | AL87: 544 | AM87: 0 | AN87: 0 | AO87: 0 | AP87: 0 | AQ87: 0 | AR87: 0 | AW87: 0 | AX87: 0 | AY87: 37 | AZ87: 66 | BA87: 97 | BB87: 489 | BC87: 0 | BD87: 1 | BE87: 1258 | BF87: 2133 | BG87: 1127 | BJ87: 209 | BK87: 4254 | BL87: Current | BM87: https://drive.google.com/open?id=1RM_9CilV1WLruR1gTHg0geQiPlsdX5Ly&usp=drive_fs | BN87: 5" x 8" | BP87: 0 | BQ87: Established | BR87: 3570 | BT87: 12134 | BU87: 0 | BV87: 77 | BW87: 45902 | BX87: 660 | BY87: 994 | BZ87: 18 | CA87: 0 | CB87: 0 | CC87: 0 | CD87: 0 | CE87: 0 | CJ87: 45352 | CK87: 23 | CL87: No | CM87: Established | CN87: Garden | CO87: Seasonal - Tree | CP87: 611 | CQ87: 0 | CR87: 90 | CS87: 1564 | CT87: 91.99 | CU87: 246 | CV87: 0
A88: Forecast | D88: TPS | E88: Walmart | F88: TPS Plant Foods | G88: Arborvitae Tree Fertilizer | H88: 8oz | I88: 0 | J88: 0 | K88: TPS-WM-ARBORVITAE-8OZ | L88: 18104257056 | M88: F.Ultra Grow | N88: 60 | O88: 12x10x12 | P88: LBL-HV-003 | Q88: Aptar Pour | R88: Liquid | S88: 75 | T88: 0 | V88: 0 | W88: FALSE | X88: FALSE | Y88: FALSE | Z88: FALSE | AB88: 0 | AC88: 0 | AD88: #VALUE! | AE88: No Sales | AF88: 0 | AH88: 0 | AI88: 0 | AJ88: 0 | AK88: NEW PRODUCT | AL88: NEW PRODUCT | AN88: 0 | AO88: 0 | AP88: 0 | AQ88: 0 | AR88: 0 | AW88: 0 | AX88: 0 | AY88: 0 | AZ88: 0 | BA88: 0 | BB88: 0 | BC88: 0 | BD88: 0 | BE88: 0 | BF88: 0 | BG88: 0 | BK88: 0 | BL88: Current | BM88: https://drive.google.com/open?id=1RM_9CilV1WLruR1gTHg0geQiPlsdX5Ly&usp=drive_fs | BN88: 5" x 8" | BP88: 0 | BR88: NEW PRODUCT | BT88: 0 | BU88: 0 | BV88: 0 | BW88: 46000 | BX88: 180 | BY88: 0 | BZ88: 0 | CA88: 0 | CB88: 0 | CC88: 0 | CD88: 0 | CE88: 0 | CH88: 810151950716 | CI88: Arborvitae Tree Fertilizer for All Arborvitaes, Evergreen Shrubs and Thuja Trees, Liquid Plant Food 8 oz (250mL) | CJ88: 45352 | CK88: 23 | CL88: No | CM88: Established | CN88: Garden | CO88: Seasonal - Tree | CP88: 0 | CQ88: 0 | CR88: No Sales | CS88: 0 | CT88: 91.99 | CU88: 0 | CV88: 0
A89: Forecast | D89: TPS | E89: Walmart | F89: TPS Plant Foods | G89: Arborvitae Tree Fertilizer | H89: Quart | I89: 0 | J89: 0 | K89: TPS-WM-ARBORVITAE-QUART | L89: 18104807952 | M89: F.Ultra Grow | N89: 12 | O89: 13x13x10 | P89: LBL-HV-036 | Q89: Aptar Pour | R89: Liquid | S89: 75 | T89: 0 | V89: 0 | W89: FALSE | X89: FALSE | Y89: FALSE | Z89: FALSE | AB89: 0 | AC89: 0 | AD89: #VALUE! | AE89: No Sales | AF89: 0 | AH89: 0 | AI89: 0 | AJ89: 0 | AK89: NEW PRODUCT | AL89: NEW PRODUCT | AN89: 0 | AO89: 0 | AP89: 0 | AQ89: 0 | AR89: 0 | AW89: 0 | AX89: 0 | AY89: 0 | AZ89: 0 | BA89: 0 | BB89: 0 | BC89: 0 | BD89: 0 | BE89: 0 | BF89: 0 | BG89: 0 | BK89: 0 | BL89: Current | BM89: https://drive.google.com/open?id=1RM_9CilV1WLruR1gTHg0geQiPlsdX5Ly&usp=drive_fs | BN89: 5" x 8" | BP89: 0 | BR89: NEW PRODUCT | BT89: 0 | BU89: 0 | BV89: 0 | BW89: 46000 | BX89: 96 | BY89: 0 | BZ89: 0 | CA89: 0 | CB89: 0 | CC89: 0 | CD89: 0 | CE89: 0 | CH89: 810151950723 | CI89: Arborvitae Tree Fertilizer for All Arborvitaes, Evergreen Shrubs and Thuja Trees, Liquid Plant Food, 32 oz (1 Quart) | CJ89: 45352 | CK89: 23 | CL89: No | CM89: Established | CN89: Garden | CO89: Seasonal - Tree | CP89: 0 | CQ89: 0 | CR89: No Sales | CS89: 0 | CT89: 91.99 | CU89: 0 | CV89: 0
A90: Forecast | C90: 46039 | D90: TPS | E90: Amazon | F90: TPS Plant Foods | G90: Aspen Tree Fertilizer | H90: 8oz | I90: 0 | J90: 0 | K90: TPS-ASPENTREE-8OZ | L90: B0DPKJ5BM5 | M90: F.Ultra Grow | N90: 60 | O90: 12x10x12 | P90: LBL-PLANT-023 | Q90: Aptar Pour | R90: Liquid | S90: 75 | T90: 0 | U90: 11.99 | V90: 0 | W90: FALSE | X90: FALSE | Y90: FALSE | Z90: FALSE | AB90: 0 | AC90: 0 | AD90: 0 | AE90: No Sales | AF90: 0 | AH90: 0 | AI90: 1584 | AJ90: 125 | AK90: 10500 | AL90: 5460 | AM90: 1 | AN90: 0 | AO90: 0 | AP90: 0 | AQ90: 0 | AR90: 0 | AW90: 0 | AX90: 0 | AY90: 0 | AZ90: 0 | BA90: 2 | BB90: 15 | BC90: 0 | BD90: 0 | BE90: 0 | BF90: 0 | BG90: 0 | BJ90: 1 | BK90: 1584 | BL90: Current | BM90: https://drive.google.com/drive/folders/1QLB5pXbjflYvZjDhrMRsqSrciaZmGevH?usp=drive_link | BN90: 5" x 8" | BP90: 0 | BQ90: Established | BR90: 68356 | BT90: 1499 | BU90: 0 | BV90: 91 | BW90: 46051 | BX90: 360 | BY90: 65 | BZ90: 0 | CA90: 0 | CB90: 60 | CC90: 0 | CD90: 0 | CE90: 0 | CJ90: 45658 | CK90: 13 | CL90: No | CM90: Emerging | CN90: Garden | CO90: Seasonal | CP90: 0 | CQ90: 0 | CR90: No Sales | CS90: -100 | CT90: 66.7 | CU90: 0 | CV90: 0
A91: Forecast | C91: 46039 | D91: TPS | E91: Amazon | F91: TPS Plant Foods | G91: Aspen Tree Fertilizer | H91: 1 Gallon | I91: 0 | J91: 0 | K91: TPS-ASPENTREE-1GAL | L91: B0DPKK517W | M91: F.Ultra Grow | N91: 4 | O91: 13x13x13 | P91: LBL-PLANT-502 | Q91: Berry Unvented | R91: Liquid | S91: 75 | T91: 0 | U91: 49.99 | V91: 0 | W91: FALSE | X91: FALSE | Y91: FALSE | Z91: FALSE | AB91: 0 | AC91: 0 | AD91: 0 | AE91: 4 | AF91: 200 | AH91: 0 | AI91: 435 | AJ91: 73 | AK91: 4906 | AL91: 1814 | AM91: 0 | AN91: 0 | AO91: 0 | AP91: 0 | AQ91: 0 | AR91: 0 | AW91: 0 | AX91: 0 | AY91: 0 | AZ91: 1 | BA91: 1 | BB91: 10 | BC91: 0 | BD91: 0 | BE91: 0 | BF91: 0 | BG91: 0 | BJ91: 1 | BK91: 435 | BL91: Current | BM91: https://drive.google.com/drive/folders/1QLB5pXbjflYvZjDhrMRsqSrciaZmGevH?usp=drive_link | BN91: 5" x 8" | BP91: 0 | BQ91: Established | BR91: 19062 | BT91: 3649 | BU91: 0 | BV91: 81 | BW91: 46049 | BX91: 44 | BY91: 27 | BZ91: 2 | CA91: 0 | CB91: 0 | CC91: 0 | CD91: 44 | CE91: 0 | CJ91: 45658 | CK91: 15 | CL91: No | CM91: Emerging | CN91: Garden | CO91: Seasonal | CP91: 5 | CQ91: 0 | CR91: 2 | CS91: -56 | CT91: 66.7 | CU91: 0 | CV91: 0
A92: Forecast | C92: 46039 | D92: TPS | E92: Amazon | F92: TPS Plant Foods | G92: Aspen Tree Fertilizer | H92: Quart | I92: 0 | J92: 0 | K92: TPS-ASPENTREE-QUART | L92: B0DPKKP6DB | M92: F.Ultra Grow | N92: 12 | O92: 13x13x10 | P92: LBL-PLANT-482 | Q92: Aptar Pour | R92: Liquid | S92: 75 | T92: 0 | U92: 24.99 | V92: 0 | W92: FALSE | X92: FALSE | Y92: FALSE | Z92: Loaded | AA92: shiner added to production | AB92: 12 | AC92: 0 | AD92: 0 | AE92: 0 | AF92: 0 | AH92: 0 | AI92: 722 | AJ92: 216 | AK92: 14515 | AL92: 13574 | AM92: 0 | AN92: 0 | AO92: 0 | AP92: 0 | AQ92: 0 | AR92: 0 | AW92: 0 | AX92: 0 | AY92: 0 | AZ92: 1 | BA92: 1 | BB92: 5 | BC92: 0 | BD92: 0 | BE92: 0 | BF92: 0 | BJ92: 1 | BK92: 722 | BN92: 5" x 8" | BP92: 0 | BQ92: Established | BR92: 51164 | BT92: 5398 | BU92: 0 | BV92: 0 | BW92: 45896 | BX92: 120 | BY92: 202 | BZ92: 12 | CA92: 0 | CB92: 2 | CC92: 0 | CD92: 0 | CE92: 0 | CJ92: 45658 | CK92: 13 | CL92: No | CM92: Emerging | CN92: Garden | CO92: Seasonal | CP92: 3 | CR92: -216 | CS92: 0 | CT92: 66.7 | CU92: 0 | CV92: 0
A93: Forecast | C93: 46096 | D93: The Perfect Shine | E93: Amazon | F93: WAX-X | G93: auto glass cleaner | H93: 16oz | M93: F.QuickClean | N93: 28 | R93: Liquid | T93: 0 | W93: FALSE | X93: FALSE | Y93: FALSE | AC93: 0 | AD93: #VALUE! | AE93: No Sales | AK93: NEW PRODUCT | AL93: NEW PRODUCT | AO93: 0 | AW93: 0 | AX93: 0 | AY93: 0 | BA93: 0 | BJ93: 0 | BL93: Current | BP93: 0 | BQ93: Established | BR93: NEW PRODUCT | BV93: 0 | BY93: 0 | BZ93: 0 | CA93: 0 | CD93: 0 | CE93: 0 | CR93: No Sales | CT93: #N/A
A94: Forecast | C94: 46039 | D94: TPS | E94: Amazon | F94: TPS Plant Foods | G94: Avocado Tree Fertilizer | H94: 8oz | I94: 0 | J94: 0 | K94: TPS-AVOCADOTREE-8OZ | L94: B0DPKKMC57 | M94: F.Ultra Grow | N94: 60 | O94: 12x10x12 | P94: LBL-PLANT-026 | Q94: Aptar Pour | R94: Liquid | S94: 75 | T94: 0 | U94: 11.99 | V94: 0 | W94: FALSE | X94: FALSE | Y94: FALSE | Z94: FALSE | AB94: 660 | AC94: 0 | AD94: 0 | AE94: 240 | AF94: 2878 | AH94: 0 | AI94: 908 | AJ94: 1096 | AK94: 296 | AL94: 65 | AM94: 0 | AN94: 0 | AO94: 0 | AP94: 0 | AQ94: 0 | AR94: 0 | AW94: 0 | AX94: 0 | AY94: 93 | AZ94: 123 | BA94: 159 | BB94: 501 | BC94: 0 | BD94: 0 | BE94: 0 | BF94: 0 | BG94: 2 | BJ94: 455 | BK94: 908 | BL94: Current | BM94: https://drive.google.com/drive/folders/16NQOomsqWDcexvoCkO85Fa_YfGA-WBeu?usp=drive_link | BN94: 5" x 8" | BP94: 0 | BQ94: Established | BR94: 971 | BT94: 13141 | BU94: 0 | BV94: 35 | BW94: 46038 | BX94: 780 | BY94: 240 | BZ94: 16 | CA94: 0 | CB94: 0 | CC94: 60 | CD94: 780 | CE94: 0 | CJ94: 45658 | CK94: 13 | CL94: No | CM94: Emerging | CN94: Garden | CO94: Seasonal | CP94: 615 | CQ94: 0 | CR94: 189 | CS94: -244 | CT94: 66.7 | CU94: 0 | CV94: 0
A95: Forecast | C95: 46039 | D95: TPS | E95: Amazon | F95: TPS Plant Foods | G95: Avocado Tree Fertilizer | H95: Quart | I95: 0 | J95: 0 | K95: TPS-AVOCADOTREE-QUART | L95: B0DPKJN89B | M95: F.Ultra Grow | N95: 12 | O95: 13x10x10 | P95: LBL-PLANT-250 | Q95: Aptar Pour | R95: Liquid | S95: 75 | T95: 0 | U95: 24.97 | V95: 0 | W95: FALSE | X95: FALSE | Y95: FALSE | Z95: FALSE | AB95: 0 | AC95: 0 | AD95: 0 | AE95: 48 | AF95: 1199 | AH95: 0 | AI95: 848 | AJ95: 119 | AK95: 220 | AL95: 129 | AM95: 4 | AN95: 0 | AO95: 0 | AP95: 0 | AQ95: 0 | AR95: 0 | AW95: 0 | AX95: 0 | AY95: 13 | AZ95: 18 | BA95: 25 | BB95: 60 | BC95: 0 | BD95: 0 | BE95: 0 | BF95: 0 | BG95: 2 | BJ95: 65 | BK95: 848 | BL95: Current | BM95: https://drive.google.com/drive/folders/16NQOomsqWDcexvoCkO85Fa_YfGA-WBeu?usp=drive_link | BN95: 5" x 8" | BP95: 0 | BQ95: Established | BR95: 3452 | BT95: 2971 | BU95: 0 | BV95: 67 | BW95: 45757 | BX95: 360 | BY95: 70 | BZ95: 1 | CA95: 0 | CB95: 48 | CC95: 0 | CD95: 0 | CE95: 0 | CJ95: 45658 | CK95: 15 | CL95: No | CM95: Emerging | CN95: Garden | CO95: Seasonal | CP95: 30 | CQ95: 0 | CR95: 40 | CS95: -17 | CT95: 66.7 | CU95: 0 | CV95: 0
A96: Forecast | C96: 46039 | D96: TPS | E96: Amazon | F96: TPS Plant Foods | G96: Avocado Tree Fertilizer | H96: 1 Gallon | I96: 0 | J96: 0 | K96: TPS-AVOCADOTREE-1GAL | L96: B0DPKKDR8G | M96: F.Ultra Grow | N96: 4 | O96: 13x13x13 | P96: LBL-PLANT-503 | Q96: Berry Unvented | R96: Liquid | S96: 75 | T96: 0 | U96: 49.99 | V96: 0 | W96: FALSE | X96: FALSE | Y96: FALSE | Z96: FALSE | AB96: 0 | AC96: 0 | AD96: 0 | AE96: 16 | AF96: 800 | AH96: 0 | AI96: 286 | AJ96: 45 | AK96: 145 | AL96: 68 | AM96: 1 | AN96: 0 | AO96: 0 | AP96: 0 | AQ96: 0 | AR96: 0 | AW96: 0 | AX96: 0 | AY96: 8 | AZ96: 10 | BA96: 13 | BB96: 29 | BC96: 0 | BD96: 0 | BE96: 0 | BF96: 0 | BG96: 0 | BJ96: 38 | BK96: 286 | BL96: Current | BM96: https://drive.google.com/drive/folders/16NQOomsqWDcexvoCkO85Fa_YfGA-WBeu?usp=drive_link | BN96: 5" x 8" | BP96: 0 | BQ96: Established | BR96: 2231 | BT96: 2250 | BU96: 0 | BV96: 93 | BW96: 45930 | BX96: 72 | BY96: 21 | BZ96: 20 | CA96: 0 | CB96: 4 | CC96: 0 | CD96: 0 | CE96: 0 | CJ96: 45658 | CK96: 15 | CL96: No | CM96: Emerging | CN96: Garden | CO96: Seasonal | CP96: 45 | CQ96: 0 | CR96: 15 | CS96: 4 | CT96: 66.7 | CU96: 0 | CV96: 0
A97: Forecast | D97: TPS | E97: Amazon | F97: TPS Plant Foods | G97: Azalea Fertilizer | H97: 8oz | I97: 0 | J97: 0 | K97: AZALEA8OZ-FBA-UPC-0523 | L97: B0C73R3GKS | M97: F.Ultra Bloom | N97: 60 | O97: 12x10x12 | P97: LBL-PLANT-027 | Q97: Aptar Pour | R97: Liquid | S97: 75 | T97: 0 | U97: 11.99 | V97: 0 | W97: FALSE | X97: FALSE | Y97: FALSE | Z97: FALSE | AB97: 0 | AC97: 0 | AD97: 0 | AE97: 60 | AF97: 719 | AH97: 0 | AI97: 1939 | AJ97: 654 | AK97: 1787 | AL97: 626 | AM97: 7 | AN97: 0 | AO97: 0 | AP97: 0 | AQ97: 0 | AR97: 0 | AW97: 0 | AX97: 0 | AY97: 8 | AZ97: 13 | BA97: 18 | BB97: 60 | BC97: 81 | BD97: 72 | BE97: 357 | BF97: 229 | BG97: 71 | BJ97: 43 | BK97: 1939 | BL97: Current | BM97: https://drive.google.com/open?id=1UDk0T2wIXdpkLXUiGrPDMg3XRtGCrijr&usp=drive_fs | BN97: 5" x 8" | BP97: 0 | BQ97: Established | BR97: 11275 | BT97: 7841 | BU97: 0 | BV97: 71 | BW97: 45785 | BX97: 1080 | BY97: 229 | BZ97: 5 | CA97: 0 | CB97: 420 | CC97: 0 | CD97: 0 | CE97: 0 | CJ97: 45108 | CK97: 31 | CL97: No | CM97: Established | CN97: Garden | CO97: Seasonal | CP97: 0 | CQ97: 0 | CR97: 29 | CS97: -242 | CT97: 66.7 | CU97: 0 | CV97: 0
A98: Forecast | D98: TPS | E98: Amazon | F98: TPS Plant Foods | G98: Azalea Fertilizer | H98: Quart | I98: 0 | J98: 0 | K98: AZALEA1Q-FBA-UPC-0523 | L98: B0C73RWH6C | M98: F.Ultra Bloom | N98: 12 | O98: 13x13x10 | P98: LBL-PLANT-251 | Q98: Aptar Pour | R98: Liquid | S98: 75 | T98: 0 | U98: 24.99 | V98: 0 | W98: FALSE | X98: FALSE | Y98: FALSE | Z98: FALSE | AB98: 96 | AC98: 0 | AD98: 0 | AE98: 24 | AF98: 600 | AH98: 0 | AI98: 287 | AJ98: 47 | AK98: 376 | AL98: 344 | AM98: 0 | AN98: 0 | AO98: 0 | AP98: 0 | AQ98: 0 | AR98: 0 | AW98: 0 | AX98: 0 | AY98: 2 | AZ98: 6 | BA98: 6 | BB98: 26 | BC98: 67 | BD98: 28 | BE98: 116 | BF98: 43 | BG98: 12 | BJ98: 14 | BK98: 287 | BL98: Current | BM98: https://drive.google.com/open?id=1UDk0T2wIXdpkLXUiGrPDMg3XRtGCrijr&usp=drive_fs | BN98: 5" x 8" | BP98: 0 | BQ98: Established | BR98: 3230 | BT98: 1175 | BU98: 0 | BV98: 58 | BW98: 46052 | BX98: 180 | BY98: 43 | BZ98: 4 | CA98: 0 | CB98: 0 | CC98: 0 | CD98: 0 | CE98: 0 | CJ98: 45108 | CK98: 31 | CL98: No | CM98: Established | CN98: Garden | CO98: Seasonal | CP98: 86 | CQ98: 0 | CR98: 13 | CS98: 104 | CT98: 66.7 | CU98: 69 | CV98: 0
A99: Forecast | D99: TPS | E99: Amazon | F99: TPS Plant Foods | G99: Azalea Fertilizer | H99: 1 Gallon | I99: 0 | J99: 0 | K99: AZALEA1G-FBA-UPC-0523 | L99: B0C73SVVDB | M99: F.Ultra Bloom | N99: 4 | O99: 13x13x13 | P99: LBL-PLANT-504 | Q99: Berry Unvented | R99: Liquid | S99: 75 | T99: 0 | U99: 49.99 | V99: 0 | W99: FALSE | X99: FALSE | Y99: FALSE | Z99: FALSE | AB99: 0 | AC99: 0 | AD99: #DIV/0! | AE99: No Sales | AF99: 0 | AH99: 0 | AI99: 193 | AJ99: 39 | AK99: NO SALES | AL99: #DIV/0! | AM99: 2 | AN99: #DIV/0! | AO99: 0 | AP99: 0 | AQ99: 0 | AR99: 0 | AW99: 0 | AX99: 0 | AY99: 0 | AZ99: 0 | BA99: 0 | BB99: 2 | BC99: 6 | BD99: 2 | BE99: 12 | BF99: 9 | BG99: 3 | BJ99: 0 | BK99: 193 | BL99: Current | BM99: https://drive.google.com/open?id=1UDk0T2wIXdpkLXUiGrPDMg3XRtGCrijr&usp=drive_fs | BN99: 5" x 8" | BP99: 0 | BQ99: Established | BR99: 69622 | BT99: 1950 | BU99: 0 | BV99: 0 | BW99: 45860 | BX99: 40 | BY99: 23 | BZ99: 8 | CA99: 0 | CB99: 8 | CC99: 0 | CD99: 0 | CE99: 0 | CJ99: 45108 | CK99: 31 | CL99: No | CM99: Established | CN99: Garden | CO99: Seasonal | CP99: 0 | CQ99: 0 | CR99: No Sales | CS99: -28 | CT99: 66.7 | CU99: 0 | CV99: 0
A100: Forecast | C100: 46067 | D100: Total Pest Supply | E100: Amazon | F100: Ms. Pixie's | G100: Baby & Toddler Mosquito Repellent | H100: 6oz Spray Bottle | I100: 0 | J100: 0 | K100: PIX-BABYMOSQUITOREP-6OZ | L100: B0F2MDL7P4 | M100: F.Kids Safe Repel | N100: 64 | O100: 14x14x8 | P100: LBL-PEST-064 | Q100: 6oz Sprayer Top | R100: Spray | S100: 75 | T100: 0 | U100: 14.99 | V100: 0 | W100: FALSE | X100: FALSE | Y100: FALSE | Z100: FALSE | AB100: 192 | AC100: 0 | AD100: 0 | AE100: 128 | AF100: 1919 | AH100: 0 | AI100: 4533 | AJ100: 461 | AK100: 478 | AL100: 440 | AM100: 0 | AN100: 0 | AO100: 0 | AP100: 0 | AQ100: 0 | AR100: 0 | AW100: 0 | AX100: 0 | AY100: 21 | AZ100: 34 | BA100: 48 | BB100: 201 | BC100: 0 | BD100: 0 | BE100: 0 | BF100: 0 | BG100: 0 | BH100: Complete | BJ100: 113 | BK100: 4533 | BL100: Current | BM100: https://drive.google.com/drive/folders/1W9RXD5Yp6ZqfR47U2sBPReaK4OdRNmjb | BN100: 5.375" x 4.5" | BO100: 45839 | BP100: 0 | BQ100: 0 | BR100: 7398 | BT100: 6910 | BU100: 0 | BV100: 214 | BW100: 45981 | BY100: 424 | BZ100: 37 | CA100: 0 | CB100: 0 | CC100: 0 | CD100: 0 | CE100: 0 | CJ100: 45715 | CK100: 11 | CM100: Emerging | CO100: Seasonal | CP100: 170 | CR100: 75.595004 | CS100: -119.3 | CT100: 66.7 | CU100: 0 | CV100: 0
...
